Workbook
Name beed: Table1[[#All],[Unit Number]:[NO. OF BEDROOMS]]
Name Slicer_AREA_CATEGORY: #N/A
Name Slicer_AREA_CATEGORY1: #N/A
Name Slicer_AREA_CATEGORY11: #N/A
Name Slicer_AREA_CATEGORY111: #N/A
Name Slicer_AREA_CATEGORY1111: #N/A
Name Slicer_AREA_CATEGORY11111: #N/A
Name Slicer_AREA_CATEGORY111111: #N/A
Name Slicer_AREA_CATEGORY1111111: #N/A
Name Slicer_AREA_CATEGORY11111111: #N/A
Name Slicer_AREA_CATEGORY111111111: #N/A
Name Slicer_AREA_CATEGORY1111111111: #N/A
Name Slicer_AREA_CATEGORY11111111111: #N/A
Name Slicer_AREA_CATEGORY111111111111: #N/A
Name Slicer_BLD._TYPE: #N/A
Name Slicer_BLD._TYPE1: #N/A
Name Slicer_BLD._TYPE11: #N/A
Name Slicer_BLD_No.: #N/A
Name Slicer_BLD_No.1: #N/A
Name Slicer_BLD_No.11: #N/A
Name Slicer_CONSTRUCTION_PHASE: #N/A
Name Slicer_CONSTRUCTION_PHASE1: #N/A
Name Slicer_CONSTRUCTION_PHASE11: #N/A
Name Slicer_PREMIUM_CATEGORY: #N/A
Name Slicer_PREMIUM_CATEGORY1: #N/A
Name Slicer_PREMIUM_CATEGORY11: #N/A
Name Slicer_PREMIUM_CATEGORY2: #N/A
Name Slicer_PREMIUM_CATEGORY21: #N/A
Name Slicer_PREMIUM_CATEGORY211: #N/A
Name Slicer_PREMIUM_CATEGORY2111: #N/A
Name Slicer_PREMIUM_CATEGORY21111: #N/A
Name Slicer_PREMIUM_CATEGORY211111: #N/A
Name Slicer_PREMIUM_CATEGORY2111111: #N/A
Name Slicer_PREMIUM_CATEGORY21111111: #N/A
Name Slicer_PREMIUM_CATEGORY211111111: #N/A
Name Slicer_PREMIUM_CATEGORY2111111111: #N/A
Name Slicer_PREMIUM_CATEGORY21111111111: #N/A
Name Slicer_PREMIUM_CATEGORY211111111111: #N/A
Name Slicer_PREMIUM_CATEGORY2111111111111: #N/A
Name Slicer_SELLING_PHASE_NAME: #N/A
Name Slicer_SELLING_PHASE_NAME1: #N/A
Name Slicer_SELLING_PHASE_NAME11: #N/A
Name Slicer_SELLING_PHASE_NAME111: #N/A
Name Slicer_SELLING_PHASE_NAME1111: #N/A
Name Slicer_SELLING_PHASE_NAME11111: #N/A
Name Slicer_SELLING_PHASE_NAME111111: #N/A
Name Slicer_SELLING_PHASE_NAME1111111: #N/A
Name Slicer_SELLING_PHASE_NAME11111111: #N/A
Name Slicer_SELLING_PHASE_NAME111111111: #N/A
Name Slicer_SELLING_PHASE_NAME1111111111: #N/A
Name Slicer_SELLING_PHASE_NAME11111111111: #N/A
Name Slicer_SELLING_PHASE_NAME111111111111: #N/A

Sheet PHASES PREM RANGE
A1: Phases | B1: Min of UNIT (BUILDING) RATE (SEMI FINISHED) | C1: Max of UNIT (BUILDING) RATE (SEMI FINISHED) | D1: Average of UNIT (BUILDING) RATE (SEMI FINISHED) | E1: Min of UNIT (BUILDING) RATE (BASIC FINISH)2 | F1: Max of UNIT (BUILDING) RATE (BASIC FINISH) | G1: Average of UNIT (BUILDING) RATE (BASIC FINISH) | H1: Min of UNIT (BUILDING) RATE (FULLY FINISH) | I1: Max of UNIT (BUILDING) RATE (FULLY FINISH) | J1: Average of UNIT (BUILDING) RATE (FULLY FINISH)
A2: R 1 | B2: 43875 | C2: 46225 | D2: 45023.316 | E2: 48375 | F2: 50725 | G2: 49523.316 | H2: 51375 | I2: 53725 | J2: 52523.316
A3: R 2 | B3: 45407.5 | C3: 47457.5 | D3: 46356.091 | E3: 49907.5 | F3: 51957.5 | G3: 50856.091 | H3: 52907.5 | I3: 54957.5 | J3: 53856.091
A4: R 3 | B4: 46331.25 | C4: 48667.5 | D4: 47460.508 | E4: 50831.25 | F4: 53167.5 | G4: 51960.508 | H4: 53831.25 | I4: 56167.5 | J4: 54960.508
A5: R 4 | B5: 47541.875 | C5: 49906.875 | D5: 48749.631 | E5: 52041.875 | F5: 54406.875 | G5: 53249.631 | H5: 55041.875 | I5: 57406.875 | J5: 56249.631
A6: R 5 | B6: 48922.5 | C6: 51122.5 | D6: 49988.689 | E6: 53422.5 | F6: 55622.5 | G6: 54488.689 | H6: 56422.5 | I6: 58622.5 | J6: 57488.689
A7: R 6 | B7: 50758.5 | C7: 53038.5 | D7: 51816.325 | E7: 55258.5 | F7: 57538.5 | G7: 56316.325 | H7: 58258.5 | I7: 60538.5 | J7: 59316.325
A8: R 7 | B8: 52392 | C8: 55047 | D8: 53655.315 | E8: 56892 | F8: 59547 | G8: 58155.315 | H8: 59892 | I8: 62547 | J8: 61155.315
A9: R 8 | B9: 54442.5 | C9: 57096 | D9: 55649.898 | E9: 58942.5 | F9: 61596 | G9: 60149.898 | H9: 61942.5 | I9: 64596 | J9: 63149.898
A10: R 9 | B10: 56322 | C10: 59062.5 | D10: 57551.386 | E10: 60822 | F10: 63562.5 | G10: 62051.386 | H10: 63822 | I10: 66562.5 | J10: 65051.386
A11: R 10 | B11: 59070 | C11: 61974 | D11: 60372.125 | E11: 63570 | F11: 66474 | G11: 64872.125 | H11: 66570 | I11: 69474 | J11: 67872.125
A12: R 11 | B12: 61858.5 | C12: 64860 | D12: 63195.786 | E12: 66358.5 | F12: 69360 | G12: 67695.786 | H12: 69358.5 | I12: 72360 | J12: 70695.786
A13: R 12 | B13: 64670 | C13: 68621.25 | D13: 66504.351 | E13: 69170 | F13: 73121.25 | G13: 71004.351 | H13: 72170 | I13: 76121.25 | J13: 74004.351
... A15: Grand Total | B15: 43875 | C15: 80815 | D15: 54113.272 | E15: 48375 | F15: 85315 | G15: 58613.272 | H15: 51375 | I15: 88315 | J15: 61613.272

Sheet DASHBOARD (7)
A1: Row Labels | B1: Count of Unit Selling Area | C1: Count of Unit Selling Area2
A2: 1 BEDROOM (STUDIO) | B2: 68 | C2: 0.079254079
A3: 2 BEDROOM | B3: 176 | C3: 0.20512821
A4: 3 BEDROOM | B4: 526 | C4: 0.61305361
A5: 3 BEDROOM + LIVING | B5: 70 | C5: 0.081585082
A6: 3 BEDROOM + LIVING (DUPLEX) | B6: 18 | C6: 0.020979021
A7: Grand Total | B7: 858 | C7: 1

Sheet product mix dash
A1: Unit Area | B1: Count of Unit Selling Area
A2: 63 | B2: 16
A3: 84 | B3: 12
A4: 106 | B4: 12
A5: 108 | B5: 20
A6: 110 | B6: 26
A7: 112 | B7: 12
A8: 116 | B8: 19
A9: 117 | B9: 19
A10: 119 | B10: 15
A11: 121 | B11: 12
A12: 153 | B12: 24
A13: 155 | B13: 88
... A26: 228 | B26: 24
A27: Grand Total | B27: 694

Sheet premium cat. per phase dash
A1: SELLING PHASE NAME | B1: R 1 | D1: SELLING PHASE NAME | E1: R 7
A3: Premium Category | B3: Count of Unit Selling Area | D3: Premium Category | E3: Count of Unit Selling Area
A4: A | B4: 33 | D4: A | E4: 16
A5: B | B5: 49 | D5: B | E5: 20
A6: C | B6: 62 | D6: C | E6: 30
A7: Grand Total | B7: 144 | D7: Grand Total | E7: 66
A9: SELLING PHASE NAME | B9: R 2 | D9: SELLING PHASE NAME | E9: R 8
A11: Premium Category | B11: Count of Unit Selling Area | D11: Premium Category | E11: Count of Unit Selling Area
A12: A | B12: 14 | D12: A | E12: 25
A13: B | B13: 19 | D13: B | E13: 27
A14: C | B14: 22 | D14: C | E14: 39
A15: Grand Total | B15: 55 | D15: Grand Total | E15: 91
A16: SELLING PHASE NAME | B16: R 3
D17: SELLING PHASE NAME | E17: R 9
A18: Premium Category | B18: Count of Unit Selling Area
A19: A | B19: 16 | D19: Premium Category | E19: Count of Unit Selling Area
A20: B | B20: 16 | D20: A | E20: 17
A21: C | B21: 30 | D21: B | E21: 20
A22: Grand Total | B22: 62 | D22: C | E22: 27
D23: Grand Total | E23: 64
A24: SELLING PHASE NAME | B24: R 4
D25: SELLING PHASE NAME | E25: R 10
A26: Premium Category | B26: Count of Unit Selling Area
A27: A | B27: 21 | D27: Premium Category | E27: Count of Unit Selling Area
A28: B | B28: 30 | D28: A | E28: 6
A29: C | B29: 37 | D29: B | E29: 8
A30: Grand Total | B30: 88 | D30: C | E30: 10
D31: Grand Total | E31: 24
A32: SELLING PHASE NAME | B32: R 5
D33: SELLING PHASE NAME | E33: R 11
A34: Premium Category | B34: Count of Unit Selling Area
A35: A | B35: 17 | D35: Premium Category | E35: Count of Unit Selling Area
A36: B | B36: 19 | D36: A | E36: 6
A37: C | B37: 25 | D37: B | E37: 6
A38: Grand Total | B38: 61 | D38: C | E38: 9
D39: Grand Total | E39: 21
A40: SELLING PHASE NAME | B40: R 6
D41: SELLING PHASE NAME | E41: R 12
A42: Premium Category | B42: Count of Unit Selling Area
A43: A | B43: 13 | D43: Premium Category | E43: Count of Unit Selling Area
A44: B | B44: 18 | D44: A | E44: 20
A45: C | B45: 23 | D45: B | E45: 21
A46: Grand Total | B46: 54 | D46: C | E46: 31
D47: Grand Total | E47: 72

Sheet PV calculation
F5: UNIT PRICING PAYMENT
F6: DP % | G6: 0.05 | H6: 0.1 | P6: =P9/J7 -> 0.88888889
G7: Unit (2) | H7: Unit (2) | J7: =90/H16 -> 3.2142857 | K7: =12*J7 -> 38.571429 | M7: =50/16 -> 3.125 | P7: =P6*210000 -> 186666.67
F8: Unit area | G8: 155 | H8: 155 | J8: 2.5 | K8: =J8*12 -> 30
F9: Unit price/m2 | G9: 41530 | H9: 41530 | K9: 10 | N9: =2.5*28 -> 70 | P9: =80/28 -> 2.8571429
F10: Total Unit Price | G10: =G9*G8 -> 6437150 | H10: =H9*H8 -> 6437150 | K10: 10
F11: DP Value | G11: =G10*G6 -> 321857.5 | H11: =H10*H6 -> 643715
F12: No. of installments years | G12: 6 | H12: 7
F13: Installment value | G13: =(G10-G11)/(G12*G15) -> 254803.85 | H13: =(H10-H11)/(H12*H15) -> 206908.39
D14: =G13*G16 -> 6115292.5 | F14: Intrest Rate (yearly) | G14: 0.13 | H14: 0.13
F15: No. of Periods | G15: 4 | H15: 4
F16: Total no. of Periods | G16: =G12*G15 -> 24 | H16: =H12*H15 -> 28
F17: Intrest Rate (Period) | G17: =G14/G15 -> 0.0325 | H17: =H14/H15 -> 0.0325
F18: Present Value (PV) | G18: =(((1-(1+G17)^(-G16))/(G17))*(G13))+(G11) -> 4523151 | H18: =(((1-(1+H17)^(-H16))/(H17))*(H13))+(H11) -> 4410128.8
F19: Discount Rate (%) | G19: =1-(G18/G10) -> 0.2973364 | H19: =1-(H18/H10) -> 0.3148942
F20: Present Value (PV)/M2 | G20: =G18/G8 -> 29181.619 | H20: =H18/H8 -> 28452.444
F22: FINISHING PAYMENT (FULLY)
F23: DP % | G23: 0.1 | H23: 0.05
G24: Unit (1) | H24: Unit (1)
F25: Unit area | G25: 155 | H25: 155
F26: Unit price | G26: 7500 | H26: 7500
F27: Total Unit Price | G27: =G26*G25 -> 1162500 | H27: =H26*H25 -> 1162500
F28: DP Value | G28: =G27*G23 -> 116250 | H28: =H27*H23 -> 58125
F29: No. of installments years | G29: 7 | H29: 6
F30: Installment value | G30: =(G27-G28)/(G29*G32) -> 37366.071 | H30: =(H27-H28)/(H29*H32) -> 46015.625
F31: Intrest Rate (yearly) | G31: 0.13 | H31: 0.13
F32: No. of Periods | G32: 4 | H32: 4
F33: Total no. of Periods | G33: =G29*G32 -> 28 | H33: =H29*H32 -> 24
F34: Intrest Rate (Period) | G34: =G31/G32 -> 0.0325 | H34: =H31/H32 -> 0.0325
F35: Present Value (PV) | G35: =(((1-(1+G34)^(-G33))/(G34))*(G30))+(G28) -> 796435.5 | H35: =(((1-(1+H34)^(-H33))/(H34))*(H30))+(H28) -> 816846.43
F36: Present Value (PV)/M2 | G36: =(G35+G28)/G25 -> 5888.2935 | H36: =(H35+H28)/H25 -> 5644.977
F39: FINISHING PAYMENT (BASIC)
F40: DP % | G40: 0.1 | H40: 0.05
G41: Unit (1) | H41: Unit (1)
F42: Unit area | G42: 155 | H42: 155
F43: Unit price | G43: 4500 | H43: 4500
F44: Total Unit Price | G44: =G43*G42 -> 697500 | H44: =H43*H42 -> 697500
F45: DP Value | G45: =G44*G40 -> 69750 | H45: =H44*H40 -> 34875
F46: No. of installments years | G46: 7 | H46: 6
F47: Installment value | G47: =(G44-G45)/(G46*G49) -> 22419.643 | H47: =(H44-H45)/(H46*H49) -> 27609.375
F48: Intrest Rate (yearly) | G48: 0.13 | H48: 0.13
F49: No. of Periods | G49: 4 | H49: 4
F50: Total no. of Periods | G50: =G46*G49 -> 28 | H50: =H46*H49 -> 24
F51: Intrest Rate (Period) | G51: =G48/G49 -> 0.0325 | H51: =H48/H49 -> 0.0325
F52: Present Value (PV) | G52: =(((1-(1+G51)^(-G50))/(G51))*(G47))+(G45) -> 477861.3 | H52: =(((1-(1+H51)^(-H50))/(H51))*(H47))+(H45) -> 490107.86
F53: Present Value (PV)/M2 | G53: =(G52+G45)/G42 -> 3532.9761 | H53: =(H52+H45)/H42 -> 3386.9862
K56: =41530+7000 -> 48530
F57: APPARTMENT & FINISHING PAYMENT (FULLY) | K57: =41530+4000 -> 45530
F58: DP % | G58: 0.25 | H58: 0.05
G59: Unit (1) | H59: Unit (1)
F60: Unit area | G60: 155 | H60: 155
F61: Unit price/M2 | G61: 39000 | H61: =K56 -> 48530
F62: Total Unit Price | G62: =G61*G60 -> 6045000 | H62: =H61*H60 -> 7522150
F63: DP Value | G63: =G62*G58 -> 1511250 | H63: =H62*H58 -> 376107.5
F64: No. of installments years | G64: 4 | H64: 6
F65: Installment value | G65: =(G62-G63)/(G64*G67) -> 283359.38 | H65: =(H62-H63)/(H64*H67) -> 297751.77
F66: Intrest Rate (yearly) | G66: 0.13 | H66: 0.13
F67: No. of Periods | G67: 4 | H67: 4
F68: Total no. of Periods | G68: =G64*G67 -> 16 | H68: =H64*H67 -> 24
F69: Intrest Rate (Period) | G69: =G66/G67 -> 0.0325 | H69: =H66/H67 -> 0.0325
F70: Present Value (PV) | G70: =(((1-(1+G69)^(-G68))/(G69))*(G65))+(G63) -> 5003472.3 | H70: =(((1-(1+H69)^(-H68))/(H69))*(H65))+(H63) -> 5285541
F71: Present Value (PV)/M2 | G71: =G70/G60 -> 32280.466 | H71: =H70/H60 -> 34100.264
F72: Discount Rate (%) | G72: =1-(G71/G61) -> 0.17229574 | H72: =1-(H71/H61) -> 0.2973364
F74: APPARTMENT & FINISHING PAYMENT (BASIC)
F75: DP % | G75: 0.1 | H75: 0.05
G76: Unit (1) | H76: Unit (1)
F77: Unit area | G77: 155 | H77: 155
F78: Unit price/M2 | G78: =K57 -> 45530 | H78: =K57 -> 45530
F79: Total Unit Price | G79: =G78*G77 -> 7057150 | H79: =H78*H77 -> 7057150
F80: DP Value | G80: =G79*G75 -> 705715 | H80: =H79*H75 -> 352857.5
F81: No. of installments years | G81: 7 | H81: 6
F82: Installment value | G82: =(G79-G80)/(G81*G84) -> 226836.96 | H82: =(H79-H80)/(H81*H84) -> 279345.52
F83: Intrest Rate (yearly) | G83: 0.13 | H83: 0.13
F84: No. of Periods | G84: 4 | H84: 4
F85: Total no. of Periods | G85: =G81*G84 -> 28 | H85: =H81*H84 -> 24
F86: Intrest Rate (Period) | G86: =G83/G84 -> 0.0325 | H86: =H83/H84 -> 0.0325
F87: Present Value (PV) | G87: =(((1-(1+G86)^(-G85))/(G86))*(G82))+(G80) -> 4834894.4 | H87: =(((1-(1+H86)^(-H85))/(H86))*(H82))+(H80) -> 4958802.4
F88: Present Value (PV)/M2 | G88: =G87/G77 -> 31192.867 | H88: =H87/H77 -> 31992.274
F89: Discount Rate (%) | G89: =1-(G88/G78) -> 0.3148942 | H89: =1-(H88/H78) -> 0.2973364
F91: APPARTMENT & FINISHING PAYMENT (FULLY) | K91: =41530+4000 -> 45530
F92: DP % | G92: 0.1 | H92: 0.05
G93: Unit (1) | H93: Unit (1)
F94: Unit area | G94: 155 | H94: 155
F95: Unit price/M2 | G95: =0.975*G61 -> 38025 | H95: =0.975*H61 -> 47316.75
F96: Total Unit Price | G96: =G95*G94 -> 5893875 | H96: =H95*H94 -> 7334096.2
F97: DP Value | G97: =G96*G92 -> 589387.5 | H97: =H96*H92 -> 366704.81
F98: No. of installments years | G98: 7 | H98: 6
F99: Installment value | G99: =(G96-G97)/(G98*G101) -> 189445.98 | H99: =(H96-H97)/(H98*H101) -> 290307.98
F100: Intrest Rate (yearly) | G100: 0.13 | H100: 0.13
F101: No. of Periods | G101: 4 | H101: 4
F102: Total no. of Periods | G102: =G98*G101 -> 28 | H102: =H98*H101 -> 24
F103: Intrest Rate (Period) | G103: =G100/G101 -> 0.0325 | H103: =H100/H101 -> 0.0325
F104: Present Value (PV) | G104: =(((1-(1+G103)^(-G102))/(G103))*(G99))+(G97) -> 4037928 | H104: =(((1-(1+H103)^(-H102))/(H103))*(H99))+(H97) -> 5153402.4
F105: Present Value (PV)/M2 | G105: =G104/G94 -> 26051.148 | H105: =H104/H94 -> 33247.758
F106: Discount Rate (%) | G106: =1-(G105/G95) -> 0.3148942 | H106: =1-(H105/H95) -> 0.2973364
F108: APPARTMENT & FINISHING PAYMENT (BASIC)
F109: DP % | G109: 0.1 | H109: 0.05
G110: Unit (1) | H110: Unit (1)
F111: Unit area | G111: 155 | H111: 155
F112: Unit price/M2 | G112: =0.975*G78 -> 44391.75 | H112: =0.975*H78 -> 44391.75
...

Sheet FINISH
B2: FULLY | G2: BASIC
B4: ITEM | C4: QUANTITY | D4: PRICE | E4: TOTAL | G4: ITEM | H4: QUANTITY | I4: PRICE | J4: TOTAL
B5: WALLS | G5: WALLS
B6: PAINT | C6: 650 | D6: 200 | E6: =D6*C6 -> 130000 | G6: PAINT | H6: 650 | I6: 100 | J6: =I6*H6 -> 65000
B7: FUTEC | C7: 90 | D7: 60 | E7: =D7*C7 -> 5400 | G7: FUTEC | H7: 0 | I7: 60 | J7: =I7*H7 -> 0
B8: PORCELAIN WALLS | C8: 135 | D8: 650 | E8: =D8*C8 -> 87750 | G8: PORCELAIN WALLS | H8: 135 | I8: 650 | J8: =I8*H8 -> 87750
B9: ITEM | C9: QUANTITY | D9: PRICE | E9: TOTAL | G9: ITEM | H9: QUANTITY | I9: PRICE | J9: TOTAL
B10: CEILLING | E10: =D10*C10 -> 0 | G10: CEILLING | J10: =I10*H10 -> 0
B11: GYPSUM | C11: 65 | D11: 336 | E11: =D11*C11 -> 21840 | G11: GYPSUM | H11: 0 | I11: 336 | J11: =I11*H11 -> 0
B12: GYPSUM COVE AND CURTIN | C12: 45 | D12: 230 | E12: =D12*C12 -> 10350 | G12: GYPSUM COVE AND CURTIN | H12: 0 | I12: 230 | J12: =I12*H12 -> 0
B13: FUTEC | C13: 40 | D13: 120 | E13: =D13*C13 -> 4800 | G13: FUTEC | H13: 0 | I13: 120 | J13: =I13*H13 -> 0
B14: ITEM | C14: QUANTITY | D14: PRICE | E14: TOTAL | G14: ITEM | H14: QUANTITY | I14: PRICE | J14: TOTAL
B15: FLOORS | E15: =D15*C15 -> 0 | G15: FLOORS | J15: =I15*H15 -> 0
B16: PORCELAIN 01 | C16: 40 | D16: 650 | E16: =D16*C16 -> 26000 | G16: PORCELAIN 01 | H16: 40 | I16: 650 | J16: =I16*H16 -> 26000
B17: PORCELAIN 02 | C17: 85 | D17: 800 | E17: =D17*C17 -> 68000 | G17: PORCELAIN 02 | H17: 85 | I17: 800 | J17: =I17*H17 -> 68000
B18: CERAMIC UNDER HDF | C18: 74 | D18: 200 | E18: =D18*C18 -> 14800 | G18: CERAMIC UNDER HDF | H18: 74 | I18: 200 | J18: =I18*H18 -> 14800
B19: HDF, SKIRT ,ACC. | C19: 74 | D19: 700 | E19: =D19*C19 -> 51800 | G19: HDF, SKIRT ,ACC. | H19: 0 | I19: 700 | J19: =I19*H19 -> 0
B20: MARBLE FLOOR FOR SHOWERS | C20: 7 | D20: 5000 | E20: =D20*C20 -> 35000 | G20: MARBLE FLOOR FOR SHOWERS | H20: 7 | I20: 5000 | J20: =I20*H20 -> 35000
B21: MARBLE THRESHOLDS | C21: 16 | D21: 500 | E21: =D21*C21 -> 8000 | G21: MARBLE THRESHOLDS | H21: 16 | I21: 500 | J21: =I21*H21 -> 8000
B22: ITEM | C22: QUANTITY | D22: PRICE | E22: TOTAL | G22: ITEM | H22: QUANTITY | I22: PRICE | J22: TOTAL
B23: BASIN WORKS | E23: =D23*C23 -> 0 | G23: BASIN WORKS | J23: =I23*H23 -> 0
B24: CHASIS (MARBLE +STEEL) | C24: 3 | D24: 5000 | E24: =D24*C24 -> 15000 | G24: CHASIS (MARBLE +STEEL) | H24: 0 | I24: 5000 | J24: =I24*H24 -> 0
B25: BASIN VANITIES | C25: 3 | D25: 6500 | E25: =D25*C25 -> 19500 | G25: BASIN VANITIES | H25: 0 | I25: 6500 | J25: =I25*H25 -> 0
B26: ITEM | C26: QUANTITY | D26: PRICE | E26: TOTAL | G26: ITEM | H26: QUANTITY | I26: PRICE | J26: TOTAL
B27: WOODEN DOORS | E27: =D27*C27 -> 0 | G27: WOODEN DOORS | J27: =I27*H27 -> 0
B28: WOODEN DOORS WITH ACC. | C28: 10 | D28: 15000 | E28: =D28*C28 -> 150000 | G28: WOODEN DOORS WITH ACC. | H28: 10 | I28: 4000 | J28: =I28*H28 -> 40000
B29: MAIN DOOR WITH ACC. | C29: 1 | D29: 30000 | E29: =D29*C29 -> 30000 | G29: MAIN DOOR WITH ACC. | H29: 1 | I29: 30000 | J29: =I29*H29 -> 30000
B30: ITEM | C30: QUANTITY | D30: PRICE | E30: TOTAL | G30: ITEM | H30: QUANTITY | I30: PRICE | J30: TOTAL
B31: MIRRORS AND GLASS PARTIONS | E31: =D31*C31 -> 0 | G31: MIRRORS AND GLASS PARTIONS | J31: =I31*H31 -> 0
B32: MIRRORS | C32: 3 | D32: 2000 | E32: =D32*C32 -> 6000 | G32: MIRRORS | H32: 0 | I32: 2000 | J32: =I32*H32 -> 0
B33: SECORITE | C33: 3 | D33: 3000 | E33: =D33*C33 -> 9000 | G33: SECORITE | H33: 3 | I33: 3000 | J33: =I33*H33 -> 9000
B34: ITEM | C34: QUANTITY | D34: PRICE | E34: TOTAL | G34: ITEM | H34: QUANTITY | I34: PRICE | J34: TOTAL
B35: ELEC WORKS AND LIGHTING FIX. | E35: =D35*C35 -> 0 | G35: ELEC WORKS AND LIGHTING FIX. | J35: =I35*H35 -> 0
B36: ELEC WORKS AND LIGHTING FIX. | C36: 1 | D36: 250000 | E36: =D36*C36 -> 250000 | G36: ELEC WORKS AND LIGHTING FIX. | H36: 1 | I36: 200000 | J36: =I36*H36 -> 200000
B37: ITEM | C37: QUANTITY | D37: PRICE | E37: TOTAL | G37: ITEM | H37: QUANTITY | I37: PRICE | J37: TOTAL
B38: AC (CHASIS, CONTROL CABLE, COPPER AND PLUM.) | E38: =D38*C38 -> 0 | G38: AC (CHASIS, CONTROL CABLE, COPPER AND PLUM.) | J38: =I38*H38 -> 0
B39: 1.5 | C39: 3 | D39: =(15*(500+150+250))+1750 -> 15250 | E39: =D39*C39 -> 45750 | G39: 1.5 | H39: 3 | I39: =(15*(500+150+250))+1750 -> 15250 | J39: =I39*H39 -> 45750
B40: 3 | C40: 2 | D40: =(15*(600+150+250))+2000 -> 17000 | E40: =D40*C40 -> 34000 | G40: 3 | H40: 2 | I40: =(15*(600+150+250))+2000 -> 17000 | J40: =I40*H40 -> 34000
B41: ITEM | C41: QUANTITY | D41: PRICE | E41: TOTAL | G41: ITEM | H41: QUANTITY | I41: PRICE | J41: TOTAL
B42: PLUMBING WORKS | E42: =D42*C42 -> 0 | G42: PLUMBING WORKS | J42: =I42*H42 -> 0
B43: PLUMBING WORKS | C43: 1 | D43: 40000 | E43: =D43*C43 -> 40000 | G43: PLUMBING WORKS | H43: 1 | I43: 40000 | J43: =I43*H43 -> 40000
B44: ITEM | C44: QUANTITY | D44: PRICE | E44: TOTAL | G44: ITEM | H44: QUANTITY | I44: PRICE | J44: TOTAL
B45: SANITARY WARE | E45: =D45*C45 -> 0 | G45: SANITARY WARE | J45: =I45*H45 -> 0
B46: SINK | C46: 3 | D46: 10000 | E46: =D46*C46 -> 30000 | G46: SINK | H46: 0 | I46: 10000 | J46: =I46*H46 -> 0
B47: MIXER | C47: 4 | D47: 12000 | E47: =D47*C47 -> 48000 | G47: MIXER | H47: 0 | I47: 12000 | J47: =I47*H47 -> 0
B48: WALL MOUNTED TOILET WITH FLUSH TANK | C48: 3 | D48: 20000 | E48: =D48*C48 -> 60000 | G48: WALL MOUNTED TOILET WITH FLUSH TANK | H48: 3 | I48: 10000 | J48: =I48*H48 -> 30000
B49: SHOWER | C49: 2 | D49: 12000 | E49: =D49*C49 -> 24000 | G49: SHOWER | H49: 2 | I49: 12000 | J49: =I49*H49 -> 24000
B50: SINK KITCHEN | C50: 1 | D50: 12000 | E50: =D50*C50 -> 12000 | G50: SINK KITCHEN | H50: 0 | I50: 12000 | J50: =I50*H50 -> 0
B51: ACC. | C51: 1 | D51: 12000 | E51: =D51*C51 -> 12000 | G51: ACC. | H51: 0 | I51: 12000 | J51: =I51*H51 -> 0
B52: WATER SPRAY | C52: 3 | D52: 3000 | E52: =D52*C52 -> 9000 | G52: WATER SPRAY | H52: 0 | I52: 3000 | J52: =I52*H52 -> 0
B53: TOTAL | E53: =SUM(E6:E52) -> 1257990 | G53: TOTAL | J53: =SUM(J6:J52) -> 757300
B54: UNIT AREA | E54: 230 | G54: UNIT AREA | J54: 230
B55: FINISH PRICE / UNIT AREA (PRESENT VALUE) | E55: =E53/E54 -> 5469.5217 | G55: FINISH PRICE / UNIT AREA (PRESENT VALUE) | J55: =J53/J54 -> 3292.6087
B56: $ to EGP. Rate | E56: 30.95 | G56: $ to EGP. Rate | J56: 30.95
B57: Finish rate ($) / UNIT AREA | E57: =E55/E56 -> 176.72122 | G57: Finish rate ($) / UNIT AREA | J57: =J55/J56 -> 106.38477
B59: FINISHING PAYMENT (FULLY) | G59: FINISHING PAYMENT (BASIC)
B60: DP % | C60: 0.1 | D60: 0.05 | G60: DP % | H60: 0.1 | I60: 0.05
C61: Unit (1) | D61: Unit (1) | H61: Unit (1) | I61: Unit (1)
B62: Unit area | C62: 155 | D62: 155 | G62: Unit area | H62: 155 | I62: 155
B63: Unit price | C63: 7500 | D63: 7500 | G63: Unit price | H63: 4500 | I63: 4500 | O63: 54545
B64: Total Unit Price | C64: =C63*C62 -> 1162500 | D64: =D63*D62 -> 1162500 | G64: Total Unit Price | H64: =H63*H62 -> 697500 | I64: =I63*I62 -> 697500
B65: DP Value | C65: =C64*C60 -> 116250 | D65: =D64*D60 -> 58125 | G65: DP Value | H65: =H64*H60 -> 69750 | I65: =I64*I60 -> 34875
B66: No. of installments years | C66: 7 | D66: 6 | G66: No. of installments years | H66: 7 | I66: 6
B67: Installment value | C67: =(C64-C65)/(C66*C69) -> 37366.071 | D67: =(D64-D65)/(D66*D69) -> 46015.625 | G67: Installment value | H67: =(H64-H65)/(H66*H69) -> 22419.643 | I67: =(I64-I65)/(I66*I69) -> 27609.375
B68: Intrest Rate (yearly) DISCOUNTING | C68: 0.13 | D68: 0.13 | G68: Intrest Rate (yearly) DISCOUNTING | H68: 0.13 | I68: 0.13
B69: No. of Periods | C69: 4 | D69: 4 | G69: No. of Periods | H69: 4 | I69: 4
B70: Total no. of Periods | C70: =C66*C69 -> 28 | D70: =D66*D69 -> 24 | G70: Total no. of Periods | H70: =H66*H69 -> 28 | I70: =I66*I69 -> 24
B71: Intrest Rate (Period) | C71: =C68/C69 -> 0.0325 | D71: =D68/D69 -> 0.0325 | G71: Intrest Rate (Period) | H71: =H68/H69 -> 0.0325 | I71: =I68/I69 -> 0.0325
B72: Present Value (PV) | C72: =(((1-(1+C71)^(-C70))/(C71))*(C67))+(C65) -> 796435.5 | D72: =(((1-(1+D71)^(-D70))/(D71))*(D67))+(D65) -> 816846.43 | G72: Present Value (PV) | H72: =(((1-(1+H71)^(-H70))/(H71))*(H67))+(H65) -> 477861.3 | I72: =(((1-(1+I71)^(-I70))/(I71))*(I67))+(I65) -> 490107.86
B73: Present Value (PV)/M2 | C73: =(C72)/C62 -> 5138.2935 | D73: =(D72+D65)/D62 -> 5644.977 | G73: Present Value (PV)/M2 | H73: =(H72+H65)/H62 -> 3532.9761 | I73: =(I72+I65)/I62 -> 3386.9862 | P73: FALSE
G75: FINISHING PAYMENT (BASIC)
G76: DP % | H76: 0.1 | I76: 0.05
B77: TOTAL NO. OF UNITS FOR LAUNCH | C77: 144 | H77: Unit (1) | I77: Unit (1)
B78: TOTAL SELLING AREA FOR LAUNCH (M2) | C78: =GETPIVOTDATA("Sum of Unit Selling Area",'R1'!$A$18) -> 22116 | G78: Unit area | H78: 155 | I78: 155
B79: TOTAL PRICE OF LAUNCH UNITS (WITHOUT FINISH) | C79: =GETPIVOTDATA("Sum of TOTAL UNIT VALUE (SEMI FINISHED)",'R1'!$A$18)*0.9 -> 9.5989228e+08 | G79: Unit price | H79: 4500 | I79: 4500
B80: TOTAL PRICE OF LAUNCH UNITS (WITH BASIC FINISH) | C80: =GETPIVOTDATA("Sum of TOTAL UNIT VALUE (BASIC FINISHED)",'R1'!$A$18)*0.9 -> 1.0494621e+09 | G80: Total Unit Price | H80: =H79*H78 -> 697500 | I80: =I79*I78 -> 697500
B81: TOTAL PRICE OF LAUNCH UNITS (WITH FULLY FINISH) | C81: =GETPIVOTDATA("Sum of TOTAL UNIT VALUE (FULLY FINISHED)",'R1'!$A$18)*0.9 -> 1.1091753e+09 | G81: DP Value | H81: =H80*H76 -> 69750 | I81: =I80*I76 -> 34875
B82: DISCOUNT PERCENTAGE FOR LAUNCH | C82: 0.025 | G82: No. of installments years | H82: 7 | I82: 6
B83: DISCOUNT VALUE FOR LAUNCH | C83: =((C80+C81)/2)*0.025 -> 26982967 | G83: Installment value | H83: =(H80-H81)/(H82*H85) -> 22419.643 | I83: =(I80-I81)/(I82*I85) -> 27609.375
B84: CAR PARKING VALUE | C84: 200000 | G84: Intrest Rate (yearly) DISCOUNTING | H84: 0.13 | I84: 0.13
B85: NO. OF EQUIVELANT DISCOUNTED CARS | C85: =C83/C84 -> 134.91484 | G85: No. of Periods | H85: 4 | I85: 4
B86: AVERAGE SELLING PRICE /M2 FOR LAUNCH (WITHOUT FINISHING) WITHOUT LAUNCH DISCOUNT | C86: =AVERAGE('R1'!B19:B162) -> 45023.316 | G86: Total no. of Periods | H86: =H82*H85 -> 28 | I86: =I82*I85 -> 24
B87: AVERAGE SELLING PRICE /M2 FOR LAUNCH (WITH BASIC FINISHING) WITHOUT LAUNCH DISCOUNT | C87: =C86+4500 -> 49523.316 | G87: Intrest Rate (Period) | H87: =H84/H85 -> 0.0325 | I87: =I84/I85 -> 0.0325
B88: AVERAGE SELLING PRICE /M2 FOR LAUNCH (WITH BASIC FINISHING) WITHOUT LAUNCH DISCOUNT | C88: =C86+7500 -> 52523.316 | G88: Present Value (PV) | H88: =(((1-(1+H87)^(-H86))/(H87))*(H83))+(H81) -> 477861.3 | I88: =(((1-(1+I87)^(-I86))/(I87))*(I83))+(I81) -> 490107.86
B89: BASIC FINISHING PRICE / M2 | C89: 4500 | G89: Present Value (PV)/M2 | H89: =(H88+H81)/H78 -> 3532.9761 | I89: =(I88+I81)/I78 -> 3386.9862
B90: FULLY FINISHING PRICE / M2 | C90: 7500
B91: AVERAGE SELLING PRICE /M2 FOR LAUNCH (SEMI FINISHED) WITH LAUNCH DISCOUNT | C91: =C86*0.975 -> 43897.733
B92: AVERAGE SELLING PRICE /M2 FOR LAUNCH (WITH BASIC FINISHING) WITH LAUNCH DISCOUNT | C92: =C87*0.975 -> 48285.233
B93: AVERAGE SELLING PRICE /M2 FOR LAUNCH (WITH BASIC FINISHING) WITH LAUNCH DISCOUNT | C93: =C88*0.975 -> 51210.233
B94: PAYMENT PLAN (1) | C94: 10% DP & 7 YEARS EQUAL INSTALLMENTS
B95: PAYMENT PLAN (2) | C95: 5% DP & 6 YEARS EQUAL INSTALLMENTS
D105: تشطيبات الكهرباء | E105: لوحة كهرباء 24 | F105: عدد | G105: 0 | H105: 2500 | I105: =H105*G105 -> 0
D106: تشطيبات الكهرباء | E106: لوحة كهرباء 36 | F106: عدد | G106: 1 | H106: 3500 | I106: =H106*G106 -> 3500
D107: تشطيبات الكهرباء | E107: مفاتيح + قواطع اللوحة | F107: عدد | G107: 1 | H107: 4500 | I107: =H107*G107 -> 4500
D108: تشطيبات الكهرباء | E108: شاسية | F108: عدد | G108: 135 | H108: 45 | I108: =H108*G108 -> 6075
D109: تشطيبات الكهرباء | E109: وش | F109: عدد | G109: 135 | H109: 130 | I109: =H109*G109 -> 17550
D110: تشطيبات الكهرباء | E110: سدادة | F110: عدد | G110: 155 | H110: 20 | I110: =H110*G110 -> 3100
D111: تشطيبات الكهرباء | E111: بريزة شوكو | F111: عدد | G111: 8 | H111: 120 | I111: =H111*G111 -> 960
D112: تشطيبات الكهرباء | E112: بريزة عادية | F112: عدد | G112: 85 | H112: 65 | I112: =H112*G112 -> 5525
D113: تشطيبات الكهرباء | E113: بريزة دش | F113: عدد | G113: 8 | H113: 185 | I113: =H113*G113 -> 1480
...

Sheet DASHBOARD (4)
A1: SELLING PHASE NAME | B1: R 1
A3: Row Labels | B3: Count of Unit Selling Area
A4: 75 | B4: 3
A5: 106 | B5: 6
A6: 108 | B6: 2
A7: 110 | B7: 9
A8: 111 | B8: 5
A9: 112 | B9: 1
A10: 116 | B10: 8
A11: 117 | B11: 6
A12: 119 | B12: 5
A13: 120 | B13: 2
A14: 121 | B14: 5
A15: 122 | B15: 1
... A35: 344 | B35: 2
A36: Grand Total | B36: 144

Sheet prem cat. total dash
A1: Premium Category | B1: Count of PREMIUM CATEGORY | C1: Min of TOTAL PREMIUM % | D1: Max of TOTAL PREMIUM %
A2: A | B2: 204 | C2: 0.73 | D2: 0.965
A3: B | B3: 253 | C3: 0.505 | D3: 0.729
A4: C | B4: 345 | C4: 0.275 | D4: 0.495
A5: HOTEL | B5: 56 | C5: 0.285 | D5: 0.65
A6: Grand Total | B6: 858 | C6: 0.275 | D6: 0.965

Sheet DASHBOARD (2)
A1: SELLING PHASE NAME | B1: R 1
A3: Row Labels | B3: Count of Unit Selling Area | C3: Min of TOTAL PREMIUM % | D3: Max of TOTAL PREMIUM %
A4: 75 | B4: 3 | C4: 0.355 | D4: 0.355
A5: 106 | B5: 6 | C5: 0.355 | D5: 0.355
A6: 108 | B6: 2 | C6: 0.325 | D6: 0.345
A7: 110 | B7: 9 | C7: 0.355 | D7: 0.745
A8: 111 | B8: 5 | C8: 0.275 | D8: 0.585
A9: 112 | B9: 1 | C9: 0.505 | D9: 0.505
A10: 116 | B10: 8 | C10: 0.325 | D10: 0.355
A11: 117 | B11: 6 | C11: 0.345 | D11: 0.585
A12: 119 | B12: 5 | C12: 0.515 | D12: 0.745
A13: 120 | B13: 2 | C13: 0.355 | D13: 0.355
A14: 121 | B14: 5 | C14: 0.345 | D14: 0.585
A15: 122 | B15: 1 | C15: 0.555 | D15: 0.555
... A35: 344 | B35: 2 | C35: 0.685 | D35: 0.735
A36: Grand Total | B36: 144 | C36: 0.275 | D36: 0.745

Sheet A
L4: BLD No. | M4: A' - ( 1 )
L5: View | M5: Garden | O5: Garden | Q5: Garden | S5: Garden
L7: APT | M7: 3 | N7: 2 | O7: 3 | P7: 2 | Q7: 3 | R7: 2 | S7: 4 | T7: 3 | U7: 2
M8: 4 | N8: 1 | O8: 4 | P8: 1 | Q8: 4 | R8: 1 | S8: 5 | T8: 6 | U8: 1
L10: View | M10: Street | O10: Street | Q10: Street | S10: Street
A11: Type A'
A12: BLD Type | B12: Plot | C12: BLD No. | D12: Floor | E12: UNIT | F12: Unit Net Area | G12: Unit Gross | H12: PRIVET GARDEN | I12: Total Gross Area | J12: Service Area
A13: A' | B13: 1 | C13: A5 | D13: 0 | E13: =[2]A!E10 -> 1 | F13: =[2]A!F10 -> 69.17 | G13: =[2]A!G10 -> 88.3224 | H13: 24.4619 | I13: =SUM(G13:G40) -> 2208.06 | J13: =[2]A!I10 -> 125.92 | K13: =[2]A!J10 -> 441.66
E14: =[2]A!E11 -> 2 | F14: =[2]A!F11 -> 68.59 | G14: =[2]A!G11 -> 87.581804 | H14: 35.7856
E15: =[2]A!E12 -> 3 | F15: =[2]A!F12 -> 51.02 | G15: =[2]A!G12 -> 65.146868 | H15: 34.8891
E16: =[2]A!E13 -> 4 | F16: =[2]A!F13 -> 63.16 | G16: =[2]A!G13 -> 80.648298 | H16: 37.7172
E17: =[2]A!E14 -> 5 | F17: =[2]A!F14 -> 63.79 | G17: =[2]A!G14 -> 81.452738 | H17: 24.6688
D18: 1 | E18: =[2]A!E15 -> 1 | F18: =[2]A!F15 -> 69.17 | G18: =[2]A!G15 -> 88.3224 | J18: =[2]A!I15 -> 125.92 | K18: =[2]A!J15 -> 440.97
E19: =[2]A!E16 -> 2 | F19: =[2]A!F16 -> 68.59 | G19: =[2]A!G16 -> 87.581804
E20: =[2]A!E17 -> 3 | F20: =[2]A!F17 -> 51.02 | G20: =[2]A!G17 -> 65.146868
E21: =[2]A!E18 -> 4 | F21: =[2]A!F18 -> 62.9 | G21: =[2]A!G18 -> 80.316307
E22: =[2]A!E19 -> 5 | F22: =[2]A!F19 -> 63.79 | G22: =[2]A!G19 -> 81.452738
D23: 2 | E23: =[2]A!E20 -> 1 | F23: =[2]A!F20 -> 68.91 | G23: =[2]A!G20 -> 87.990409 | J23: =[2]A!I20 -> 75.75 | K23: =[2]A!J20 -> 442.77
E24: =[2]A!E21 -> 2 | F24: =[2]A!F21 -> 68.89 | G24: =[2]A!G21 -> 87.964871
E25: =[2]A!E22 -> 3 | F25: =[2]A!F22 -> 51.48 | G25: =[2]A!G22 -> 65.734237
E26: =[2]A!E23 -> 4 | F26: =[2]A!F23 -> 63.11 | G26: =[2]A!G23 -> 80.584454
E27: =[2]A!E24 -> 5 | F27: =[2]A!F24 -> 63.16 | G27: =[2]A!G24 -> 80.648298
E28: =[2]A!E25 -> 6 | F28: =[2]A!F25 -> 51.5 | G28: =[2]A!G25 -> 65.759774
D29: 3 | E29: =[2]A!E26 -> 1 | F29: =[2]A!F26 -> 68.62 | G29: =[2]A!G26 -> 87.620111 | J29: =[2]A!I26 -> 75.75 | K29: =[2]A!J26 -> 440.39
E30: =[2]A!E27 -> 2 | F30: =[2]A!F27 -> 68.6 | G30: =[2]A!G27 -> 87.594573
E31: =[2]A!E28 -> 3 | F31: =[2]A!F28 -> 50.89 | G31: =[2]A!G28 -> 64.980872
E32: =[2]A!E29 -> 4 | F32: =[2]A!F29 -> 62.84 | G32: =[2]A!G29 -> 80.239694
E33: =[2]A!E30 -> 5 | F33: =[2]A!F30 -> 62.86 | G33: =[2]A!G30 -> 80.265232
E34: =[2]A!E31 -> 6 | F34: =[2]A!F31 -> 50.89 | G34: =[2]A!G31 -> 64.980872
D35: 4 | E35: =[2]A!E32 -> 1 | F35: =[2]A!F32 -> 68.68 | G35: =[2]A!G32 -> 87.696724 | J35: =[2]A!I32 -> 75.75 | K35: =[2]A!J32 -> 442.27
E36: =[2]A!E33 -> 2 | F36: =[2]A!F33 -> 68.68 | G36: =[2]A!G33 -> 87.696724
E37: =[2]A!E34 -> 3 | F37: =[2]A!F34 -> 51.5 | G37: =[2]A!G34 -> 65.759774
E38: =[2]A!E35 -> 4 | F38: =[2]A!F35 -> 62.97 | G38: =[2]A!G35 -> 80.405689
E39: =[2]A!E36 -> 5 | F39: =[2]A!F36 -> 62.97 | G39: =[2]A!G36 -> 80.405689
E40: =[2]A!E37 -> 6 | F40: =[2]A!F37 -> 51.5 | G40: =[2]A!G37 -> 65.759774
A41: Total | F41: =SUM(F13:F40) -> 1729.25 | I41: =K13+K18+K23+K29+K35 -> 2208.06 | J41: =J35+J29+J23+J18+J13 -> 479.09
F42: =I41/F41 -> 1.2768888 | J42: =(J13+J18+J23+J29+J35)/I41 -> 0.21697327
A45: Type A'
A46: BLD Type | B46: Plot | C46: BLD No. | D46: Floor | E46: UNIT | F46: Unit Net Area | G46: Unit Gross | H46: PRIVET GARDEN | I46: Total Gross Area | J46: Service Area
A47: A' | B47: 1 | C47: A6 | D47: 0 | E47: =[2]A!E44 -> 1 | F47: =[2]A!F44 -> 60.98 | G47: =[2]A!G44 -> 66.845202 | H47: 23.8181 | I47: =SUM(G47:G66) -> 1994.46 | J47: =J99 -> 48.87 | K47: =[2]A!J44 -> 396.25
E48: =[2]A!E45 -> 2 | F48: =[2]A!F45 -> 89.96 | G48: =[2]A!G45 -> 98.612567 | H48: 50.5401
E49: =[2]A!E46 -> 3 | F49: =[2]A!F46 -> 97.98 | G49: =[2]A!G46 -> 107.40395 | H49: 50.7053
E50: =[2]A!E47 -> 4 | F50: =[2]A!F47 -> 98.17 | G50: =[2]A!G47 -> 107.61222 | H50: 31.5972
D51: 1 | E51: =[2]A!E48 -> 1 | F51: =[2]A!F48 -> 61.82 | G51: =[2]A!G48 -> 67.765995 | J51: =J103 -> 35.73 | K51: =[2]A!J48 -> 380.7
E52: =[2]A!E49 -> 2 | F52: =[2]A!F49 -> 89.05 | G52: =[2]A!G49 -> 97.615041
E53: =[2]A!E50 -> 3 | F53: =[2]A!F50 -> 97.06 | G53: =[2]A!G50 -> 106.39546
E54: =[2]A!E51 -> 4 | F54: =[2]A!F51 -> 97.09 | G54: =[2]A!G51 -> 106.42835
D55: 2 | E55: =[2]A!E52 -> 1 | F55: =[2]A!F52 -> 90.9 | G55: =[2]A!G52 -> 99.642979 | J55: =J107 -> 29.85 | K55: =[2]A!J52 -> 409.54
E56: =[2]A!E53 -> 2 | F56: =[2]A!F53 -> 90.91 | G56: =[2]A!G53 -> 99.653941
E57: =[2]A!E54 -> 3 | F57: =[2]A!F54 -> 98.93 | G57: =[2]A!G54 -> 108.44532
E58: =[2]A!E55 -> 4 | F58: =[2]A!F55 -> 98.95 | G58: =[2]A!G55 -> 108.46725
D59: 3 | E59: =[2]A!E56 -> 1 | F59: =[2]A!F56 -> 89.05 | G59: =[2]A!G56 -> 97.615041 | J59: =J111 -> 29.85 | K59: =[2]A!J56 -> 402.11
E60: =[2]A!E57 -> 2 | F60: =[2]A!F57 -> 89.05 | G60: =[2]A!G57 -> 97.615041
E61: =[2]A!E58 -> 3 | F61: =[2]A!F58 -> 97.09 | G61: =[2]A!G58 -> 106.42835
E62: =[2]A!E59 -> 4 | F62: =[2]A!F59 -> 97.09 | G62: =[2]A!G59 -> 106.42835
D63: 4 | E63: =[2]A!E60 -> 1 | F63: =[2]A!F60 -> 89.12 | G63: =[2]A!G60 -> 97.691774 | J63: =J115 -> 29.85 | K63: =[2]A!J60 -> 405.86
E64: =[2]A!E61 -> 2 | F64: =[2]A!F61 -> 90.52 | G64: =[2]A!G61 -> 99.226429
E65: =[2]A!E62 -> 3 | F65: =[2]A!F62 -> 98.57 | G65: =[2]A!G62 -> 108.0507
E66: =[2]A!E63 -> 4 | F66: =[2]A!F63 -> 97.17 | G66: =[2]A!G63 -> 106.51604
A67: Total | F67: =SUM(F47:F66) -> 1819.46 | I67: =K47+K51+K55+K59+K63 -> 1994.46 | J67: =J63+J59+J55+J51+J47 -> 174.15
F68: =I67/F67 -> 1.0961824 | J68: =(J47+J51+J55+J59+J63)/I67 -> 0.087316868
A71: Type A'
A72: BLD Type | B72: Plot | C72: BLD No. | D72: Floor | E72: UNIT | F72: Unit Net Area | G72: Unit Gross | H72: PRIVET GARDEN | I72: Total Gross Area | J72: Service Area
A73: A' | B73: 1 | C73: A7 | D73: 0 | E73: =[2]A!E70 -> 1 | F73: =[2]A!F70 -> 98.17 | G73: =[2]A!G70 -> 107.61045 | H73: 31.5979 | I73: =SUM(G73:G92) -> 1994.46 | J73: =J99 -> 48.87 | K73: =K47 -> 396.25
E74: =[2]A!E71 -> 2 | F74: =[2]A!F71 -> 97.98 | G74: =[2]A!G71 -> 107.40218 | H74: 50.7053
E75: =[2]A!E72 -> 3 | F75: =[2]A!F72 -> 89.96 | G75: =[2]A!G72 -> 98.610941 | H75: 50.5039
E76: =[2]A!E73 -> 4 | F76: =[2]A!F73 -> 60.98 | G76: =[2]A!G73 -> 66.8441 | H76: 23.7996
D77: 1 | E77: =[2]A!E74 -> 1 | F77: =[2]A!F74 -> 97.09 | G77: =[2]A!G74 -> 106.42659 | J77: =J103 -> 35.73 | K77: =K51 -> 380.7
E78: =[2]A!E75 -> 2 | F78: =[2]A!F75 -> 97.06 | G78: =[2]A!G75 -> 106.39371
E79: =[2]A!E76 -> 3 | F79: =[2]A!F76 -> 89.05 | G79: =[2]A!G76 -> 97.613432
E80: =[2]A!E77 -> 4 | F80: =[2]A!F77 -> 61.82 | G80: =[2]A!G77 -> 67.764878
D81: 2 | E81: =[2]A!E78 -> 1 | F81: =[2]A!F78 -> 98.95 | G81: =[2]A!G78 -> 108.46546 | J81: =J107 -> 29.85 | K81: =K55 -> 409.54
E82: =[2]A!E79 -> 2 | F82: =[2]A!F79 -> 98.95 | G82: =[2]A!G79 -> 108.46546
E83: =[2]A!E80 -> 3 | F83: =[2]A!F80 -> 90.91 | G83: =[2]A!G80 -> 99.652297
E84: =[2]A!E81 -> 4 | F84: =[2]A!F81 -> 90.91 | G84: =[2]A!G81 -> 99.652297
D85: 3 | E85: =[2]A!E82 -> 1 | F85: =[2]A!F82 -> 97.09 | G85: =[2]A!G82 -> 106.42659 | J85: =J111 -> 29.85 | K85: =K59 -> 402.11
E86: =[2]A!E83 -> 2 | F86: =[2]A!F83 -> 97.09 | G86: =[2]A!G83 -> 106.42659
E87: =[2]A!E84 -> 3 | F87: =[2]A!F84 -> 89.05 | G87: =[2]A!G84 -> 97.613432
E88: =[2]A!E85 -> 4 | F88: =[2]A!F85 -> 89.05 | G88: =[2]A!G85 -> 97.613432
D89: 4 | E89: =[2]A!E86 -> 1 | F89: =[2]A!F86 -> 97.17 | G89: =[2]A!G86 -> 106.51429 | J89: =J115 -> 29.85 | K89: =K63 -> 405.86
E90: =[2]A!E87 -> 2 | F90: =[2]A!F87 -> 98.57 | G90: =[2]A!G87 -> 108.04892
E91: =[2]A!E88 -> 3 | F91: =[2]A!F88 -> 90.52 | G91: =[2]A!G88 -> 99.224793
E92: =[2]A!E89 -> 4 | F92: =[2]A!F89 -> 89.12 | G92: =[2]A!G89 -> 97.690163
A93: Total | F93: =SUM(F73:F92) -> 1819.49 | I93: =K73+K77+K81+K85+K89 -> 1994.46 | J93: =J89+J85+J81+J77+J73 -> 174.15
F94: =I93/F93 -> 1.0961643 | J94: =(J73+J77+J81+J85+J89)/I93 -> 0.087316868
A97: Type A'
A98: BLD Type | B98: Plot | C98: BLD No. | D98: Floor | E98: UNIT | F98: Unit Net Area | G98: Unit Gross | H98: PRIVET GARDEN | I98: Total Gross Area | J98: Service Area
A99: A' | B99: 1 | C99: A8 | D99: 0 | E99: =[2]A!E96 -> 1 | F99: =[2]A!F96 -> 60.98 | G99: =[2]A!G96 -> 66.556564 | H99: 23.8008 | I99: =SUM(G99:G118) -> 2124.2 | J99: =[2]A!I96 -> 48.87 | K99: =[2]A!J96 -> 420.41
E100: =[2]A!E97 -> 2 | F100: =[2]A!F97 -> 89.96 | G100: =[2]A!G97 -> 98.186758 | H100: 50.5078
E101: =[2]A!E98 -> 3 | F101: =[2]A!F98 -> 110.14 | G101: =[2]A!G98 -> 120.2122 | H101: 59.4821
E102: =[2]A!E99 -> 4 | F102: =[2]A!F99 -> 110.32 | G102: =[2]A!G99 -> 120.40866 | H102: 50.0389
D103: 1 | E103: =[2]A!E100 -> 1 | F103: =[2]A!F100 -> 61.82 | G103: =[2]A!G100 -> 67.473381 | J103: =[2]A!I100 -> 35.73 | K103: =[2]A!J100 -> 407.35
E104: =[2]A!E101 -> 2 | F104: =[2]A!F101 -> 89.05 | G104: =[2]A!G101 -> 97.193539
E105: =[2]A!E102 -> 3 | F105: =[2]A!F102 -> 110.14 | G105: =[2]A!G102 -> 120.2122
E106: =[2]A!E103 -> 4 | F106: =[2]A!F103 -> 110.61 | G106: =[2]A!G103 -> 120.72518
D107: 2 | E107: =[2]A!E104 -> 1 | F107: =[2]A!F104 -> 90.91 | G107: =[2]A!G104 -> 99.223635 | J107: =[2]A!I104 -> 29.85 | K107: =[2]A!J104 -> 436.05
E108: =[2]A!E105 -> 2 | F108: =[2]A!F105 -> 90.91 | G108: =[2]A!G105 -> 99.223635
E109: =[2]A!E106 -> 3 | F109: =[2]A!F106 -> 112.2 | G109: =[2]A!G106 -> 122.46059
E110: =[2]A!E107 -> 4 | F110: =[2]A!F107 -> 112.2 | G110: =[2]A!G107 -> 122.46059
D111: 3 | E111: =[2]A!E108 -> 1 | F111: =[2]A!F108 -> 89.05 | G111: =[2]A!G108 -> 97.193539 | J111: =[2]A!I108 -> 29.85 | K111: =[2]A!J108 -> 428.22
...

Sheet Regent's Square
A4: BLD Type | B4: Plot | C4: BLD No. | D4: Floor | E4: UNIT | F4: Unit Number | G4: Unit Net Area | H4: Unit Gross Area | I4: Unit Selling Area | J4: Private Garden Area | K4: Total Gross Area | L4: Service Area
A5: A | B5: 15 | C5: A1 | D5: 0 | E5: 1 | F5: =LEFT(C5,2)&D5&E5 -> A101 | G5: 110.32 | H5: 120.40866 | I5: =G5*1.22 -> 134.5904 | J5: 42.7795 | K5: =SUM(H5:H24) -> 2124.2 | L5: 48.87
C6: A1 | D6: 0 | E6: 2 | F6: =LEFT(C6,2)&D6&E6 -> A102 | G6: 110.14 | H6: 120.2122 | I6: =G6*1.22 -> 134.3708 | J6: 59.4821
C7: A1 | D7: 0 | E7: 3 | F7: =LEFT(C7,2)&D7&E7 -> A103 | G7: 89.96 | H7: 98.186758 | I7: =G7*1.22 -> 109.7512 | J7: 50.5078
C8: A1 | D8: 0 | E8: 4 | F8: =LEFT(C8,2)&D8&E8 -> A104 | G8: 60.98 | H8: 66.556564 | I8: =G8*1.22 -> 74.3956 | J8: 23.8084
C9: A1 | D9: 1 | E9: 1 | F9: =LEFT(C9,2)&D9&E9 -> A111 | G9: 110.61 | H9: 120.72518 | I9: =G9*1.22 -> 134.9442 | L9: 35.73
C10: A1 | D10: 1 | E10: 2 | F10: =LEFT(C10,2)&D10&E10 -> A112 | G10: 110.14 | H10: 120.2122 | I10: =G10*1.22 -> 134.3708
C11: A1 | D11: 1 | E11: 3 | F11: =LEFT(C11,2)&D11&E11 -> A113 | G11: 89.05 | H11: 97.193539 | I11: =G11*1.22 -> 108.641
C12: A1 | D12: 1 | E12: 4 | F12: =LEFT(C12,2)&D12&E12 -> A114 | G12: 61.82 | H12: 67.473381 | I12: =G12*1.22 -> 75.4204
C13: A1 | D13: 2 | E13: 1 | F13: =LEFT(C13,2)&D13&E13 -> A121 | G13: 112.2 | H13: 122.46059 | I13: =G13*1.22 -> 136.884 | L13: 29.85
C14: A1 | D14: 2 | E14: 2 | F14: =LEFT(C14,2)&D14&E14 -> A122 | G14: 112.2 | H14: 122.46059 | I14: =G14*1.22 -> 136.884
C15: A1 | D15: 2 | E15: 3 | F15: =LEFT(C15,2)&D15&E15 -> A123 | G15: 90.91 | H15: 99.223635 | I15: =G15*1.22 -> 110.9102
C16: A1 | D16: 2 | E16: 4 | F16: =LEFT(C16,2)&D16&E16 -> A124 | G16: 90.91 | H16: 99.223635 | I16: =G16*1.22 -> 110.9102
C17: A1 | D17: 3 | E17: 1 | F17: =LEFT(C17,2)&D17&E17 -> A131 | G17: 110.14 | H17: 120.2122 | I17: =G17*1.22 -> 134.3708 | L17: 29.85
C18: A1 | D18: 3 | E18: 2 | F18: =LEFT(C18,2)&D18&E18 -> A132 | G18: 110.14 | H18: 120.2122 | I18: =G18*1.22 -> 134.3708
C19: A1 | D19: 3 | E19: 3 | F19: =LEFT(C19,2)&D19&E19 -> A133 | G19: 89.05 | H19: 97.193539 | I19: =G19*1.22 -> 108.641
C20: A1 | D20: 3 | E20: 4 | F20: =LEFT(C20,2)&D20&E20 -> A134 | G20: 89.05 | H20: 97.193539 | I20: =G20*1.22 -> 108.641
C21: A1 | D21: 4 | E21: 1 | F21: =LEFT(C21,2)&D21&E21 -> A141 | G21: 110.18 | H21: 120.25586 | I21: =G21*1.22 -> 134.4196 | L21: 29.85
C22: A1 | D22: 4 | E22: 2 | F22: =LEFT(C22,2)&D22&E22 -> A142 | G22: 110.18 | H22: 120.25586 | I22: =G22*1.22 -> 134.4196
C23: A1 | D23: 4 | E23: 3 | F23: =LEFT(C23,2)&D23&E23 -> A143 | G23: 89.12 | H23: 97.269941 | I23: =G23*1.22 -> 108.7264
C24: A1 | D24: 4 | E24: 4 | F24: =LEFT(C24,2)&D24&E24 -> A144 | G24: 89.12 | H24: 97.269941 | I24: =G24*1.22 -> 108.7264
A25: Total | G25: 1946.22 | I25: =SUM(I5:I24) -> 2374.3884 | K25: =SUM(K5) -> 2124.2 | L25: =L21+L17+L13+L9+L5 -> 174.15
G26: =K25/G25 -> 1.0914491 | L26: =(L5+L9+L13+L17+L21)/K25 -> 0.081983806
A29: Type A
A30: BLD Type | B30: Plot | C30: BLD No. | D30: Floor | E30: UNIT | F30: Unit Number | G30: Unit Net Area | H30: Unit Gross Area | I30: Unit Selling Area | J30: Private Garden Area | K30: Total Gross Area | L30: Service Area
A31: A | B31: 15 | C31: A2 | D31: 0 | E31: 1 | F31: =LEFT(C31,2)&D31&E31 -> A201 | G31: 60.98 | H31: 66.8441 | I31: =G31*1.22 -> 74.3956 | J31: 23.8084 | K31: =SUM(I31:I50) -> 2219.7778 | L31: =L5 -> 48.87
C32: A2 | D32: 0 | E32: 2 | F32: =LEFT(C32,2)&D32&E32 -> A202 | G32: 89.96 | H32: 98.610941 | I32: =G32*1.22 -> 109.7512 | J32: 50.5039
C33: A2 | D33: 0 | E33: 3 | F33: =LEFT(C33,2)&D33&E33 -> A203 | G33: 97.98 | H33: 107.40218 | I33: =G33*1.22 -> 119.5356 | J33: 50.7053
C34: A2 | D34: 0 | E34: 4 | F34: =LEFT(C34,2)&D34&E34 -> A204 | G34: 98.17 | H34: 107.61045 | I34: =G34*1.22 -> 119.7674 | J34: 31.6139
C35: A2 | D35: 1 | E35: 1 | F35: =LEFT(C35,2)&D35&E35 -> A211 | G35: 61.82 | H35: 67.764878 | I35: =G35*1.22 -> 75.4204 | L35: =L9 -> 35.73
C36: A2 | D36: 1 | E36: 2 | F36: =LEFT(C36,2)&D36&E36 -> A212 | G36: 89.05 | H36: 97.613432 | I36: =G36*1.22 -> 108.641
C37: A2 | D37: 1 | E37: 3 | F37: =LEFT(C37,2)&D37&E37 -> A213 | G37: 97.06 | H37: 106.39371 | I37: =G37*1.22 -> 118.4132
C38: A2 | D38: 1 | E38: 4 | F38: =LEFT(C38,2)&D38&E38 -> A214 | G38: 97.09 | H38: 106.42659 | I38: =G38*1.22 -> 118.4498
C39: A2 | D39: 2 | E39: 1 | F39: =LEFT(C39,2)&D39&E39 -> A221 | G39: 90.91 | H39: 99.652297 | I39: =G39*1.22 -> 110.9102 | L39: =L13 -> 29.85
C40: A2 | D40: 2 | E40: 2 | F40: =LEFT(C40,2)&D40&E40 -> A222 | G40: 90.91 | H40: 99.652297 | I40: =G40*1.22 -> 110.9102
C41: A2 | D41: 2 | E41: 3 | F41: =LEFT(C41,2)&D41&E41 -> A223 | G41: 98.95 | H41: 108.46546 | I41: =G41*1.22 -> 120.719
C42: A2 | D42: 2 | E42: 4 | F42: =LEFT(C42,2)&D42&E42 -> A224 | G42: 98.95 | H42: 108.46546 | I42: =G42*1.22 -> 120.719
C43: A2 | D43: 3 | E43: 1 | F43: =LEFT(C43,2)&D43&E43 -> A231 | G43: 89.05 | H43: 97.613432 | I43: =G43*1.22 -> 108.641 | L43: =L17 -> 29.85
C44: A2 | D44: 3 | E44: 2 | F44: =LEFT(C44,2)&D44&E44 -> A232 | G44: 89.05 | H44: 97.613432 | I44: =G44*1.22 -> 108.641
C45: A2 | D45: 3 | E45: 3 | F45: =LEFT(C45,2)&D45&E45 -> A233 | G45: 97.09 | H45: 106.42659 | I45: =G45*1.22 -> 118.4498
C46: A2 | D46: 3 | E46: 4 | F46: =LEFT(C46,2)&D46&E46 -> A234 | G46: 97.09 | H46: 106.42659 | I46: =G46*1.22 -> 118.4498
C47: A2 | D47: 4 | E47: 1 | F47: =LEFT(C47,2)&D47&E47 -> A241 | G47: 89.12 | H47: 97.690163 | I47: =G47*1.22 -> 108.7264 | L47: =L21 -> 29.85
C48: A2 | D48: 4 | E48: 2 | F48: =LEFT(C48,2)&D48&E48 -> A242 | G48: 90.52 | H48: 99.224793 | I48: =G48*1.22 -> 110.4344
C49: A2 | D49: 4 | E49: 3 | F49: =LEFT(C49,2)&D49&E49 -> A243 | G49: 98.57 | H49: 108.04892 | I49: =G49*1.22 -> 120.2554
C50: A2 | D50: 4 | E50: 4 | F50: =LEFT(C50,2)&D50&E50 -> A244 | G50: 97.17 | H50: 106.51429 | I50: =G50*1.22 -> 118.5474
A51: Total | G51: =SUM(G31:G50) -> 1819.49 | I51: =SUM(I31:I50) -> 2219.7778 | K51: =SUM(K31) -> 2219.7778 | L51: =L47+L43+L39+L35+L31 -> 174.15
G52: =K51/G51 -> 1.22 | L52: =(L31+L35+L39+L43+L47)/K51 -> 0.078453798
A55: Type A
A56: BLD Type | B56: Plot | C56: BLD No. | D56: Floor | E56: UNIT | F56: Unit Number | G56: Unit Net Area | H56: Unit Gross Area | I56: Unit Selling Area | J56: Private Garden Area | K56: Total Gross Area | L56: Service Area
A57: A | B57: 15 | C57: A3 | D57: 0 | E57: 1 | F57: =LEFT(C57,2)&D57&E57 -> A301 | G57: 98.17 | H57: 107.61163 | I57: =G57*1.22 -> 119.7674 | J57: 31.6147 | K57: =SUM(H57:H76) -> 1994.46 | L57: =L5 -> 48.87
C58: A3 | D58: 0 | E58: 2 | F58: =LEFT(C58,2)&D58&E58 -> A302 | G58: 97.98 | H58: 107.40336 | I58: =G58*1.22 -> 119.5356 | J58: 50.7053
C59: A3 | D59: 0 | E59: 3 | F59: =LEFT(C59,2)&D59&E59 -> A303 | G59: 89.96 | H59: 98.612025 | I59: =G59*1.22 -> 109.7512 | J59: 50.5401
C60: A3 | D60: 0 | E60: 4 | F60: =LEFT(C60,2)&D60&E60 -> A304 | G60: 60.98 | H60: 66.844834 | I60: =G60*1.22 -> 74.3956 | J60: 23.8301
C61: A3 | D61: 1 | E61: 1 | F61: =LEFT(C61,2)&D61&E61 -> A311 | G61: 97.09 | H61: 106.42776 | I61: =G61*1.22 -> 118.4498 | L61: =L9 -> 35.73
C62: A3 | D62: 1 | E62: 2 | F62: =LEFT(C62,2)&D62&E62 -> A312 | G62: 97.06 | H62: 106.39488 | I62: =G62*1.22 -> 118.4132
C63: A3 | D63: 1 | E63: 3 | F63: =LEFT(C63,2)&D63&E63 -> A313 | G63: 89.05 | H63: 97.614505 | I63: =G63*1.22 -> 108.641
C64: A3 | D64: 1 | E64: 4 | F64: =LEFT(C64,2)&D64&E64 -> A314 | G64: 61.82 | H64: 67.765623 | I64: =G64*1.22 -> 75.4204
C65: A3 | D65: 2 | E65: 1 | F65: =LEFT(C65,2)&D65&E65 -> A321 | G65: 98.95 | H65: 108.46665 | I65: =G65*1.22 -> 120.719 | L65: =L13 -> 29.85
C66: A3 | D66: 2 | E66: 2 | F66: =LEFT(C66,2)&D66&E66 -> A322 | G66: 98.93 | H66: 108.44473 | I66: =G66*1.22 -> 120.6946
C67: A3 | D67: 2 | E67: 3 | F67: =LEFT(C67,2)&D67&E67 -> A323 | G67: 90.91 | H67: 99.653393 | I67: =G67*1.22 -> 110.9102
C68: A3 | D68: 2 | E68: 4 | F68: =LEFT(C68,2)&D68&E68 -> A324 | G68: 90.91 | H68: 99.653393 | I68: =G68*1.22 -> 110.9102
C69: A3 | D69: 3 | E69: 1 | F69: =LEFT(C69,2)&D69&E69 -> A331 | G69: 97.09 | H69: 106.42776 | I69: =G69*1.22 -> 118.4498 | L69: =L17 -> 29.85
C70: A3 | D70: 3 | E70: 2 | F70: =LEFT(C70,2)&D70&E70 -> A332 | G70: 97.09 | H70: 106.42776 | I70: =G70*1.22 -> 118.4498
C71: A3 | D71: 3 | E71: 3 | F71: =LEFT(C71,2)&D71&E71 -> A333 | G71: 89.05 | H71: 97.614505 | I71: =G71*1.22 -> 108.641
C72: A3 | D72: 3 | E72: 4 | F72: =LEFT(C72,2)&D72&E72 -> A334 | G72: 89.05 | H72: 97.614505 | I72: =G72*1.22 -> 108.641
C73: A3 | D73: 4 | E73: 1 | F73: =LEFT(C73,2)&D73&E73 -> A341 | G73: 97.17 | H73: 106.51546 | I73: =G73*1.22 -> 118.5474 | L73: =L21 -> 29.85
C74: A3 | D74: 4 | E74: 2 | F74: =LEFT(C74,2)&D74&E74 -> A342 | G74: 98.57 | H74: 108.0501 | I74: =G74*1.22 -> 120.2554
C75: A3 | D75: 4 | E75: 3 | F75: =LEFT(C75,2)&D75&E75 -> A343 | G75: 90.52 | H75: 99.225884 | I75: =G75*1.22 -> 110.4344
C76: A3 | D76: 4 | E76: 4 | F76: =LEFT(C76,2)&D76&E76 -> A344 | G76: 89.12 | H76: 97.691237 | I76: =G76*1.22 -> 108.7264
A77: Total | G77: =SUM(G57:G76) -> 1819.47 | I77: =SUM(I57:I76) -> 2219.7534 | K77: =SUM(K57) -> 1994.46 | L77: =L73+L69+L65+L61+L57 -> 174.15
G78: =K77/G77 -> 1.0961764 | L78: =(L57+L61+L65+L69+L73)/K77 -> 0.087316868
A80: Type A
A81: BLD Type | B81: Plot | C81: BLD No. | D81: Floor | E81: UNIT | F81: Unit Number | G81: Unit Net Area | H81: Unit Gross Area | I81: Unit Selling Area | J81: Private Garden Area | K81: Total Gross Area | L81: Service Area
A82: A | B82: 15 | C82: A4 | D82: 0 | E82: 1 | F82: =LEFT(C82,2)&D82&E82 -> A401 | G82: 63.79 | H82: 81.452738 | I82: =G82*1.28 -> 81.6512 | J82: 24.6822 | K82: =SUM(H82:H109) -> 2208.06 | L82: 125.92
C83: A4 | D83: 0 | E83: 2 | F83: =LEFT(C83,2)&D83&E83 -> A402 | G83: 63.16 | H83: 80.648298 | I83: =G83*1.28 -> 80.8448 | J83: 37.7172
C84: A4 | D84: 0 | E84: 3 | F84: =LEFT(C84,2)&D84&E84 -> A403 | G84: 51.02 | H84: 65.146868 | I84: =G84*1.28 -> 65.3056 | J84: 34.8891
C85: A4 | D85: 0 | E85: 4 | F85: =LEFT(C85,2)&D85&E85 -> A404 | G85: 68.59 | H85: 87.581804 | I85: =G85*1.28 -> 87.7952 | J85: 35.7856
C86: A4 | D86: 0 | E86: 5 | F86: =LEFT(C86,2)&D86&E86 -> A405 | G86: 69.17 | H86: 88.3224 | I86: =G86*1.28 -> 88.5376 | J86: 24.1423
C87: A4 | D87: 1 | E87: 1 | F87: =LEFT(C87,2)&D87&E87 -> A411 | G87: 63.79 | H87: 81.452738 | I87: =G87*1.28 -> 81.6512 | L87: 125.92
C88: A4 | D88: 1 | E88: 2 | F88: =LEFT(C88,2)&D88&E88 -> A412 | G88: 62.9 | H88: 80.316307 | I88: =G88*1.28 -> 80.512
C89: A4 | D89: 1 | E89: 3 | F89: =LEFT(C89,2)&D89&E89 -> A413 | G89: 51.02 | H89: 65.146868 | I89: =G89*1.28 -> 65.3056
C90: A4 | D90: 1 | E90: 4 | F90: =LEFT(C90,2)&D90&E90 -> A414 | G90: 68.59 | H90: 87.581804 | I90: =G90*1.28 -> 87.7952
C91: A4 | D91: 1 | E91: 5 | F91: =LEFT(C91,2)&D91&E91 -> A415 | G91: 69.17 | H91: 88.3224 | I91: =G91*1.28 -> 88.5376
C92: A4 | D92: 2 | E92: 1 | F92: =LEFT(C92,2)&D92&E92 -> A421 | G92: 63.16 | H92: 80.648298 | I92: =G92*1.28 -> 80.8448 | L92: 75.75
C93: A4 | D93: 2 | E93: 2 | F93: =LEFT(C93,2)&D93&E93 -> A422 | G93: 63.11 | H93: 80.584454 | I93: =G93*1.28 -> 80.7808
C94: A4 | D94: 2 | E94: 3 | F94: =LEFT(C94,2)&D94&E94 -> A423 | G94: 51.48 | H94: 65.734237 | I94: =G94*1.28 -> 65.8944
C95: A4 | D95: 2 | E95: 4 | F95: =LEFT(C95,2)&D95&E95 -> A424 | G95: 68.89 | H95: 87.964871 | I95: =G95*1.28 -> 88.1792
C96: A4 | D96: 2 | E96: 5 | F96: =LEFT(C96,2)&D96&E96 -> A425 | G96: 68.91 | H96: 87.990409 | I96: =G96*1.28 -> 88.2048
C97: A4 | D97: 2 | E97: 6 | F97: =LEFT(C97,2)&D97&E97 -> A426 | G97: 51.5 | H97: 65.759774 | I97: =G97*1.28 -> 65.92
C98: A4 | D98: 3 | E98: 1 | F98: =LEFT(C98,2)&D98&E98 -> A431 | G98: 62.86 | H98: 80.265232 | I98: =G98*1.28 -> 80.4608 | L98: 75.75
C99: A4 | D99: 3 | E99: 2 | F99: =LEFT(C99,2)&D99&E99 -> A432 | G99: 62.84 | H99: 80.239694 | I99: =G99*1.28 -> 80.4352
C100: A4 | D100: 3 | E100: 3 | F100: =LEFT(C100,2)&D100&E100 -> A433 | G100: 50.89 | H100: 64.980872 | I100: =G100*1.28 -> 65.1392
C101: A4 | D101: 3 | E101: 4 | F101: =LEFT(C101,2)&D101&E101 -> A434 | G101: 68.6 | H101: 87.594573 | I101: =G101*1.28 -> 87.808
C102: A4 | D102: 3 | E102: 5 | F102: =LEFT(C102,2)&D102&E102 -> A435 | G102: 68.62 | H102: 87.620111 | I102: =G102*1.28 -> 87.8336
C103: A4 | D103: 3 | E103: 6 | F103: =LEFT(C103,2)&D103&E103 -> A436 | G103: 50.89 | H103: 64.980872 | I103: =G103*1.28 -> 65.1392
C104: A4 | D104: 4 | E104: 1 | F104: =LEFT(C104,2)&D104&E104 -> A441 | G104: 62.97 | H104: 80.405689 | I104: =G104*1.28 -> 80.6016 | L104: 75.75
C105: A4 | D105: 4 | E105: 2 | F105: =LEFT(C105,2)&D105&E105 -> A442 | G105: 62.97 | H105: 80.405689 | I105: =G105*1.28 -> 80.6016
C106: A4 | D106: 4 | E106: 3 | F106: =LEFT(C106,2)&D106&E106 -> A443 | G106: 51.5 | H106: 65.759774 | I106: =G106*1.28 -> 65.92
C107: A4 | D107: 4 | E107: 4 | F107: =LEFT(C107,2)&D107&E107 -> A444 | G107: 68.68 | H107: 87.696724 | I107: =G107*1.28 -> 87.9104
C108: A4 | D108: 4 | E108: 5 | F108: =LEFT(C108,2)&D108&E108 -> A445 | G108: 68.68 | H108: 87.696724 | I108: =G108*1.28 -> 87.9104
...

Sheet FACTS
A1: DATE | B1: SELLING PHASE | C1: PHASES ESCALLATION RATES | D1: PLANNED PHASES SELLING % | E1: PLANNED PHASES SELLING AREA | F1: CATEGORY (A) (SELLING PHASE AREA) | G1: CATEGORY (B) (SELLING PHASE AREA) | H1: CATEGORY (C) (SELLING PHASE AREA) | J1: PARKING PRICE | K1: PHASE (BUILDING) STARTING PRICE | L1: PHASE (BUILDING) CLOSING PRICE | M1: PHASE AVERAGE PRICE | N1: PHASE PREMIUM RANGE | O1: PREMIUM RANGE % | P1: BASIC PRICE INCREASE | Q1: PREMIUM PRICE INCREASE | R1: PHASE INCREASE % | S1: MAINTENANCE % | T1: GARDEN PRICE %
A2: 45200 | B2: R 1 | C2: 0 | D2: 0.17 | E2: =131531*D2 -> 22360.27 | F2: =GETPIVOTDATA("Sum of Unit Selling Area2",PIVOT!$A$227,"PREMIUM CATEGORY","A")*E2 -> 6579.5378 | G2: =GETPIVOTDATA("Sum of Unit Selling Area2",PIVOT!$A$227,"PREMIUM CATEGORY","B")*E2 -> 7320.0161 | H2: =GETPIVOTDATA("Sum of Unit Selling Area2",PIVOT!$A$227,"PREMIUM CATEGORY","C")*E2 -> 8460.7162 | J2: 200000 | K2: 42500 | L2: 47500 | M2: =AVERAGE(K2:L2) -> 45000 | N2: =L2-K2 -> 5000 | O2: =N2/K2 -> 0.11764706 | P2: =K2-K2 -> 0 | Q2: =N2-N2 -> 0 | R2: =C2-C2 -> 0 | S2: 0.085 | T2: 0.33
A3: =EDATE(A2,3) -> 45292 | B3: R 2 | C3: 0.025 | D3: 0.07 | E3: =131531*D3 -> 9207.17 | F3: =GETPIVOTDATA("Sum of Unit Selling Area2",PIVOT!$A$227,"PREMIUM CATEGORY","A")*E3 -> 2709.2214 | G3: =GETPIVOTDATA("Sum of Unit Selling Area2",PIVOT!$A$227,"PREMIUM CATEGORY","B")*E3 -> 3014.1243 | H3: =GETPIVOTDATA("Sum of Unit Selling Area2",PIVOT!$A$227,"PREMIUM CATEGORY","C")*E3 -> 3483.8243 | J3: =$J$2*(1+C3) -> 205000 | K3: =$K$2*(1+C3) -> 43562.5 | L3: =$L$2*(1+C3) -> 48687.5 | M3: =AVERAGE(K3:L3) -> 46125 | N3: =L3-K3 -> 5125 | O3: =N3/K3 -> 0.11764706 | P3: =K3-K2 -> 1062.5 | Q3: =N3-$N$2 -> 125 | R3: =C3-C2 -> 0.025 | S3: 0.085 | T3: 0.33
A4: =EDATE(A3,3) -> 45383 | B4: R 3 | C4: 0.05 | D4: 0.07 | E4: =131531*D4 -> 9207.17 | F4: =GETPIVOTDATA("Sum of Unit Selling Area2",PIVOT!$A$227,"PREMIUM CATEGORY","A")*E4 -> 2709.2214 | G4: =GETPIVOTDATA("Sum of Unit Selling Area2",PIVOT!$A$227,"PREMIUM CATEGORY","B")*E4 -> 3014.1243 | H4: =GETPIVOTDATA("Sum of Unit Selling Area2",PIVOT!$A$227,"PREMIUM CATEGORY","C")*E4 -> 3483.8243 | J4: =$J$2*(1+C4) -> 210000 | K4: =$K$2*(1+C4) -> 44625 | L4: =$L$2*(1+C4) -> 49875 | M4: =AVERAGE(K4:L4) -> 47250 | N4: =L4-K4 -> 5250 | O4: =N4/K4 -> 0.11764706 | P4: =K4-K3 -> 1062.5 | Q4: =N4-$N$2 -> 250 | R4: =C4-C3 -> 0.025 | S4: 0.085 | T4: 0.33
A5: =EDATE(A4,3) -> 45474 | B5: R 4 | C5: 0.075 | D5: 0.11 | E5: =131531*D5 -> 14468.41 | F5: =GETPIVOTDATA("Sum of Unit Selling Area2",PIVOT!$A$227,"PREMIUM CATEGORY","A")*E5 -> 4257.348 | G5: =GETPIVOTDATA("Sum of Unit Selling Area2",PIVOT!$A$227,"PREMIUM CATEGORY","B")*E5 -> 4736.481 | H5: =GETPIVOTDATA("Sum of Unit Selling Area2",PIVOT!$A$227,"PREMIUM CATEGORY","C")*E5 -> 5474.581 | J5: =$J$2*(1+C5) -> 215000 | K5: =$K$2*(1+C5) -> 45687.5 | L5: =$L$2*(1+C5) -> 51062.5 | M5: =AVERAGE(K5:L5) -> 48375 | N5: =L5-K5 -> 5375 | O5: =N5/K5 -> 0.11764706 | P5: =K5-K4 -> 1062.5 | Q5: =N5-$N$2 -> 375 | R5: =C5-C4 -> 0.025 | S5: 0.085 | T5: 0.33
A6: =EDATE(A5,3) -> 45566 | B6: R 5 | C6: 0.1 | D6: 0.08 | E6: =131531*D6 -> 10522.48 | F6: =GETPIVOTDATA("Sum of Unit Selling Area2",PIVOT!$A$227,"PREMIUM CATEGORY","A")*E6 -> 3096.2531 | G6: =GETPIVOTDATA("Sum of Unit Selling Area2",PIVOT!$A$227,"PREMIUM CATEGORY","B")*E6 -> 3444.7134 | H6: =GETPIVOTDATA("Sum of Unit Selling Area2",PIVOT!$A$227,"PREMIUM CATEGORY","C")*E6 -> 3981.5135 | J6: =$J$2*(1+C6) -> 220000 | K6: =$K$2*(1+C6) -> 46750 | L6: =$L$2*(1+C6) -> 52250 | M6: =AVERAGE(K6:L6) -> 49500 | N6: =L6-K6 -> 5500 | O6: =N6/K6 -> 0.11764706 | P6: =K6-K5 -> 1062.5 | Q6: =N6-$N$2 -> 500 | R6: =C6-C5 -> 0.025 | S6: 0.085 | T6: 0.33
A7: =EDATE(A6,3) -> 45658 | B7: R 6 | C7: 0.14 | D7: 0.07 | E7: =131531*D7 -> 9207.17 | F7: =GETPIVOTDATA("Sum of Unit Selling Area2",PIVOT!$A$227,"PREMIUM CATEGORY","A")*E7 -> 2709.2214 | G7: =GETPIVOTDATA("Sum of Unit Selling Area2",PIVOT!$A$227,"PREMIUM CATEGORY","B")*E7 -> 3014.1243 | H7: =GETPIVOTDATA("Sum of Unit Selling Area2",PIVOT!$A$227,"PREMIUM CATEGORY","C")*E7 -> 3483.8243 | J7: =$J$2*(1+C7) -> 228000 | K7: =$K$2*(1+C7) -> 48450 | L7: =$L$2*(1+C7) -> 54150 | M7: =AVERAGE(K7:L7) -> 51300 | N7: =L7-K7 -> 5700 | O7: =N7/K7 -> 0.11764706 | P7: =K7-K6 -> 1700 | Q7: =N7-$N$2 -> 700 | R7: =C7-C6 -> 0.04 | S7: 0.085 | T7: 0.33
A8: =EDATE(A7,3) -> 45748 | B8: R 7 | C8: 0.18 | D8: 0.08 | E8: =131531*D8 -> 10522.48 | F8: =GETPIVOTDATA("Sum of Unit Selling Area2",PIVOT!$A$227,"PREMIUM CATEGORY","A")*E8 -> 3096.2531 | G8: =GETPIVOTDATA("Sum of Unit Selling Area2",PIVOT!$A$227,"PREMIUM CATEGORY","B")*E8 -> 3444.7134 | H8: =GETPIVOTDATA("Sum of Unit Selling Area2",PIVOT!$A$227,"PREMIUM CATEGORY","C")*E8 -> 3981.5135 | J8: =$J$2*(1+C8) -> 236000 | K8: =$K$2*(1+C8) -> 50150 | L8: =$L$2*(1+C8) -> 56050 | M8: =AVERAGE(K8:L8) -> 53100 | N8: =L8-K8 -> 5900 | O8: =N8/K8 -> 0.11764706 | P8: =K8-K7 -> 1700 | Q8: =N8-$N$2 -> 900 | R8: =C8-C7 -> 0.04 | S8: 0.085 | T8: 0.33
A9: =EDATE(A8,3) -> 45839 | B9: R 8 | C9: 0.22 | D9: 0.12 | E9: =131531*D9 -> 15783.72 | F9: =GETPIVOTDATA("Sum of Unit Selling Area2",PIVOT!$A$227,"PREMIUM CATEGORY","A")*E9 -> 4644.3796 | G9: =GETPIVOTDATA("Sum of Unit Selling Area2",PIVOT!$A$227,"PREMIUM CATEGORY","B")*E9 -> 5167.0702 | H9: =GETPIVOTDATA("Sum of Unit Selling Area2",PIVOT!$A$227,"PREMIUM CATEGORY","C")*E9 -> 5972.2702 | J9: =$J$2*(1+C9) -> 244000 | K9: =$K$2*(1+C9) -> 51850 | L9: =$L$2*(1+C9) -> 57950 | M9: =AVERAGE(K9:L9) -> 54900 | N9: =L9-K9 -> 6100 | O9: =N9/K9 -> 0.11764706 | P9: =K9-K8 -> 1700 | Q9: =N9-$N$2 -> 1100 | R9: =C9-C8 -> 0.04 | S9: 0.085 | T9: 0.33
A10: =EDATE(A9,3) -> 45931 | B10: R 9 | C10: 0.26 | D10: 0.08 | E10: =131531*D10 -> 10522.48 | F10: =GETPIVOTDATA("Sum of Unit Selling Area2",PIVOT!$A$227,"PREMIUM CATEGORY","A")*E10 -> 3096.2531 | G10: =GETPIVOTDATA("Sum of Unit Selling Area2",PIVOT!$A$227,"PREMIUM CATEGORY","B")*E10 -> 3444.7134 | H10: =GETPIVOTDATA("Sum of Unit Selling Area2",PIVOT!$A$227,"PREMIUM CATEGORY","C")*E10 -> 3981.5135 | J10: =$J$2*(1+C10) -> 252000 | K10: =$K$2*(1+C10) -> 53550 | L10: =$L$2*(1+C10) -> 59850 | M10: =AVERAGE(K10:L10) -> 56700 | N10: =L10-K10 -> 6300 | O10: =N10/K10 -> 0.11764706 | P10: =K10-K9 -> 1700 | Q10: =N10-$N$2 -> 1300 | R10: =C10-C9 -> 0.04 | S10: 0.085 | T10: 0.33
A11: =EDATE(A10,3) -> 46023 | B11: R 10 | C11: 0.32 | D11: 0.03 | E11: =131531*D11 -> 3945.93 | F11: =GETPIVOTDATA("Sum of Unit Selling Area2",PIVOT!$A$227,"PREMIUM CATEGORY","A")*E11 -> 1161.0949 | G11: =GETPIVOTDATA("Sum of Unit Selling Area2",PIVOT!$A$227,"PREMIUM CATEGORY","B")*E11 -> 1291.7675 | H11: =GETPIVOTDATA("Sum of Unit Selling Area2",PIVOT!$A$227,"PREMIUM CATEGORY","C")*E11 -> 1493.0676 | J11: =$J$2*(1+C11) -> 264000 | K11: =$K$2*(1+C11) -> 56100 | L11: =$L$2*(1+C11) -> 62700 | M11: =AVERAGE(K11:L11) -> 59400 | N11: =L11-K11 -> 6600 | O11: =N11/K11 -> 0.11764706 | P11: =K11-K10 -> 2550 | Q11: =N11-$N$2 -> 1600 | R11: =C11-C10 -> 0.06 | S11: 0.085 | T11: 0.33
A12: =EDATE(A11,3) -> 46113 | B12: R 11 | C12: 0.38 | D12: 0.03 | E12: =131531*D12 -> 3945.93 | F12: =GETPIVOTDATA("Sum of Unit Selling Area2",PIVOT!$A$227,"PREMIUM CATEGORY","A")*E12 -> 1161.0949 | G12: =GETPIVOTDATA("Sum of Unit Selling Area2",PIVOT!$A$227,"PREMIUM CATEGORY","B")*E12 -> 1291.7675 | H12: =GETPIVOTDATA("Sum of Unit Selling Area2",PIVOT!$A$227,"PREMIUM CATEGORY","C")*E12 -> 1493.0676 | J12: =$J$2*(1+C12) -> 276000 | K12: =$K$2*(1+C12) -> 58650 | L12: =$L$2*(1+C12) -> 65550 | M12: =AVERAGE(K12:L12) -> 62100 | N12: =L12-K12 -> 6900 | O12: =N12/K12 -> 0.11764706 | P12: =K12-K11 -> 2550 | Q12: =N12-$N$2 -> 1900 | R12: =C12-C11 -> 0.06 | S12: 0.085 | T12: 0.33
A13: =EDATE(A12,3) -> 46204 | B13: R 12 | C13: 0.45 | D13: 0.09 | E13: =131531*D13 -> 11837.79 | F13: =GETPIVOTDATA("Sum of Unit Selling Area2",PIVOT!$A$227,"PREMIUM CATEGORY","A")*E13 -> 3483.2847 | G13: =GETPIVOTDATA("Sum of Unit Selling Area2",PIVOT!$A$227,"PREMIUM CATEGORY","B")*E13 -> 3875.3026 | H13: =GETPIVOTDATA("Sum of Unit Selling Area2",PIVOT!$A$227,"PREMIUM CATEGORY","C")*E13 -> 4479.2027 | J13: =$J$2*(1+C13) -> 290000 | K13: =$K$2*(1+C13) -> 61625 | L13: =$L$2*(1+C13) -> 68875 | M13: =AVERAGE(K13:L13) -> 65250 | N13: =L13-K13 -> 7250 | O13: =N13/K13 -> 0.11764706 | P13: =K13-K12 -> 2975 | Q13: =N13-$N$2 -> 2250 | R13: =C13-C12 -> 0.07 | S13: 0.085 | T13: 0.33
A14: =EDATE(A8,3) -> 45839 | B14: RH | C14: =C9 -> 0.22 | D14: 1 | E14: 4434 | F14: 0 | G14: 2808 | H14: 1626 | J14: =J9 -> 244000 | K14: =K9+25000 -> 76850 | L14: =L9+25000 -> 82950 | M14: =M9+25000 -> 79900 | N14: =L14-K14 -> 6100 | S14: 0.2 | T14: 0.33
F15: COMMULATIVE | G15: COMMULATIVE | H15: COMMULATIVE
A16: CATEGORY | B16: AREA RANGE | C16: NO. OF CAR PARKING | E16: R1 | F16: =F2 -> 6579.5378 | G16: =G2 -> 7320.0161 | H16: =H2 -> 8460.7162
A17: HOTEL | B17: 0-89M2 | C17: 1 | E17: R2 | F17: =F16+F3 -> 9288.7592 | G17: =G16+G3 -> 10334.14 | H17: =H16+H3 -> 11944.54
A18: A | B18: 0-89M2 | C18: 1 | E18: R3 | F18: =F17+F4 -> 11997.981 | G18: =G17+G4 -> 13348.265 | H18: =H17+H4 -> 15428.365
A19: B | B19: 90-122M2 | C19: 1 | E19: R4 | F19: =F18+F5 -> 16255.329 | G19: =G18+G5 -> 18084.746 | H19: =H18+H5 -> 20902.946
A20: C | B20: 123-160M2 | C20: 2 | E20: R5 | F20: =F19+F6 -> 19351.582 | G20: =G19+G6 -> 21529.459 | H20: =H19+H6 -> 24884.459
A21: D | B21: 161-185M2 | C21: 2 | E21: R6 | F21: =F20+F7 -> 22060.803 | G21: =G20+G7 -> 24543.583 | H21: =H20+H7 -> 28368.284
A22: E | B22: 186-230M2 | C22: 2 | E22: R7 | F22: =F21+F8 -> 25157.056 | G22: =G21+G8 -> 27988.297 | H22: =H21+H8 -> 32349.797
A23: F | B23: 230-350M2 | C23: 2 | E23: R8 | F23: =F22+F9 -> 29801.436 | G23: =G22+G9 -> 33155.367 | H23: =H22+H9 -> 38322.067
E24: R9 | F24: =F23+F10 -> 32897.689 | G24: =G23+G10 -> 36600.08 | H24: =H23+H10 -> 42303.581
E25: R10 | F25: =F24+F11 -> 34058.784 | G25: =G24+G11 -> 37891.848 | H25: =H24+H11 -> 43796.648
E26: R11 | F26: =F25+F12 -> 35219.879 | G26: =G25+G12 -> 39183.615 | H26: =H25+H12 -> 45289.716
E27: R12 | F27: =F26+F13 -> 38703.163 | G27: =G26+G13 -> 43058.918 | H27: =H26+H13 -> 49768.919

Sheet PREMIUM TABLES
G3: FLOOR PREMIUM
G4: FLOOR NAME | H4: PREMIUM %
G5: GROUND | H5: 0.05
G6: FIRST | H6: 0.07
G7: SECOND | H7: 0.11
G8: THIRD | H8: 0.15
G9: FORTH | H9: 0.06
G11: SELLING PHASES
G12: BUILDING NO. | H12: PHASE NO.
G13: A1 | H13: R1
G14: A2 | H14: R2
G15: A3 | H15: R2
G16: A4 | H16: R1
G17: B1 | H17: R3
G18: B2 | H18: R4
G19: B3 | H19: R4
G20: B4 | H20: R3
G21: C1 | H21: R4
G22: C2 | H22: R7
G23: C3 | H23: R3
... G55: F5 | H55: R6
G57: INTERNAL LOCATION
G58: BUILDING NO. | H58: PHASE NO.
G59: A1 | H59: CV
G60: A2 | H60: M
G61: A3 | H61: M
G62: A4 | H62: CV
G63: A5 | H63: CV
G64: A6 | H64: M
G65: A7 | H65: M
G66: A8 | H66: CV
G67: B1 | H67: CV
G68: B2 | H68: CV
G69: B3 | H69: CV
... G101: E5 | H101: C3
G105: CONSTRUCTION PHASES
G106: BUILDING NO. | H106: PHASE NO.
G107: A1 | H107: C1
G108: A2 | H108: C1
G109: A3 | H109: C1
G110: A4 | H110: C1
G111: A5 | H111: C1
G112: A6 | H112: C1
G113: A7 | H113: C1
G114: A8 | H114: C1
G115: B1 | H115: C1
G116: B2 | H116: C1
G117: B3 | H117: C1
... G149: E5 | H149: C3
G151: Project Premiums
G152: Premium Name | H152: Premium %
G153: View | H153: 0.6
G154: Orientation | H154: 0.15
G155: Floor | H155: 0.15
G156: Internal Location | H156: 0.05
G157: Area | H157: 0.05
G163: ORIENTATION PREMIUM
G164: ORIENTATION | H164: PREMIUM %
G165: NE | H165: 0.15
G166: N | H166: 0.14
G167: NW | H167: 0.13
G168: E | H168: 0.1
G169: W | H169: 0.1
G170: SE | H170: 0.08
G171: SW | H171: 0.06
G172: S | H172: 0.05
G173: VIEW PREMIUM
G174: VIEW | H174: PREMIUM %
G175: LAKE B-1 | H175: 0.6
G176: LAKE B-2 | H176: 0.53
G177: SEMI LAKE B-1 | H177: =0.8*H175 -> 0.48
G178: SEMI LAKE B-2 | H178: =0.8*H176 -> 0.424
G179: LAKE C | H179: 0.46
G180: LAKE D | H180: 0.43
G181: LAKE E | H181: 0.43
G182: SEMI LAKE D | H182: =0.75*H180 -> 0.3225
G183: SEMI LAKE E | H183: =0.75*H181 -> 0.3225
G184: LAKE F | H184: 0.3
G185: LAKE A-1 | H185: 0.4
G186: LAKE A-2 | H186: 0.4
G187: COMMERCIAL & PLAYCOURT | H187: 0.3
G188: MAIN GATE & LAKE ENTRANCE | H188: 0.25
G189: SECONDARY GATE | H189: 0.2
G190: ROAD 18M (VILLAS) | H190: 0.16
G191: ROAD 18M (BUILDINGS) | H191: 0.15
G192: LAYAN VILLAS | H192: 0.2
G193: ROAD 12M | H193: 0.13
G194: SEMI LAKE AND FENCE | H194: 0.25
G195: FENCE | H195: 0.1
F197: AREA PREMIUM
F198: CATEGORY | G198: AREA RANGE | H198: PREMIUM %
F199: HOTEL | G199: 0-89M2 | H199: 0.05
F200: A | G200: 0-89M2 | H200: 0.05
F201: B | G201: 90-122M2 | H201: 0.04
F202: C | G202: 123-160M2 | H202: 0.035
F203: D | G203: 161-185M2 | H203: 0.025
F204: E | G204: 186-230M2 | H204: 0.015
F205: F | G205: 230-350M2 | H205: 0
G206: INTERNAL LOCATION PREMIUM
G207: INTERNAL LOCATION | H207: PREMIUM %
...

Sheet C PHASES
G8: CONSTRUCTION PHASES
G9: Column1 | H9: Column2
G10: BUILDING NO. | H10: PHASE NO.
G11: A1 | H11: C1
G12: A2 | H12: C1
G13: A3 | H13: C1
G14: A4 | H14: C1
G15: A5 | H15: C1
G16: A6 | H16: C1
G17: A7 | H17: C1
G18: A8 | H18: C1
G19: B1 | H19: C1
G20: B2 | H20: C1
... G53: E5 | H53: C3
L87: A1 | M87: B6 | N87: D1
L88: A2 | M88: B7 | N88: D2
L89: A3 | M89: B8 | N89: D3
L90: A4 | M90: B9 | N90: D4
L91: A5 | M91: B10 | N91: D5
L92: A6 | M92: B11 | N92: E1
L93: A7 | M93: B12 | N93: E2
L94: A8 | M94: B13 | N94: E3
L95: B1 | M95: B14 | N95: E4
L96: B2 | M96: C1 | N96: E5
L97: B3 | M97: C2
L98: B4 | M98: C3
L99: B5 | M99: C4
L100: B15 | M100: C5
L101: B16 | M101: C6
L102: B17
L103: B18
L104: B19
I107: CONSTRUCTION PHASE | J107: DELIVERY TIME | K107: DELIVERY PERIOD
I108: C1 | J108: 45839 | K108: 3 YEARS
I109: C2 | J109: 46204
I110: C3 | J110: 46569
I113: R 1 | J113: 45170
I114: R 2 | J114: 45292
I115: R 3 | J115: =EDATE(J114,3) -> 45383
I116: R 4 | J116: =EDATE(J115,3) -> 45474
I117: R 5 | J117: =EDATE(J116,3) -> 45566
I118: R 6 | J118: =EDATE(J117,3) -> 45658
I119: R 7 | J119: =EDATE(J118,3) -> 45748
I120: R 8 | J120: =EDATE(J119,3) -> 45839
I121: RH | J121: =J120 -> 45839
I122: R 9 | J122: =EDATE(J121,3) -> 45931
I123: R 10 | J123: =EDATE(J122,3) -> 46023
I124: R 11 | J124: =EDATE(J123,3) -> 46113
I125: R 12 | J125: =EDATE(J124,3) -> 46204

Sheet PIVOT
A3: PREMIUM % | B3: Count of UnitS
A4: 0.275 | B4: 1
A5: 0.285 | B5: 2
A6: 0.31 | B6: 1
A7: 0.32 | B7: 2
A8: 0.32 | B8: 2
A9: 0.325 | B9: 2
A10: 0.325 | B10: 4
A11: 0.33 | B11: 1
A12: 0.33 | B12: 2
A13: 0.335 | B13: 3
A14: 0.34 | B14: 5
A15: 0.345 | B15: 6
... A220: 0.72 | B220: 1
A221: Grand Total | B221: 858
A227: PREMIUM % | B227: Count of Unit Number | C227: Sum of Unit Selling Area | D227: Sum of Unit Selling Area2
A228: A | B228: 204 | C228: 38732 | D228: 0.29425127
A229: B | B229: 253 | C229: 43091 | D229: 0.32736707
A230: C | B230: 345 | C230: 49806 | D230: 0.37838166
A231: Grand Total | B231: 802 | C231: 131629 | D231: 1
A233: PREMIUM CATEGORY | B233: C
A235: PREMIUM % | B235: Sum of Unit Selling Area
A236: 0.275 | B236: 111
A237: A602 | B237: 111
A238: 0.32 | B238: 340
A239: B141 | B239: 170
A240: B244 | B240: 170
A241: 0.32 | B241: 340
A242: C141 | B242: 170
A243: C344 | B243: 170
A244: 0.325 | B244: 232
A245: B101 | B245: 116
A246: B204 | B246: 116
A247: 0.325 | B247: 448
A248: C101 | B248: 116
A249: C304 | B249: 116
A250: E101 | B250: 108
A251: E204 | B251: 108
A252: 0.33 | B252: 173
A253: C201 | B253: 173
A254: 0.33 | B254: 306
A255: E141 | B255: 153
A256: E244 | B256: 153
A257: 0.335 | B257: 513
A258: B104 | B258: 176
A259: B201 | B259: 176
A260: E104 | B260: 161
A261: 0.34 | B261: 833
A262: B401 | B262: 160
A263: B701 | B263: 173
A264: C241 | B264: 170
A265: C244 | B265: 170
A266: D201 | B266: 160
A267: 0.345 | B267: 703
A268: A204 | B268: 121
A269: A301 | B269: 121
A270: A303 | B270: 111
A271: B111 | B271: 117
A272: B214 | B272: 117
A273: C204 | B273: 116
A274: 0.345 | B274: 796
A275: B144 | B275: 173
A276: B241 | B276: 173
A277: C111 | B277: 117
A278: C314 | B278: 117
A279: E111 | B279: 108
A280: E214 | B280: 108
A281: 0.35 | B281: 854
A282: B641 | B282: 170
A283: B741 | B283: 170
A284: B744 | B284: 170
A285: B844 | B285: 170
A286: C211 | B286: 174
A287: 0.355 | B287: 1937
A288: A104 | B288: 75
A289: A144 | B289: 110
A290: A201 | B290: 75
A291: A241 | B291: 110
A292: A244 | B292: 120
A293: A304 | B293: 75
A294: A341 | B294: 120
A295: A344 | B295: 110
A296: B301 | B296: 106
A297: B404 | B297: 106
A298: B504 | B298: 106
A299: B601 | B299: 116
... A305: E144 | B305: 158
A306: 0.355 | B306: 346
A307: B114 | B307: 173
A308: B211 | B308: 173
A309: 0.36 | B309: 1234
A310: B341 | B310: 153
A311: B441 | B311: 158
A312: B444 | B312: 153
A313: B544 | B313: 153
A314: D141 | B314: 153
A315: D241 | B315: 158
A316: D244 | B316: 153
A317: D344 | B317: 153
A318: 0.36 | B318: 498
...

Sheet GANNT CHART
A3: LAUNCH PHASE | V3: RH | AH3: CLOSING PHASE
B4: R1 | E4: R2 | H4: R3 | K4: R4 | N4: R5 | Q4: R6 | T4: R7 | W4: R8 | Z4: R9 | AC4: R10 | AF4: R11 | AI4: R12
C9: YEAR 2023 | G9: YEAR 2024 | S9: YEAR 2025 | AE9: YEAR 2026 | AQ9: YEAR 2027
C16: 1 | D16: 2 | E16: 3 | F16: 4
G18: 5 | H18: 6 | I18: 7 | J18: 8 | K18: 9 | L18: 10 | M18: 11 | N18: 12 | O18: 13 | P18: 14 | Q18: 15 | R18: 16 | S18: 17 | T18: 18 | U18: 19 | V18: 20 | W18: 21 | X18: 22
S20: 17 | T20: 18 | U20: 19 | V20: 20 | W20: 21 | X20: 22 | Y20: 23 | Z20: 24 | AA20: 25 | AB20: 26 | AC20: 27 | AD20: 28 | AE20: 29 | AF20: 30 | AG20: 31 | AH20: 32 | AI20: 33 | AJ20: 34
P21: 14 | Q21: 15 | R21: 16
AE22: 29 | AF22: 30 | AG22: 31 | AH22: 32 | AI22: 33 | AJ22: 34 | AK22: 35 | AL22: 36 | AM22: 37 | AN22: 38 | AO22: 39 | AP22: 40 | AQ22: 41 | AR22: 42 | AS22: 43 | AT22: 44 | AU22: 45 | AV22: 46
AB23: 26 | AC23: 27 | AD23: 28
AK24: 35 | AL24: 36 | AM24: 37 | AN24: 38 | AO24: 39 | AP24: 40 | AQ24: 41 | AR24: 42 | AS24: 43 | AT24: 44 | AU24: 45 | AV24: 46 | AW24: 47 | AX24: 48 | AY24: 49
AH25: 32 | AI25: 33 | AJ25: 34
A39: 45170 | H39: TENDERING & LICENSING | O39: CONSTRUCTION PHASE (C1) RESIDENTIAL | X39: CONSTRUCTION PHASE (C2) RESIDENTIAL | AG39: CONSTRUCTION PHASE (C3) RESIDENTIAL | AP39: CONSTRUCTION PHASE (C4) COMMERCIAL | AX39: 46631
O42: A1 | P42: A5 | Q42: B1 | R42: B5 | S42: B18 | X42: B6 | Y42: B10 | Z42: B14 | AA42: C4 | AG42: D1 | AH42: D5 | AI42: E4
O43: A2 | P43: A6 | Q43: B2 | R43: B15 | S43: B19 | X43: B7 | Y43: B11 | Z43: C1 | AA43: C5 | AG43: D2 | AH43: E1 | AI43: E5
O44: A3 | P44: A7 | Q44: B3 | R44: B16 | X44: B8 | Y44: B12 | Z44: C2 | AA44: C6 | AG44: D3 | AH44: E2
O45: A4 | P45: A8 | Q45: B4 | R45: B17 | X45: B9 | Y45: B13 | Z45: C3 | AG45: D4 | AH45: E3

Sheet DATA FOR PIVOT
A4: BLD Type | B4: ZONE | C4: BLD No. | D4: BLD. TYPE | E4: Floor | F4: UNIT | G4: Unit Number | H4: NO. OF BEDROOMS | I4: CONSTRUCTION PHASE | J4: Unit Net Area | K4: Unit Gross Area | L4: Unit Selling Area | M4: Private Garden Area | N4: No. of Bedrooms2 | O4: ORIENTATION | P4: INTERNAL LOCATION | Q4: VIEW | R4: FLOOR2 | S4: AREA CATEGORY | T4: P1 | U4: P2 | V4: P3 | W4: P4 | X4: P5 | Y4: TOTAL PREMIUM % | Z4: PREMIUM CATEGORY | AA4: SELLING PHASE NAME | AB4: PHASE (BUILDING) STARTING PRICE | AC4: PHASE (BUILDING) CLOSING PRICE | AD4: PHASE PREMIUM RANGE | AE4: UNIT PREMIUM VALUE | AF4: UNIT (BUILDING) RATE (SEMI FINISHED) | AG4: UNIT (GARDEN) RATE | AH4: UNIT (BUILDING) RATE (BASIC FINISH) | AI4: UNIT (BUILDING) RATE (FULLY FINISH) | AJ4: UNIT (BUILDING) VALUE SEMI FINISHED | AK4: UNIT (BUILDING) VALUE BASIC FINISHED | AL4: UNIT (BUILDING) VALUE FULLY FINISHED | AM4: UNIT (GARDEN) VALUE | AN4: MAINTENANCE VALUE | AO4: MAX. NO. OF CAR PARKING | AP4: PARKING VALUE | AQ4: TOTAL CARS VALUE | AR4: TOTAL UNIT VALUE (SEMI FINISHED) | AS4: TOTAL UNIT VALUE (BASIC FINISHED) | AT4: TOTAL UNIT VALUE (FULLY FINISHED) | AU4: UNIT DELIVERY DATE | AV4: PHASE SELLING START DATE
A5: A | B5: =LEFT(C5,1) -> A | C5: A1 | D5: RESIDENTIAL | E5: 0 | F5: 1 | G5: =LEFT(C5,2)&E5&F5 -> A101 | H5: 2 BEDROOM | I5: =VLOOKUP(C5,'PREMIUM TABLES'!$G$107:$H$149,2,FALSE) -> C1 | J5: 110.32 | K5: 120.40866 | L5: 136 | M5: 42.7795 | O5: SE | P5: CORNER | Q5: ROAD 18M (BUILDINGS) | R5: =VLOOKUP(E5,'PREMIUM TABLES'!$F$214:$G$219,2,FALSE) -> GROUND | S5: {=IF(AND(L5>0,L5<90),"A",IF(AND(L5>90,L5<123),"B",IF(AND(L5>122,L5<159),"C",IF(AND(L5>159,L5<185),"D",IF(AND(L5>185,L5<230),"E",IF(AND(L5>230,L5<350),"F",NONE))))))} -> C | T5: =VLOOKUP(O5,'PREMIUM TABLES'!$G$165:$H$172,2,FALSE) -> 0.08 | U5: =VLOOKUP(P5,'PREMIUM TABLES'!$G$208:$H$209,2,FALSE) -> 0.05 | V5: =VLOOKUP(Q5,'PREMIUM TABLES'!$G$175:$H$195,2,FALSE) -> 0.15 | W5: =VLOOKUP(R5,'PREMIUM TABLES'!$G$214:$H$219,2,FALSE) -> 0.05 | X5: =VLOOKUP(S5,'PREMIUM TABLES'!$F$199:$H$205,3,FALSE) -> 0.035 | Y5: =SUM(T5:X5) -> 0.365 | Z5: {=IF(AND(Y5>0,Y5<0.5),"C",IF(AND(Y5>=0.5,Y5<0.73),"B",IF(AND(Y5>=0.73,Y5<0.98),"A",NONE)))} -> C | AA5: =VLOOKUP(G5,'ALL (R)'!$N$5:$R$862,5,FALSE) -> R 2 | AB5: =VLOOKUP(AA5,FACTS!$B$2:$L$14,10,FALSE) -> 43562.5 | AC5: =VLOOKUP(AA5,FACTS!$B$2:$L$14,11,FALSE) -> 48687.5 | AD5: =VLOOKUP(AA5,FACTS!$B$2:$N$14,13,FALSE) -> 5125 | AE5: =AD5*Y5 -> 1870.625 | AF5: =AE5+AB5 -> 45433.125 | AG5: =AF5*FACTS!$T$2 -> 14992.931 | AH5: =Table1[[#This Row],[UNIT (BUILDING) RATE (SEMI FINISHED)]]+4500 -> 49933.125 | AI5: =Table1[[#This Row],[UNIT (BUILDING) RATE (SEMI FINISHED)]]+7500 -> 52933.125 | AJ5: =AF5*L5 -> 6178905 | AK5: =Table1[[#This Row],[UNIT (BUILDING) RATE (BASIC FINISH)]]*Table1[[#This Row],[Unit Selling Area]] -> 6790905 | AL5: =Table1[[#This Row],[UNIT (BUILDING) RATE (FULLY FINISH)]]*Table1[[#This Row],[Unit Selling Area]] -> 7198905 | AM5: =AG5*M5 -> 641390.1 | AN5: =(AM5+AJ5)*FACTS!$S$2 -> 579725.08 | AO5: =VLOOKUP(S5,FACTS!$A$17:$C$23,3,FALSE) -> 2 | AP5: =VLOOKUP(AA5,FACTS!$B$2:$J$14,9,FALSE) -> 205000 | AQ5: =Table1[[#This Row],[PARKING VALUE]]*1 -> 205000 | AR5: =AQ5+AM5+AJ5 -> 7025295.1 | AS5: =Table1[[#This Row],[TOTAL CARS VALUE]]+Table1[[#This Row],[UNIT (BUILDING) VALUE BASIC FINISHED]]+Table1[[#This Row],[UNIT (GARDEN) VALUE]] -> 7637295.1 | AT5: =Table1[[#This Row],[TOTAL CARS VALUE]]+Table1[[#This Row],[UNIT (GARDEN) VALUE]]+Table1[[#This Row],[UNIT (BUILDING) VALUE FULLY FINISHED]] -> 8045295.1 | AU5: =VLOOKUP(I5,'C PHASES'!$I$108:$J$110,2,FALSE) -> 45839 | AV5: =VLOOKUP(AA5,'C PHASES'!$I$113:$J$125,2,FALSE) -> 45292
B6: =LEFT(C6,1) -> A | C6: A1 | D6: RESIDENTIAL | E6: 0 | F6: 2 | G6: =LEFT(C6,2)&E6&F6 -> A102 | H6: 2 BEDROOM | I6: =VLOOKUP(C6,'PREMIUM TABLES'!$G$107:$H$149,2,FALSE) -> C1 | J6: 110.14 | K6: 120.2122 | L6: 135 | M6: 59.4821 | O6: NW | P6: CORNER | Q6: LAKE A-1 | R6: =VLOOKUP(E6,'PREMIUM TABLES'!$F$214:$G$219,2,FALSE) -> GROUND | S6: {=IF(AND(L6>0,L6<90),"A",IF(AND(L6>90,L6<123),"B",IF(AND(L6>122,L6<159),"C",IF(AND(L6>159,L6<185),"D",IF(AND(L6>185,L6<230),"E",IF(AND(L6>230,L6<350),"F",NONE))))))} -> C | T6: =VLOOKUP(O6,'PREMIUM TABLES'!$G$165:$H$172,2,FALSE) -> 0.13 | U6: =VLOOKUP(P6,'PREMIUM TABLES'!$G$208:$H$209,2,FALSE) -> 0.05 | V6: =VLOOKUP(Q6,'PREMIUM TABLES'!$G$175:$H$195,2,FALSE) -> 0.4 | W6: =VLOOKUP(R6,'PREMIUM TABLES'!$G$214:$H$219,2,FALSE) -> 0.05 | X6: =VLOOKUP(S6,'PREMIUM TABLES'!$F$199:$H$205,3,FALSE) -> 0.035 | Y6: =SUM(T6:X6) -> 0.665 | Z6: {=IF(AND(Y6>0,Y6<0.5),"C",IF(AND(Y6>=0.5,Y6<0.73),"B",IF(AND(Y6>=0.73,Y6<0.98),"A",NONE)))} -> B | AA6: =VLOOKUP(G6,'ALL (R)'!$N$5:$R$862,5,FALSE) -> R 6 | AB6: =VLOOKUP(AA6,FACTS!$B$2:$L$14,10,FALSE) -> 48450 | AC6: =VLOOKUP(AA6,FACTS!$B$2:$L$14,11,FALSE) -> 54150 | AD6: =VLOOKUP(AA6,FACTS!$B$2:$N$14,13,FALSE) -> 5700 | AE6: =AD6*Y6 -> 3790.5 | AF6: =AE6+AB6 -> 52240.5 | AG6: =AF6*FACTS!$T$2 -> 17239.365 | AH6: =Table1[[#This Row],[UNIT (BUILDING) RATE (SEMI FINISHED)]]+4500 -> 56740.5 | AI6: =Table1[[#This Row],[UNIT (BUILDING) RATE (SEMI FINISHED)]]+7500 -> 59740.5 | AJ6: =AF6*L6 -> 7052467.5 | AK6: =Table1[[#This Row],[UNIT (BUILDING) RATE (BASIC FINISH)]]*Table1[[#This Row],[Unit Selling Area]] -> 7659967.5 | AL6: =Table1[[#This Row],[UNIT (BUILDING) RATE (FULLY FINISH)]]*Table1[[#This Row],[Unit Selling Area]] -> 8064967.5 | AM6: =AG6*M6 -> 1025433.6 | AN6: =(AM6+AJ6)*FACTS!$S$2 -> 686621.6 | AO6: =VLOOKUP(S6,FACTS!$A$17:$C$23,3,FALSE) -> 2 | AP6: =VLOOKUP(AA6,FACTS!$B$2:$J$14,9,FALSE) -> 228000 | AQ6: =Table1[[#This Row],[PARKING VALUE]]*1 -> 228000 | AR6: =AQ6+AM6+AJ6 -> 8305901.1 | AS6: =Table1[[#This Row],[TOTAL CARS VALUE]]+Table1[[#This Row],[UNIT (BUILDING) VALUE BASIC FINISHED]]+Table1[[#This Row],[UNIT (GARDEN) VALUE]] -> 8913401.1 | AT6: =Table1[[#This Row],[TOTAL CARS VALUE]]+Table1[[#This Row],[UNIT (GARDEN) VALUE]]+Table1[[#This Row],[UNIT (BUILDING) VALUE FULLY FINISHED]] -> 9318401.1 | AU6: =VLOOKUP(I6,'C PHASES'!$I$108:$J$110,2,FALSE) -> 45839 | AV6: =VLOOKUP(AA6,'C PHASES'!$I$113:$J$125,2,FALSE) -> 45658
B7: =LEFT(C7,1) -> A | C7: A1 | D7: RESIDENTIAL | E7: 0 | F7: 3 | G7: =LEFT(C7,2)&E7&F7 -> A103 | H7: 2 BEDROOM | I7: =VLOOKUP(C7,'PREMIUM TABLES'!$G$107:$H$149,2,FALSE) -> C1 | J7: 89.96 | K7: 98.186758 | L7: 111 | M7: 50.5078 | O7: NW | P7: MIDDLE | Q7: LAKE A-1 | R7: =VLOOKUP(E7,'PREMIUM TABLES'!$F$214:$G$219,2,FALSE) -> GROUND | S7: {=IF(AND(L7>0,L7<90),"A",IF(AND(L7>90,L7<123),"B",IF(AND(L7>122,L7<159),"C",IF(AND(L7>159,L7<185),"D",IF(AND(L7>185,L7<230),"E",IF(AND(L7>230,L7<350),"F",NONE))))))} -> B | T7: =VLOOKUP(O7,'PREMIUM TABLES'!$G$165:$H$172,2,FALSE) -> 0.13 | U7: =VLOOKUP(P7,'PREMIUM TABLES'!$G$208:$H$209,2,FALSE) -> 0.025 | V7: =VLOOKUP(Q7,'PREMIUM TABLES'!$G$175:$H$195,2,FALSE) -> 0.4 | W7: =VLOOKUP(R7,'PREMIUM TABLES'!$G$214:$H$219,2,FALSE) -> 0.05 | X7: =VLOOKUP(S7,'PREMIUM TABLES'!$F$199:$H$205,3,FALSE) -> 0.04 | Y7: =SUM(T7:X7) -> 0.645 | Z7: {=IF(AND(Y7>0,Y7<0.5),"C",IF(AND(Y7>=0.5,Y7<0.73),"B",IF(AND(Y7>=0.73,Y7<0.98),"A",NONE)))} -> B | AA7: =VLOOKUP(G7,'ALL (R)'!$N$5:$R$862,5,FALSE) -> R 4 | AB7: =VLOOKUP(AA7,FACTS!$B$2:$L$14,10,FALSE) -> 45687.5 | AC7: =VLOOKUP(AA7,FACTS!$B$2:$L$14,11,FALSE) -> 51062.5 | AD7: =VLOOKUP(AA7,FACTS!$B$2:$N$14,13,FALSE) -> 5375 | AE7: =AD7*Y7 -> 3466.875 | AF7: =AE7+AB7 -> 49154.375 | AG7: =AF7*FACTS!$T$2 -> 16220.944 | AH7: =Table1[[#This Row],[UNIT (BUILDING) RATE (SEMI FINISHED)]]+4500 -> 53654.375 | AI7: =Table1[[#This Row],[UNIT (BUILDING) RATE (SEMI FINISHED)]]+7500 -> 56654.375 | AJ7: =AF7*L7 -> 5456135.6 | AK7: =Table1[[#This Row],[UNIT (BUILDING) RATE (BASIC FINISH)]]*Table1[[#This Row],[Unit Selling Area]] -> 5955635.6 | AL7: =Table1[[#This Row],[UNIT (BUILDING) RATE (FULLY FINISH)]]*Table1[[#This Row],[Unit Selling Area]] -> 6288635.6 | AM7: =AG7*M7 -> 819284.18 | AN7: =(AM7+AJ7)*FACTS!$S$2 -> 533410.68 | AO7: =VLOOKUP(S7,FACTS!$A$17:$C$23,3,FALSE) -> 1 | AP7: =VLOOKUP(AA7,FACTS!$B$2:$J$14,9,FALSE) -> 215000 | AQ7: =Table1[[#This Row],[PARKING VALUE]]*1 -> 215000 | AR7: =AQ7+AM7+AJ7 -> 6490419.8 | AS7: =Table1[[#This Row],[TOTAL CARS VALUE]]+Table1[[#This Row],[UNIT (BUILDING) VALUE BASIC FINISHED]]+Table1[[#This Row],[UNIT (GARDEN) VALUE]] -> 6989919.8 | AT7: =Table1[[#This Row],[TOTAL CARS VALUE]]+Table1[[#This Row],[UNIT (GARDEN) VALUE]]+Table1[[#This Row],[UNIT (BUILDING) VALUE FULLY FINISHED]] -> 7322919.8 | AU7: =VLOOKUP(I7,'C PHASES'!$I$108:$J$110,2,FALSE) -> 45839 | AV7: =VLOOKUP(AA7,'C PHASES'!$I$113:$J$125,2,FALSE) -> 45474
B8: =LEFT(C8,1) -> A | C8: A1 | D8: RESIDENTIAL | E8: 0 | F8: 4 | G8: =LEFT(C8,2)&E8&F8 -> A104 | H8: 1 BEDROOM (STUDIO) | I8: =VLOOKUP(C8,'PREMIUM TABLES'!$G$107:$H$149,2,FALSE) -> C1 | J8: 60.98 | K8: 66.556564 | L8: 75 | M8: 23.8084 | O8: SE | P8: MIDDLE | Q8: ROAD 18M (BUILDINGS) | R8: =VLOOKUP(E8,'PREMIUM TABLES'!$F$214:$G$219,2,FALSE) -> GROUND | S8: {=IF(AND(L8>0,L8<90),"A",IF(AND(L8>90,L8<123),"B",IF(AND(L8>122,L8<159),"C",IF(AND(L8>159,L8<185),"D",IF(AND(L8>185,L8<230),"E",IF(AND(L8>230,L8<350),"F",NONE))))))} -> A | T8: =VLOOKUP(O8,'PREMIUM TABLES'!$G$165:$H$172,2,FALSE) -> 0.08 | U8: =VLOOKUP(P8,'PREMIUM TABLES'!$G$208:$H$209,2,FALSE) -> 0.025 | V8: =VLOOKUP(Q8,'PREMIUM TABLES'!$G$175:$H$195,2,FALSE) -> 0.15 | W8: =VLOOKUP(R8,'PREMIUM TABLES'!$G$214:$H$219,2,FALSE) -> 0.05 | X8: =VLOOKUP(S8,'PREMIUM TABLES'!$F$199:$H$205,3,FALSE) -> 0.05 | Y8: =SUM(T8:X8) -> 0.355 | Z8: {=IF(AND(Y8>0,Y8<0.5),"C",IF(AND(Y8>=0.5,Y8<0.73),"B",IF(AND(Y8>=0.73,Y8<0.98),"A",NONE)))} -> C | AA8: =VLOOKUP(G8,'ALL (R)'!$N$5:$R$862,5,FALSE) -> R 1 | AB8: =VLOOKUP(AA8,FACTS!$B$2:$L$14,10,FALSE) -> 42500 | AC8: =VLOOKUP(AA8,FACTS!$B$2:$L$14,11,FALSE) -> 47500 | AD8: =VLOOKUP(AA8,FACTS!$B$2:$N$14,13,FALSE) -> 5000 | AE8: =AD8*Y8 -> 1775 | AF8: =AE8+AB8 -> 44275 | AG8: =AF8*FACTS!$T$2 -> 14610.75 | AH8: =Table1[[#This Row],[UNIT (BUILDING) RATE (SEMI FINISHED)]]+4500 -> 48775 | AI8: =Table1[[#This Row],[UNIT (BUILDING) RATE (SEMI FINISHED)]]+7500 -> 51775 | AJ8: =AF8*L8 -> 3320625 | AK8: =Table1[[#This Row],[UNIT (BUILDING) RATE (BASIC FINISH)]]*Table1[[#This Row],[Unit Selling Area]] -> 3658125 | AL8: =Table1[[#This Row],[UNIT (BUILDING) RATE (FULLY FINISH)]]*Table1[[#This Row],[Unit Selling Area]] -> 3883125 | AM8: =AG8*M8 -> 347858.58 | AN8: =(AM8+AJ8)*FACTS!$S$2 -> 311821.1 | AO8: =VLOOKUP(S8,FACTS!$A$17:$C$23,3,FALSE) -> 1 | AP8: =VLOOKUP(AA8,FACTS!$B$2:$J$14,9,FALSE) -> 200000 | AQ8: =Table1[[#This Row],[PARKING VALUE]]*1 -> 200000 | AR8: =AQ8+AM8+AJ8 -> 3868483.6 | AS8: =Table1[[#This Row],[TOTAL CARS VALUE]]+Table1[[#This Row],[UNIT (BUILDING) VALUE BASIC FINISHED]]+Table1[[#This Row],[UNIT (GARDEN) VALUE]] -> 4205983.6 | AT8: =Table1[[#This Row],[TOTAL CARS VALUE]]+Table1[[#This Row],[UNIT (GARDEN) VALUE]]+Table1[[#This Row],[UNIT (BUILDING) VALUE FULLY FINISHED]] -> 4430983.6 | AU8: =VLOOKUP(I8,'C PHASES'!$I$108:$J$110,2,FALSE) -> 45839 | AV8: =VLOOKUP(AA8,'C PHASES'!$I$113:$J$125,2,FALSE) -> 45170
B9: =LEFT(C9,1) -> A | C9: A1 | D9: RESIDENTIAL | E9: 1 | F9: 1 | G9: =LEFT(C9,2)&E9&F9 -> A111 | H9: 2 BEDROOM | I9: =VLOOKUP(C9,'PREMIUM TABLES'!$G$107:$H$149,2,FALSE) -> C1 | J9: 110.61 | K9: 120.72518 | L9: 136 | O9: SE | P9: CORNER | Q9: ROAD 18M (BUILDINGS) | R9: =VLOOKUP(E9,'PREMIUM TABLES'!$F$214:$G$219,2,FALSE) -> FIRST | S9: {=IF(AND(L9>0,L9<90),"A",IF(AND(L9>90,L9<123),"B",IF(AND(L9>122,L9<159),"C",IF(AND(L9>159,L9<185),"D",IF(AND(L9>185,L9<230),"E",IF(AND(L9>230,L9<350),"F",NONE))))))} -> C | T9: =VLOOKUP(O9,'PREMIUM TABLES'!$G$165:$H$172,2,FALSE) -> 0.08 | U9: =VLOOKUP(P9,'PREMIUM TABLES'!$G$208:$H$209,2,FALSE) -> 0.05 | V9: =VLOOKUP(Q9,'PREMIUM TABLES'!$G$175:$H$195,2,FALSE) -> 0.15 | W9: =VLOOKUP(R9,'PREMIUM TABLES'!$G$214:$H$219,2,FALSE) -> 0.07 | X9: =VLOOKUP(S9,'PREMIUM TABLES'!$F$199:$H$205,3,FALSE) -> 0.035 | Y9: =SUM(T9:X9) -> 0.385 | Z9: {=IF(AND(Y9>0,Y9<0.5),"C",IF(AND(Y9>=0.5,Y9<0.73),"B",IF(AND(Y9>=0.73,Y9<0.98),"A",NONE)))} -> C | AA9: =VLOOKUP(G9,'ALL (R)'!$N$5:$R$862,5,FALSE) -> R 4 | AB9: =VLOOKUP(AA9,FACTS!$B$2:$L$14,10,FALSE) -> 45687.5 | AC9: =VLOOKUP(AA9,FACTS!$B$2:$L$14,11,FALSE) -> 51062.5 | AD9: =VLOOKUP(AA9,FACTS!$B$2:$N$14,13,FALSE) -> 5375 | AE9: =AD9*Y9 -> 2069.375 | AF9: =AE9+AB9 -> 47756.875 | AG9: =AF9*FACTS!$T$2 -> 15759.769 | AH9: =Table1[[#This Row],[UNIT (BUILDING) RATE (SEMI FINISHED)]]+4500 -> 52256.875 | AI9: =Table1[[#This Row],[UNIT (BUILDING) RATE (SEMI FINISHED)]]+7500 -> 55256.875 | AJ9: =AF9*L9 -> 6494935 | AK9: =Table1[[#This Row],[UNIT (BUILDING) RATE (BASIC FINISH)]]*Table1[[#This Row],[Unit Selling Area]] -> 7106935 | AL9: =Table1[[#This Row],[UNIT (BUILDING) RATE (FULLY FINISH)]]*Table1[[#This Row],[Unit Selling Area]] -> 7514935 | AM9: =AG9*M9 -> 0 | AN9: =(AM9+AJ9)*FACTS!$S$2 -> 552069.48 | AO9: =VLOOKUP(S9,FACTS!$A$17:$C$23,3,FALSE) -> 2 | AP9: =VLOOKUP(AA9,FACTS!$B$2:$J$14,9,FALSE) -> 215000 | AQ9: =Table1[[#This Row],[PARKING VALUE]]*1 -> 215000 | AR9: =AQ9+AM9+AJ9 -> 6709935 | AS9: =Table1[[#This Row],[TOTAL CARS VALUE]]+Table1[[#This Row],[UNIT (BUILDING) VALUE BASIC FINISHED]]+Table1[[#This Row],[UNIT (GARDEN) VALUE]] -> 7321935 | AT9: =Table1[[#This Row],[TOTAL CARS VALUE]]+Table1[[#This Row],[UNIT (GARDEN) VALUE]]+Table1[[#This Row],[UNIT (BUILDING) VALUE FULLY FINISHED]] -> 7729935 | AU9: =VLOOKUP(I9,'C PHASES'!$I$108:$J$110,2,FALSE) -> 45839 | AV9: =VLOOKUP(AA9,'C PHASES'!$I$113:$J$125,2,FALSE) -> 45474
B10: =LEFT(C10,1) -> A | C10: A1 | D10: RESIDENTIAL | E10: 1 | F10: 2 | G10: =LEFT(C10,2)&E10&F10 -> A112 | H10: 2 BEDROOM | I10: =VLOOKUP(C10,'PREMIUM TABLES'!$G$107:$H$149,2,FALSE) -> C1 | J10: 110.14 | K10: 120.2122 | L10: 135 | O10: NW | P10: CORNER | Q10: LAKE A-1 | R10: =VLOOKUP(E10,'PREMIUM TABLES'!$F$214:$G$219,2,FALSE) -> FIRST | S10: {=IF(AND(L10>0,L10<90),"A",IF(AND(L10>90,L10<123),"B",IF(AND(L10>122,L10<159),"C",IF(AND(L10>159,L10<185),"D",IF(AND(L10>185,L10<230),"E",IF(AND(L10>230,L10<350),"F",NONE))))))} -> C | T10: =VLOOKUP(O10,'PREMIUM TABLES'!$G$165:$H$172,2,FALSE) -> 0.13 | U10: =VLOOKUP(P10,'PREMIUM TABLES'!$G$208:$H$209,2,FALSE) -> 0.05 | V10: =VLOOKUP(Q10,'PREMIUM TABLES'!$G$175:$H$195,2,FALSE) -> 0.4 | W10: =VLOOKUP(R10,'PREMIUM TABLES'!$G$214:$H$219,2,FALSE) -> 0.07 | X10: =VLOOKUP(S10,'PREMIUM TABLES'!$F$199:$H$205,3,FALSE) -> 0.035 | Y10: =SUM(T10:X10) -> 0.685 | Z10: {=IF(AND(Y10>0,Y10<0.5),"C",IF(AND(Y10>=0.5,Y10<0.73),"B",IF(AND(Y10>=0.73,Y10<0.98),"A",NONE)))} -> B | AA10: =VLOOKUP(G10,'ALL (R)'!$N$5:$R$862,5,FALSE) -> R 8 | AB10: =VLOOKUP(AA10,FACTS!$B$2:$L$14,10,FALSE) -> 51850 | AC10: =VLOOKUP(AA10,FACTS!$B$2:$L$14,11,FALSE) -> 57950 | AD10: =VLOOKUP(AA10,FACTS!$B$2:$N$14,13,FALSE) -> 6100 | AE10: =AD10*Y10 -> 4178.5 | AF10: =AE10+AB10 -> 56028.5 | AG10: =AF10*FACTS!$T$2 -> 18489.405 | AH10: =Table1[[#This Row],[UNIT (BUILDING) RATE (SEMI FINISHED)]]+4500 -> 60528.5 | AI10: =Table1[[#This Row],[UNIT (BUILDING) RATE (SEMI FINISHED)]]+7500 -> 63528.5 | AJ10: =AF10*L10 -> 7563847.5 | AK10: =Table1[[#This Row],[UNIT (BUILDING) RATE (BASIC FINISH)]]*Table1[[#This Row],[Unit Selling Area]] -> 8171347.5 | AL10: =Table1[[#This Row],[UNIT (BUILDING) RATE (FULLY FINISH)]]*Table1[[#This Row],[Unit Selling Area]] -> 8576347.5 | AM10: =AG10*M10 -> 0 | AN10: =(AM10+AJ10)*FACTS!$S$2 -> 642927.04 | AO10: =VLOOKUP(S10,FACTS!$A$17:$C$23,3,FALSE) -> 2 | AP10: =VLOOKUP(AA10,FACTS!$B$2:$J$14,9,FALSE) -> 244000 | AQ10: =Table1[[#This Row],[PARKING VALUE]]*1 -> 244000 | AR10: =AQ10+AM10+AJ10 -> 7807847.5 | AS10: =Table1[[#This Row],[TOTAL CARS VALUE]]+Table1[[#This Row],[UNIT (BUILDING) VALUE BASIC FINISHED]]+Table1[[#This Row],[UNIT (GARDEN) VALUE]] -> 8415347.5 | AT10: =Table1[[#This Row],[TOTAL CARS VALUE]]+Table1[[#This Row],[UNIT (GARDEN) VALUE]]+Table1[[#This Row],[UNIT (BUILDING) VALUE FULLY FINISHED]] -> 8820347.5 | AU10: =VLOOKUP(I10,'C PHASES'!$I$108:$J$110,2,FALSE) -> 45839 | AV10: =VLOOKUP(AA10,'C PHASES'!$I$113:$J$125,2,FALSE) -> 45839
B11: =LEFT(C11,1) -> A | C11: A1 | D11: RESIDENTIAL | E11: 1 | F11: 3 | G11: =LEFT(C11,2)&E11&F11 -> A113 | H11: 2 BEDROOM | I11: =VLOOKUP(C11,'PREMIUM TABLES'!$G$107:$H$149,2,FALSE) -> C1 | J11: 89.05 | K11: 97.193539 | L11: 110 | O11: NW | P11: MIDDLE | Q11: LAKE A-1 | R11: =VLOOKUP(E11,'PREMIUM TABLES'!$F$214:$G$219,2,FALSE) -> FIRST | S11: {=IF(AND(L11>0,L11<90),"A",IF(AND(L11>90,L11<123),"B",IF(AND(L11>122,L11<159),"C",IF(AND(L11>159,L11<185),"D",IF(AND(L11>185,L11<230),"E",IF(AND(L11>230,L11<350),"F",NONE))))))} -> B | T11: =VLOOKUP(O11,'PREMIUM TABLES'!$G$165:$H$172,2,FALSE) -> 0.13 | U11: =VLOOKUP(P11,'PREMIUM TABLES'!$G$208:$H$209,2,FALSE) -> 0.025 | V11: =VLOOKUP(Q11,'PREMIUM TABLES'!$G$175:$H$195,2,FALSE) -> 0.4 | W11: =VLOOKUP(R11,'PREMIUM TABLES'!$G$214:$H$219,2,FALSE) -> 0.07 | X11: =VLOOKUP(S11,'PREMIUM TABLES'!$F$199:$H$205,3,FALSE) -> 0.04 | Y11: =SUM(T11:X11) -> 0.665 | Z11: {=IF(AND(Y11>0,Y11<0.5),"C",IF(AND(Y11>=0.5,Y11<0.73),"B",IF(AND(Y11>=0.73,Y11<0.98),"A",NONE)))} -> B | AA11: =VLOOKUP(G11,'ALL (R)'!$N$5:$R$862,5,FALSE) -> R 5 | AB11: =VLOOKUP(AA11,FACTS!$B$2:$L$14,10,FALSE) -> 46750 | AC11: =VLOOKUP(AA11,FACTS!$B$2:$L$14,11,FALSE) -> 52250 | AD11: =VLOOKUP(AA11,FACTS!$B$2:$N$14,13,FALSE) -> 5500 | AE11: =AD11*Y11 -> 3657.5 | AF11: =AE11+AB11 -> 50407.5 | AG11: =AF11*FACTS!$T$2 -> 16634.475 | AH11: =Table1[[#This Row],[UNIT (BUILDING) RATE (SEMI FINISHED)]]+4500 -> 54907.5 | AI11: =Table1[[#This Row],[UNIT (BUILDING) RATE (SEMI FINISHED)]]+7500 -> 57907.5 | AJ11: =AF11*L11 -> 5544825 | AK11: =Table1[[#This Row],[UNIT (BUILDING) RATE (BASIC FINISH)]]*Table1[[#This Row],[Unit Selling Area]] -> 6039825 | AL11: =Table1[[#This Row],[UNIT (BUILDING) RATE (FULLY FINISH)]]*Table1[[#This Row],[Unit Selling Area]] -> 6369825 | AM11: =AG11*M11 -> 0 | AN11: =(AM11+AJ11)*FACTS!$S$2 -> 471310.13 | AO11: =VLOOKUP(S11,FACTS!$A$17:$C$23,3,FALSE) -> 1 | AP11: =VLOOKUP(AA11,FACTS!$B$2:$J$14,9,FALSE) -> 220000 | AQ11: =Table1[[#This Row],[PARKING VALUE]]*1 -> 220000 | AR11: =AQ11+AM11+AJ11 -> 5764825 | AS11: =Table1[[#This Row],[TOTAL CARS VALUE]]+Table1[[#This Row],[UNIT (BUILDING) VALUE BASIC FINISHED]]+Table1[[#This Row],[UNIT (GARDEN) VALUE]] -> 6259825 | AT11: =Table1[[#This Row],[TOTAL CARS VALUE]]+Table1[[#This Row],[UNIT (GARDEN) VALUE]]+Table1[[#This Row],[UNIT (BUILDING) VALUE FULLY FINISHED]] -> 6589825 | AU11: =VLOOKUP(I11,'C PHASES'!$I$108:$J$110,2,FALSE) -> 45839 | AV11: =VLOOKUP(AA11,'C PHASES'!$I$113:$J$125,2,FALSE) -> 45566
B12: =LEFT(C12,1) -> A | C12: A1 | D12: RESIDENTIAL | E12: 1 | F12: 4 | G12: =LEFT(C12,2)&E12&F12 -> A114 | H12: 1 BEDROOM (STUDIO) | I12: =VLOOKUP(C12,'PREMIUM TABLES'!$G$107:$H$149,2,FALSE) -> C1 | J12: 61.82 | K12: 67.473381 | L12: 76 | O12: SE | P12: MIDDLE | Q12: ROAD 18M (BUILDINGS) | R12: =VLOOKUP(E12,'PREMIUM TABLES'!$F$214:$G$219,2,FALSE) -> FIRST | S12: {=IF(AND(L12>0,L12<90),"A",IF(AND(L12>90,L12<123),"B",IF(AND(L12>122,L12<159),"C",IF(AND(L12>159,L12<185),"D",IF(AND(L12>185,L12<230),"E",IF(AND(L12>230,L12<350),"F",NONE))))))} -> A | T12: =VLOOKUP(O12,'PREMIUM TABLES'!$G$165:$H$172,2,FALSE) -> 0.08 | U12: =VLOOKUP(P12,'PREMIUM TABLES'!$G$208:$H$209,2,FALSE) -> 0.025 | V12: =VLOOKUP(Q12,'PREMIUM TABLES'!$G$175:$H$195,2,FALSE) -> 0.15 | W12: =VLOOKUP(R12,'PREMIUM TABLES'!$G$214:$H$219,2,FALSE) -> 0.07 | X12: =VLOOKUP(S12,'PREMIUM TABLES'!$F$199:$H$205,3,FALSE) -> 0.05 | Y12: =SUM(T12:X12) -> 0.375 | Z12: {=IF(AND(Y12>0,Y12<0.5),"C",IF(AND(Y12>=0.5,Y12<0.73),"B",IF(AND(Y12>=0.73,Y12<0.98),"A",NONE)))} -> C | AA12: =VLOOKUP(G12,'ALL (R)'!$N$5:$R$862,5,FALSE) -> R 3 | AB12: =VLOOKUP(AA12,FACTS!$B$2:$L$14,10,FALSE) -> 44625 | AC12: =VLOOKUP(AA12,FACTS!$B$2:$L$14,11,FALSE) -> 49875 | AD12: =VLOOKUP(AA12,FACTS!$B$2:$N$14,13,FALSE) -> 5250 | AE12: =AD12*Y12 -> 1968.75 | AF12: =AE12+AB12 -> 46593.75 | AG12: =AF12*FACTS!$T$2 -> 15375.938 | AH12: =Table1[[#This Row],[UNIT (BUILDING) RATE (SEMI FINISHED)]]+4500 -> 51093.75 | AI12: =Table1[[#This Row],[UNIT (BUILDING) RATE (SEMI FINISHED)]]+7500 -> 54093.75 | AJ12: =AF12*L12 -> 3541125 | AK12: =Table1[[#This Row],[UNIT (BUILDING) RATE (BASIC FINISH)]]*Table1[[#This Row],[Unit Selling Area]] -> 3883125 | AL12: =Table1[[#This Row],[UNIT (BUILDING) RATE (FULLY FINISH)]]*Table1[[#This Row],[Unit Selling Area]] -> 4111125 | AM12: =AG12*M12 -> 0 | AN12: =(AM12+AJ12)*FACTS!$S$2 -> 300995.62 | AO12: =VLOOKUP(S12,FACTS!$A$17:$C$23,3,FALSE) -> 1 | AP12: =VLOOKUP(AA12,FACTS!$B$2:$J$14,9,FALSE) -> 210000 | AQ12: =Table1[[#This Row],[PARKING VALUE]]*1 -> 210000 | AR12: =AQ12+AM12+AJ12 -> 3751125 | AS12: =Table1[[#This Row],[TOTAL CARS VALUE]]+Table1[[#This Row],[UNIT (BUILDING) VALUE BASIC FINISHED]]+Table1[[#This Row],[UNIT (GARDEN) VALUE]] -> 4093125 | AT12: =Table1[[#This Row],[TOTAL CARS VALUE]]+Table1[[#This Row],[UNIT (GARDEN) VALUE]]+Table1[[#This Row],[UNIT (BUILDING) VALUE FULLY FINISHED]] -> 4321125 | AU12: =VLOOKUP(I12,'C PHASES'!$I$108:$J$110,2,FALSE) -> 45839 | AV12: =VLOOKUP(AA12,'C PHASES'!$I$113:$J$125,2,FALSE) -> 45383
B13: =LEFT(C13,1) -> A | C13: A1 | D13: RESIDENTIAL | E13: 2 | F13: 1 | G13: =LEFT(C13,2)&E13&F13 -> A121 | H13: 2 BEDROOM | I13: =VLOOKUP(C13,'PREMIUM TABLES'!$G$107:$H$149,2,FALSE) -> C1 | J13: 112.2 | K13: 122.46059 | L13: 138 | O13: SE | P13: CORNER | Q13: ROAD 18M (BUILDINGS) | R13: =VLOOKUP(E13,'PREMIUM TABLES'!$F$214:$G$219,2,FALSE) -> SECOND | S13: {=IF(AND(L13>0,L13<90),"A",IF(AND(L13>90,L13<123),"B",IF(AND(L13>122,L13<159),"C",IF(AND(L13>159,L13<185),"D",IF(AND(L13>185,L13<230),"E",IF(AND(L13>230,L13<350),"F",NONE))))))} -> C | T13: =VLOOKUP(O13,'PREMIUM TABLES'!$G$165:$H$172,2,FALSE) -> 0.08 | U13: =VLOOKUP(P13,'PREMIUM TABLES'!$G$208:$H$209,2,FALSE) -> 0.05 | V13: =VLOOKUP(Q13,'PREMIUM TABLES'!$G$175:$H$195,2,FALSE) -> 0.15 | W13: =VLOOKUP(R13,'PREMIUM TABLES'!$G$214:$H$219,2,FALSE) -> 0.11 | X13: =VLOOKUP(S13,'PREMIUM TABLES'!$F$199:$H$205,3,FALSE) -> 0.035 | Y13: =SUM(T13:X13) -> 0.425 | Z13: {=IF(AND(Y13>0,Y13<0.5),"C",IF(AND(Y13>=0.5,Y13<0.73),"B",IF(AND(Y13>=0.73,Y13<0.98),"A",NONE)))} -> C | AA13: =VLOOKUP(G13,'ALL (R)'!$N$5:$R$862,5,FALSE) -> R 8 | AB13: =VLOOKUP(AA13,FACTS!$B$2:$L$14,10,FALSE) -> 51850 | AC13: =VLOOKUP(AA13,FACTS!$B$2:$L$14,11,FALSE) -> 57950 | AD13: =VLOOKUP(AA13,FACTS!$B$2:$N$14,13,FALSE) -> 6100 | AE13: =AD13*Y13 -> 2592.5 | AF13: =AE13+AB13 -> 54442.5 | AG13: =AF13*FACTS!$T$2 -> 17966.025 | AH13: =Table1[[#This Row],[UNIT (BUILDING) RATE (SEMI FINISHED)]]+4500 -> 58942.5 | AI13: =Table1[[#This Row],[UNIT (BUILDING) RATE (SEMI FINISHED)]]+7500 -> 61942.5 | AJ13: =AF13*L13 -> 7513065 | AK13: =Table1[[#This Row],[UNIT (BUILDING) RATE (BASIC FINISH)]]*Table1[[#This Row],[Unit Selling Area]] -> 8134065 | AL13: =Table1[[#This Row],[UNIT (BUILDING) RATE (FULLY FINISH)]]*Table1[[#This Row],[Unit Selling Area]] -> 8548065 | AM13: =AG13*M13 -> 0 | AN13: =(AM13+AJ13)*FACTS!$S$2 -> 638610.53 | AO13: =VLOOKUP(S13,FACTS!$A$17:$C$23,3,FALSE) -> 2 | AP13: =VLOOKUP(AA13,FACTS!$B$2:$J$14,9,FALSE) -> 244000 | AQ13: =Table1[[#This Row],[PARKING VALUE]]*1 -> 244000 | AR13: =AQ13+AM13+AJ13 -> 7757065 | AS13: =Table1[[#This Row],[TOTAL CARS VALUE]]+Table1[[#This Row],[UNIT (BUILDING) VALUE BASIC FINISHED]]+Table1[[#This Row],[UNIT (GARDEN) VALUE]] -> 8378065 | AT13: =Table1[[#This Row],[TOTAL CARS VALUE]]+Table1[[#This Row],[UNIT (GARDEN) VALUE]]+Table1[[#This Row],[UNIT (BUILDING) VALUE FULLY FINISHED]] -> 8792065 | AU13: =VLOOKUP(I13,'C PHASES'!$I$108:$J$110,2,FALSE) -> 45839 | AV13: =VLOOKUP(AA13,'C PHASES'!$I$113:$J$125,2,FALSE) -> 45839
B14: =LEFT(C14,1) -> A | C14: A1 | D14: RESIDENTIAL | E14: 2 | F14: 2 | G14: =LEFT(C14,2)&E14&F14 -> A122 | H14: 2 BEDROOM | I14: =VLOOKUP(C14,'PREMIUM TABLES'!$G$107:$H$149,2,FALSE) -> C1 | J14: 112.2 | K14: 122.46059 | L14: 138 | O14: NW | P14: CORNER | Q14: LAKE A-1 | R14: =VLOOKUP(E14,'PREMIUM TABLES'!$F$214:$G$219,2,FALSE) -> SECOND | S14: {=IF(AND(L14>0,L14<90),"A",IF(AND(L14>90,L14<123),"B",IF(AND(L14>122,L14<159),"C",IF(AND(L14>159,L14<185),"D",IF(AND(L14>185,L14<230),"E",IF(AND(L14>230,L14<350),"F",NONE))))))} -> C | T14: =VLOOKUP(O14,'PREMIUM TABLES'!$G$165:$H$172,2,FALSE) -> 0.13 | U14: =VLOOKUP(P14,'PREMIUM TABLES'!$G$208:$H$209,2,FALSE) -> 0.05 | V14: =VLOOKUP(Q14,'PREMIUM TABLES'!$G$175:$H$195,2,FALSE) -> 0.4 | W14: =VLOOKUP(R14,'PREMIUM TABLES'!$G$214:$H$219,2,FALSE) -> 0.11 | X14: =VLOOKUP(S14,'PREMIUM TABLES'!$F$199:$H$205,3,FALSE) -> 0.035 | Y14: =SUM(T14:X14) -> 0.725 | Z14: {=IF(AND(Y14>0,Y14<0.5),"C",IF(AND(Y14>=0.5,Y14<0.73),"B",IF(AND(Y14>=0.73,Y14<0.98),"A",NONE)))} -> B | AA14: =VLOOKUP(G14,'ALL (R)'!$N$5:$R$862,5,FALSE) -> R 12 | AB14: =VLOOKUP(AA14,FACTS!$B$2:$L$14,10,FALSE) -> 61625 | AC14: =VLOOKUP(AA14,FACTS!$B$2:$L$14,11,FALSE) -> 68875 | AD14: =VLOOKUP(AA14,FACTS!$B$2:$N$14,13,FALSE) -> 7250 | AE14: =AD14*Y14 -> 5256.25 | AF14: =AE14+AB14 -> 66881.25 | AG14: =AF14*FACTS!$T$2 -> 22070.812 | AH14: =Table1[[#This Row],[UNIT (BUILDING) RATE (SEMI FINISHED)]]+4500 -> 71381.25 | AI14: =Table1[[#This Row],[UNIT (BUILDING) RATE (SEMI FINISHED)]]+7500 -> 74381.25 | AJ14: =AF14*L14 -> 9229612.5 | AK14: =Table1[[#This Row],[UNIT (BUILDING) RATE (BASIC FINISH)]]*Table1[[#This Row],[Unit Selling Area]] -> 9850612.5 | AL14: =Table1[[#This Row],[UNIT (BUILDING) RATE (FULLY FINISH)]]*Table1[[#This Row],[Unit Selling Area]] -> 10264612 | AM14: =AG14*M14 -> 0 | AN14: =(AM14+AJ14)*FACTS!$S$2 -> 784517.06 | AO14: =VLOOKUP(S14,FACTS!$A$17:$C$23,3,FALSE) -> 2 | AP14: =VLOOKUP(AA14,FACTS!$B$2:$J$14,9,FALSE) -> 290000 | AQ14: =Table1[[#This Row],[PARKING VALUE]]*1 -> 290000 | AR14: =AQ14+AM14+AJ14 -> 9519612.5 | AS14: =Table1[[#This Row],[TOTAL CARS VALUE]]+Table1[[#This Row],[UNIT (BUILDING) VALUE BASIC FINISHED]]+Table1[[#This Row],[UNIT (GARDEN) VALUE]] -> 10140612 | AT14: =Table1[[#This Row],[TOTAL CARS VALUE]]+Table1[[#This Row],[UNIT (GARDEN) VALUE]]+Table1[[#This Row],[UNIT (BUILDING) VALUE FULLY FINISHED]] -> 10554612 | AU14: =VLOOKUP(I14,'C PHASES'!$I$108:$J$110,2,FALSE) -> 45839 | AV14: =VLOOKUP(AA14,'C PHASES'!$I$113:$J$125,2,FALSE) -> 46204
B15: =LEFT(C15,1) -> A | C15: A1 | D15: RESIDENTIAL | E15: 2 | F15: 3 | G15: =LEFT(C15,2)&E15&F15 -> A123 | H15: 2 BEDROOM | I15: =VLOOKUP(C15,'PREMIUM TABLES'!$G$107:$H$149,2,FALSE) -> C1 | J15: 90.91 | K15: 99.223635 | L15: 112 | O15: NW | P15: MIDDLE | Q15: LAKE A-1 | R15: =VLOOKUP(E15,'PREMIUM TABLES'!$F$214:$G$219,2,FALSE) -> SECOND | S15: {=IF(AND(L15>0,L15<90),"A",IF(AND(L15>90,L15<123),"B",IF(AND(L15>122,L15<159),"C",IF(AND(L15>159,L15<185),"D",IF(AND(L15>185,L15<230),"E",IF(AND(L15>230,L15<350),"F",NONE))))))} -> B | T15: =VLOOKUP(O15,'PREMIUM TABLES'!$G$165:$H$172,2,FALSE) -> 0.13 | U15: =VLOOKUP(P15,'PREMIUM TABLES'!$G$208:$H$209,2,FALSE) -> 0.025 | V15: =VLOOKUP(Q15,'PREMIUM TABLES'!$G$175:$H$195,2,FALSE) -> 0.4 | W15: =VLOOKUP(R15,'PREMIUM TABLES'!$G$214:$H$219,2,FALSE) -> 0.11 | X15: =VLOOKUP(S15,'PREMIUM TABLES'!$F$199:$H$205,3,FALSE) -> 0.04 | Y15: =SUM(T15:X15) -> 0.705 | Z15: {=IF(AND(Y15>0,Y15<0.5),"C",IF(AND(Y15>=0.5,Y15<0.73),"B",IF(AND(Y15>=0.73,Y15<0.98),"A",NONE)))} -> B | AA15: =VLOOKUP(G15,'ALL (R)'!$N$5:$R$862,5,FALSE) -> R 10 | AB15: =VLOOKUP(AA15,FACTS!$B$2:$L$14,10,FALSE) -> 56100 | AC15: =VLOOKUP(AA15,FACTS!$B$2:$L$14,11,FALSE) -> 62700 | AD15: =VLOOKUP(AA15,FACTS!$B$2:$N$14,13,FALSE) -> 6600 | AE15: =AD15*Y15 -> 4653 | AF15: =AE15+AB15 -> 60753 | AG15: =AF15*FACTS!$T$2 -> 20048.49 | AH15: =Table1[[#This Row],[UNIT (BUILDING) RATE (SEMI FINISHED)]]+4500 -> 65253 | AI15: =Table1[[#This Row],[UNIT (BUILDING) RATE (SEMI FINISHED)]]+7500 -> 68253 | AJ15: =AF15*L15 -> 6804336 | AK15: =Table1[[#This Row],[UNIT (BUILDING) RATE (BASIC FINISH)]]*Table1[[#This Row],[Unit Selling Area]] -> 7308336 | AL15: =Table1[[#This Row],[UNIT (BUILDING) RATE (FULLY FINISH)]]*Table1[[#This Row],[Unit Selling Area]] -> 7644336 | AM15: =AG15*M15 -> 0 | AN15: =(AM15+AJ15)*FACTS!$S$2 -> 578368.56 | AO15: =VLOOKUP(S15,FACTS!$A$17:$C$23,3,FALSE) -> 1 | AP15: =VLOOKUP(AA15,FACTS!$B$2:$J$14,9,FALSE) -> 264000 | AQ15: =Table1[[#This Row],[PARKING VALUE]]*1 -> 264000 | AR15: =AQ15+AM15+AJ15 -> 7068336 | AS15: =Table1[[#This Row],[TOTAL CARS VALUE]]+Table1[[#This Row],[UNIT (BUILDING) VALUE BASIC FINISHED]]+Table1[[#This Row],[UNIT (GARDEN) VALUE]] -> 7572336 | AT15: =Table1[[#This Row],[TOTAL CARS VALUE]]+Table1[[#This Row],[UNIT (GARDEN) VALUE]]+Table1[[#This Row],[UNIT (BUILDING) VALUE FULLY FINISHED]] -> 7908336 | AU15: =VLOOKUP(I15,'C PHASES'!$I$108:$J$110,2,FALSE) -> 45839 | AV15: =VLOOKUP(AA15,'C PHASES'!$I$113:$J$125,2,FALSE) -> 46023
B16: =LEFT(C16,1) -> A | C16: A1 | D16: RESIDENTIAL | E16: 2 | F16: 4 | G16: =LEFT(C16,2)&E16&F16 -> A124 | H16: 2 BEDROOM | I16: =VLOOKUP(C16,'PREMIUM TABLES'!$G$107:$H$149,2,FALSE) -> C1 | J16: 90.91 | K16: 99.223635 | L16: 112 | O16: SE | P16: MIDDLE | Q16: ROAD 18M (BUILDINGS) | R16: =VLOOKUP(E16,'PREMIUM TABLES'!$F$214:$G$219,2,FALSE) -> SECOND | S16: {=IF(AND(L16>0,L16<90),"A",IF(AND(L16>90,L16<123),"B",IF(AND(L16>122,L16<159),"C",IF(AND(L16>159,L16<185),"D",IF(AND(L16>185,L16<230),"E",IF(AND(L16>230,L16<350),"F",NONE))))))} -> B | T16: =VLOOKUP(O16,'PREMIUM TABLES'!$G$165:$H$172,2,FALSE) -> 0.08 | U16: =VLOOKUP(P16,'PREMIUM TABLES'!$G$208:$H$209,2,FALSE) -> 0.025 | V16: =VLOOKUP(Q16,'PREMIUM TABLES'!$G$175:$H$195,2,FALSE) -> 0.15 | W16: =VLOOKUP(R16,'PREMIUM TABLES'!$G$214:$H$219,2,FALSE) -> 0.11 | X16: =VLOOKUP(S16,'PREMIUM TABLES'!$F$199:$H$205,3,FALSE) -> 0.04 | Y16: =SUM(T16:X16) -> 0.405 | Z16: {=IF(AND(Y16>0,Y16<0.5),"C",IF(AND(Y16>=0.5,Y16<0.73),"B",IF(AND(Y16>=0.73,Y16<0.98),"A",NONE)))} -> C | AA16: =VLOOKUP(G16,'ALL (R)'!$N$5:$R$862,5,FALSE) -> R 5 | AB16: =VLOOKUP(AA16,FACTS!$B$2:$L$14,10,FALSE) -> 46750 | AC16: =VLOOKUP(AA16,FACTS!$B$2:$L$14,11,FALSE) -> 52250 | AD16: =VLOOKUP(AA16,FACTS!$B$2:$N$14,13,FALSE) -> 5500 | AE16: =AD16*Y16 -> 2227.5 | AF16: =AE16+AB16 -> 48977.5 | AG16: =AF16*FACTS!$T$2 -> 16162.575 | AH16: =Table1[[#This Row],[UNIT (BUILDING) RATE (SEMI FINISHED)]]+4500 -> 53477.5 | AI16: =Table1[[#This Row],[UNIT (BUILDING) RATE (SEMI FINISHED)]]+7500 -> 56477.5 | AJ16: =AF16*L16 -> 5485480 | AK16: =Table1[[#This Row],[UNIT (BUILDING) RATE (BASIC FINISH)]]*Table1[[#This Row],[Unit Selling Area]] -> 5989480 | AL16: =Table1[[#This Row],[UNIT (BUILDING) RATE (FULLY FINISH)]]*Table1[[#This Row],[Unit Selling Area]] -> 6325480 | AM16: =AG16*M16 -> 0 | AN16: =(AM16+AJ16)*FACTS!$S$2 -> 466265.8 | AO16: =VLOOKUP(S16,FACTS!$A$17:$C$23,3,FALSE) -> 1 | AP16: =VLOOKUP(AA16,FACTS!$B$2:$J$14,9,FALSE) -> 220000 | AQ16: =Table1[[#This Row],[PARKING VALUE]]*1 -> 220000 | AR16: =AQ16+AM16+AJ16 -> 5705480 | AS16: =Table1[[#This Row],[TOTAL CARS VALUE]]+Table1[[#This Row],[UNIT (BUILDING) VALUE BASIC FINISHED]]+Table1[[#This Row],[UNIT (GARDEN) VALUE]] -> 6209480 | AT16: =Table1[[#This Row],[TOTAL CARS VALUE]]+Table1[[#This Row],[UNIT (GARDEN) VALUE]]+Table1[[#This Row],[UNIT (BUILDING) VALUE FULLY FINISHED]] -> 6545480 | AU16: =VLOOKUP(I16,'C PHASES'!$I$108:$J$110,2,FALSE) -> 45839 | AV16: =VLOOKUP(AA16,'C PHASES'!$I$113:$J$125,2,FALSE) -> 45566
B17: =LEFT(C17,1) -> A | C17: A1 | D17: RESIDENTIAL | E17: 3 | F17: 1 | G17: =LEFT(C17,2)&E17&F17 -> A131 | H17: 2 BEDROOM | I17: =VLOOKUP(C17,'PREMIUM TABLES'!$G$107:$H$149,2,FALSE) -> C1 | J17: 110.14 | K17: 120.2122 | L17: 135 | O17: SE | P17: CORNER | Q17: ROAD 18M (BUILDINGS) | R17: =VLOOKUP(E17,'PREMIUM TABLES'!$F$214:$G$219,2,FALSE) -> THIRD | S17: {=IF(AND(L17>0,L17<90),"A",IF(AND(L17>90,L17<123),"B",IF(AND(L17>122,L17<159),"C",IF(AND(L17>159,L17<185),"D",IF(AND(L17>185,L17<230),"E",IF(AND(L17>230,L17<350),"F",NONE))))))} -> C | T17: =VLOOKUP(O17,'PREMIUM TABLES'!$G$165:$H$172,2,FALSE) -> 0.08 | U17: =VLOOKUP(P17,'PREMIUM TABLES'!$G$208:$H$209,2,FALSE) -> 0.05 | V17: =VLOOKUP(Q17,'PREMIUM TABLES'!$G$175:$H$195,2,FALSE) -> 0.15 | W17: =VLOOKUP(R17,'PREMIUM TABLES'!$G$214:$H$219,2,FALSE) -> 0.15 | X17: =VLOOKUP(S17,'PREMIUM TABLES'!$F$199:$H$205,3,FALSE) -> 0.035 | Y17: =SUM(T17:X17) -> 0.465 | Z17: {=IF(AND(Y17>0,Y17<0.5),"C",IF(AND(Y17>=0.5,Y17<0.73),"B",IF(AND(Y17>=0.73,Y17<0.98),"A",NONE)))} -> C | AA17: =VLOOKUP(G17,'ALL (R)'!$N$5:$R$862,5,FALSE) -> R 11 | AB17: =VLOOKUP(AA17,FACTS!$B$2:$L$14,10,FALSE) -> 58650 | AC17: =VLOOKUP(AA17,FACTS!$B$2:$L$14,11,FALSE) -> 65550 | AD17: =VLOOKUP(AA17,FACTS!$B$2:$N$14,13,FALSE) -> 6900 | AE17: =AD17*Y17 -> 3208.5 | AF17: =AE17+AB17 -> 61858.5 | AG17: =AF17*FACTS!$T$2 -> 20413.305 | AH17: =Table1[[#This Row],[UNIT (BUILDING) RATE (SEMI FINISHED)]]+4500 -> 66358.5 | AI17: =Table1[[#This Row],[UNIT (BUILDING) RATE (SEMI FINISHED)]]+7500 -> 69358.5 | AJ17: =AF17*L17 -> 8350897.5 | AK17: =Table1[[#This Row],[UNIT (BUILDING) RATE (BASIC FINISH)]]*Table1[[#This Row],[Unit Selling Area]] -> 8958397.5 | AL17: =Table1[[#This Row],[UNIT (BUILDING) RATE (FULLY FINISH)]]*Table1[[#This Row],[Unit Selling Area]] -> 9363397.5 | AM17: =AG17*M17 -> 0 | AN17: =(AM17+AJ17)*FACTS!$S$2 -> 709826.29 | AO17: =VLOOKUP(S17,FACTS!$A$17:$C$23,3,FALSE) -> 2 | AP17: =VLOOKUP(AA17,FACTS!$B$2:$J$14,9,FALSE) -> 276000 | AQ17: =Table1[[#This Row],[PARKING VALUE]]*1 -> 276000 | AR17: =AQ17+AM17+AJ17 -> 8626897.5 | AS17: =Table1[[#This Row],[TOTAL CARS VALUE]]+Table1[[#This Row],[UNIT (BUILDING) VALUE BASIC FINISHED]]+Table1[[#This Row],[UNIT (GARDEN) VALUE]] -> 9234397.5 | AT17: =Table1[[#This Row],[TOTAL CARS VALUE]]+Table1[[#This Row],[UNIT (GARDEN) VALUE]]+Table1[[#This Row],[UNIT (BUILDING) VALUE FULLY FINISHED]] -> 9639397.5 | AU17: =VLOOKUP(I17,'C PHASES'!$I$108:$J$110,2,FALSE) -> 45839 | AV17: =VLOOKUP(AA17,'C PHASES'!$I$113:$J$125,2,FALSE) -> 46113
B18: =LEFT(C18,1) -> A | C18: A1 | D18: RESIDENTIAL | E18: 3 | F18: 2 | G18: =LEFT(C18,2)&E18&F18 -> A132 | H18: 2 BEDROOM | I18: =VLOOKUP(C18,'PREMIUM TABLES'!$G$107:$H$149,2,FALSE) -> C1 | J18: 110.14 | K18: 120.2122 | L18: 135 | O18: NW | P18: CORNER | Q18: LAKE A-1 | R18: =VLOOKUP(E18,'PREMIUM TABLES'!$F$214:$G$219,2,FALSE) -> THIRD | S18: {=IF(AND(L18>0,L18<90),"A",IF(AND(L18>90,L18<123),"B",IF(AND(L18>122,L18<159),"C",IF(AND(L18>159,L18<185),"D",IF(AND(L18>185,L18<230),"E",IF(AND(L18>230,L18<350),"F",NONE))))))} -> C | T18: =VLOOKUP(O18,'PREMIUM TABLES'!$G$165:$H$172,2,FALSE) -> 0.13 | U18: =VLOOKUP(P18,'PREMIUM TABLES'!$G$208:$H$209,2,FALSE) -> 0.05 | V18: =VLOOKUP(Q18,'PREMIUM TABLES'!$G$175:$H$195,2,FALSE) -> 0.4 | W18: =VLOOKUP(R18,'PREMIUM TABLES'!$G$214:$H$219,2,FALSE) -> 0.15 | X18: =VLOOKUP(S18,'PREMIUM TABLES'!$F$199:$H$205,3,FALSE) -> 0.035 | Y18: =SUM(T18:X18) -> 0.765 | Z18: {=IF(AND(Y18>0,Y18<0.5),"C",IF(AND(Y18>=0.5,Y18<0.73),"B",IF(AND(Y18>=0.73,Y18<0.98),"A",NONE)))} -> A | AA18: =VLOOKUP(G18,'ALL (R)'!$N$5:$R$862,5,FALSE) -> R 3 | AB18: =VLOOKUP(AA18,FACTS!$B$2:$L$14,10,FALSE) -> 44625 | AC18: =VLOOKUP(AA18,FACTS!$B$2:$L$14,11,FALSE) -> 49875 | AD18: =VLOOKUP(AA18,FACTS!$B$2:$N$14,13,FALSE) -> 5250 | AE18: =AD18*Y18 -> 4016.25 | AF18: =AE18+AB18 -> 48641.25 | AG18: =AF18*FACTS!$T$2 -> 16051.613 | AH18: =Table1[[#This Row],[UNIT (BUILDING) RATE (SEMI FINISHED)]]+4500 -> 53141.25 | AI18: =Table1[[#This Row],[UNIT (BUILDING) RATE (SEMI FINISHED)]]+7500 -> 56141.25 | AJ18: =AF18*L18 -> 6566568.8 | AK18: =Table1[[#This Row],[UNIT (BUILDING) RATE (BASIC FINISH)]]*Table1[[#This Row],[Unit Selling Area]] -> 7174068.8 | AL18: =Table1[[#This Row],[UNIT (BUILDING) RATE (FULLY FINISH)]]*Table1[[#This Row],[Unit Selling Area]] -> 7579068.8 | AM18: =AG18*M18 -> 0 | AN18: =(AM18+AJ18)*FACTS!$S$2 -> 558158.34 | AO18: =VLOOKUP(S18,FACTS!$A$17:$C$23,3,FALSE) -> 2 | AP18: =VLOOKUP(AA18,FACTS!$B$2:$J$14,9,FALSE) -> 210000 | AQ18: =Table1[[#This Row],[PARKING VALUE]]*1 -> 210000 | AR18: =AQ18+AM18+AJ18 -> 6776568.8 | AS18: =Table1[[#This Row],[TOTAL CARS VALUE]]+Table1[[#This Row],[UNIT (BUILDING) VALUE BASIC FINISHED]]+Table1[[#This Row],[UNIT (GARDEN) VALUE]] -> 7384068.8 | AT18: =Table1[[#This Row],[TOTAL CARS VALUE]]+Table1[[#This Row],[UNIT (GARDEN) VALUE]]+Table1[[#This Row],[UNIT (BUILDING) VALUE FULLY FINISHED]] -> 7789068.8 | AU18: =VLOOKUP(I18,'C PHASES'!$I$108:$J$110,2,FALSE) -> 45839 | AV18: =VLOOKUP(AA18,'C PHASES'!$I$113:$J$125,2,FALSE) -> 45383
B19: =LEFT(C19,1) -> A | C19: A1 | D19: RESIDENTIAL | E19: 3 | F19: 3 | G19: =LEFT(C19,2)&E19&F19 -> A133 | H19: 2 BEDROOM | I19: =VLOOKUP(C19,'PREMIUM TABLES'!$G$107:$H$149,2,FALSE) -> C1 | J19: 89.05 | K19: 97.193539 | L19: 110 | O19: NW | P19: MIDDLE | Q19: LAKE A-1 | R19: =VLOOKUP(E19,'PREMIUM TABLES'!$F$214:$G$219,2,FALSE) -> THIRD | S19: {=IF(AND(L19>0,L19<90),"A",IF(AND(L19>90,L19<123),"B",IF(AND(L19>122,L19<159),"C",IF(AND(L19>159,L19<185),"D",IF(AND(L19>185,L19<230),"E",IF(AND(L19>230,L19<350),"F",NONE))))))} -> B | T19: =VLOOKUP(O19,'PREMIUM TABLES'!$G$165:$H$172,2,FALSE) -> 0.13 | U19: =VLOOKUP(P19,'PREMIUM TABLES'!$G$208:$H$209,2,FALSE) -> 0.025 | V19: =VLOOKUP(Q19,'PREMIUM TABLES'!$G$175:$H$195,2,FALSE) -> 0.4 | W19: =VLOOKUP(R19,'PREMIUM TABLES'!$G$214:$H$219,2,FALSE) -> 0.15 | X19: =VLOOKUP(S19,'PREMIUM TABLES'!$F$199:$H$205,3,FALSE) -> 0.04 | Y19: =SUM(T19:X19) -> 0.745 | Z19: {=IF(AND(Y19>0,Y19<0.5),"C",IF(AND(Y19>=0.5,Y19<0.73),"B",IF(AND(Y19>=0.73,Y19<0.98),"A",NONE)))} -> A | AA19: =VLOOKUP(G19,'ALL (R)'!$N$5:$R$862,5,FALSE) -> R 2 | AB19: =VLOOKUP(AA19,FACTS!$B$2:$L$14,10,FALSE) -> 43562.5 | AC19: =VLOOKUP(AA19,FACTS!$B$2:$L$14,11,FALSE) -> 48687.5 | AD19: =VLOOKUP(AA19,FACTS!$B$2:$N$14,13,FALSE) -> 5125 | AE19: =AD19*Y19 -> 3818.125 | AF19: =AE19+AB19 -> 47380.625 | AG19: =AF19*FACTS!$T$2 -> 15635.606 | AH19: =Table1[[#This Row],[UNIT (BUILDING) RATE (SEMI FINISHED)]]+4500 -> 51880.625 | AI19: =Table1[[#This Row],[UNIT (BUILDING) RATE (SEMI FINISHED)]]+7500 -> 54880.625 | AJ19: =AF19*L19 -> 5211868.7 | AK19: =Table1[[#This Row],[UNIT (BUILDING) RATE (BASIC FINISH)]]*Table1[[#This Row],[Unit Selling Area]] -> 5706868.7 | AL19: =Table1[[#This Row],[UNIT (BUILDING) RATE (FULLY FINISH)]]*Table1[[#This Row],[Unit Selling Area]] -> 6036868.7 | AM19: =AG19*M19 -> 0 | AN19: =(AM19+AJ19)*FACTS!$S$2 -> 443008.84 | AO19: =VLOOKUP(S19,FACTS!$A$17:$C$23,3,FALSE) -> 1 | AP19: =VLOOKUP(AA19,FACTS!$B$2:$J$14,9,FALSE) -> 205000 | AQ19: =Table1[[#This Row],[PARKING VALUE]]*1 -> 205000 | AR19: =AQ19+AM19+AJ19 -> 5416868.7 | AS19: =Table1[[#This Row],[TOTAL CARS VALUE]]+Table1[[#This Row],[UNIT (BUILDING) VALUE BASIC FINISHED]]+Table1[[#This Row],[UNIT (GARDEN) VALUE]] -> 5911868.7 | AT19: =Table1[[#This Row],[TOTAL CARS VALUE]]+Table1[[#This Row],[UNIT (GARDEN) VALUE]]+Table1[[#This Row],[UNIT (BUILDING) VALUE FULLY FINISHED]] -> 6241868.7 | AU19: =VLOOKUP(I19,'C PHASES'!$I$108:$J$110,2,FALSE) -> 45839 | AV19: =VLOOKUP(AA19,'C PHASES'!$I$113:$J$125,2,FALSE) -> 45292
B20: =LEFT(C20,1) -> A | C20: A1 | D20: RESIDENTIAL | E20: 3 | F20: 4 | G20: =LEFT(C20,2)&E20&F20 -> A134 | H20: 2 BEDROOM | I20: =VLOOKUP(C20,'PREMIUM TABLES'!$G$107:$H$149,2,FALSE) -> C1 | J20: 89.05 | K20: 97.193539 | L20: 110 | O20: SE | P20: MIDDLE | Q20: ROAD 18M (BUILDINGS) | R20: =VLOOKUP(E20,'PREMIUM TABLES'!$F$214:$G$219,2,FALSE) -> THIRD | S20: {=IF(AND(L20>0,L20<90),"A",IF(AND(L20>90,L20<123),"B",IF(AND(L20>122,L20<159),"C",IF(AND(L20>159,L20<185),"D",IF(AND(L20>185,L20<230),"E",IF(AND(L20>230,L20<350),"F",NONE))))))} -> B | T20: =VLOOKUP(O20,'PREMIUM TABLES'!$G$165:$H$172,2,FALSE) -> 0.08 | U20: =VLOOKUP(P20,'PREMIUM TABLES'!$G$208:$H$209,2,FALSE) -> 0.025 | V20: =VLOOKUP(Q20,'PREMIUM TABLES'!$G$175:$H$195,2,FALSE) -> 0.15 | W20: =VLOOKUP(R20,'PREMIUM TABLES'!$G$214:$H$219,2,FALSE) -> 0.15 | X20: =VLOOKUP(S20,'PREMIUM TABLES'!$F$199:$H$205,3,FALSE) -> 0.04 | Y20: =SUM(T20:X20) -> 0.445 | Z20: {=IF(AND(Y20>0,Y20<0.5),"C",IF(AND(Y20>=0.5,Y20<0.73),"B",IF(AND(Y20>=0.73,Y20<0.98),"A",NONE)))} -> C | AA20: =VLOOKUP(G20,'ALL (R)'!$N$5:$R$862,5,FALSE) -> R 9 | AB20: =VLOOKUP(AA20,FACTS!$B$2:$L$14,10,FALSE) -> 53550 | AC20: =VLOOKUP(AA20,FACTS!$B$2:$L$14,11,FALSE) -> 59850 | AD20: =VLOOKUP(AA20,FACTS!$B$2:$N$14,13,FALSE) -> 6300 | AE20: =AD20*Y20 -> 2803.5 | AF20: =AE20+AB20 -> 56353.5 | AG20: =AF20*FACTS!$T$2 -> 18596.655 | AH20: =Table1[[#This Row],[UNIT (BUILDING) RATE (SEMI FINISHED)]]+4500 -> 60853.5 | AI20: =Table1[[#This Row],[UNIT (BUILDING) RATE (SEMI FINISHED)]]+7500 -> 63853.5 | AJ20: =AF20*L20 -> 6198885 | AK20: =Table1[[#This Row],[UNIT (BUILDING) RATE (BASIC FINISH)]]*Table1[[#This Row],[Unit Selling Area]] -> 6693885 | AL20: =Table1[[#This Row],[UNIT (BUILDING) RATE (FULLY FINISH)]]*Table1[[#This Row],[Unit Selling Area]] -> 7023885 | AM20: =AG20*M20 -> 0 | AN20: =(AM20+AJ20)*FACTS!$S$2 -> 526905.23 | AO20: =VLOOKUP(S20,FACTS!$A$17:$C$23,3,FALSE) -> 1 | AP20: =VLOOKUP(AA20,FACTS!$B$2:$J$14,9,FALSE) -> 252000 | AQ20: =Table1[[#This Row],[PARKING VALUE]]*1 -> 252000 | AR20: =AQ20+AM20+AJ20 -> 6450885 | AS20: =Table1[[#This Row],[TOTAL CARS VALUE]]+Table1[[#This Row],[UNIT (BUILDING) VALUE BASIC FINISHED]]+Table1[[#This Row],[UNIT (GARDEN) VALUE]] -> 6945885 | AT20: =Table1[[#This Row],[TOTAL CARS VALUE]]+Table1[[#This Row],[UNIT (GARDEN) VALUE]]+Table1[[#This Row],[UNIT (BUILDING) VALUE FULLY FINISHED]] -> 7275885 | AU20: =VLOOKUP(I20,'C PHASES'!$I$108:$J$110,2,FALSE) -> 45839 | AV20: =VLOOKUP(AA20,'C PHASES'!$I$113:$J$125,2,FALSE) -> 45931
... B24: =LEFT(C24,1) -> A | C24: A1 | D24: RESIDENTIAL | E24: 4 | F24: 4 | G24: =LEFT(C24,2)&E24&F24 -> A144 | H24: 2 BEDROOM | I24: =VLOOKUP(C24,'PREMIUM TABLES'!$G$107:$H$149,2,FALSE) -> C1 | J24: 89.12 | K24: 97.269941 | L24: 110 | O24: SE | P24: MIDDLE | Q24: ROAD 18M (BUILDINGS) | R24: =VLOOKUP(E24,'PREMIUM TABLES'!$F$214:$G$219,2,FALSE) -> FORTH | S24: {=IF(AND(L24>0,L24<90),"A",IF(AND(L24>90,L24<123),"B",IF(AND(L24>122,L24<159),"C",IF(AND(L24>159,L24<185),"D",IF(AND(L24>185,L24<230),"E",IF(AND(L24>230,L24<350),"F",NONE))))))} -> B | T24: =VLOOKUP(O24,'PREMIUM TABLES'!$G$165:$H$172,2,FALSE) -> 0.08 | U24: =VLOOKUP(P24,'PREMIUM TABLES'!$G$208:$H$209,2,FALSE) -> 0.025 | V24: =VLOOKUP(Q24,'PREMIUM TABLES'!$G$175:$H$195,2,FALSE) -> 0.15 | W24: =VLOOKUP(R24,'PREMIUM TABLES'!$G$214:$H$219,2,FALSE) -> 0.06 | X24: =VLOOKUP(S24,'PREMIUM TABLES'!$F$199:$H$205,3,FALSE) -> 0.04 | Y24: =SUM(T24:X24) -> 0.355 | Z24: {=IF(AND(Y24>0,Y24<0.5),"C",IF(AND(Y24>=0.5,Y24<0.73),"B",IF(AND(Y24>=0.73,Y24<0.98),"A",NONE)))} -> C | AA24: =VLOOKUP(G24,'ALL (R)'!$N$5:$R$862,5,FALSE) -> R 1 | AB24: =VLOOKUP(AA24,FACTS!$B$2:$L$14,10,FALSE) -> 42500 | AC24: =VLOOKUP(AA24,FACTS!$B$2:$L$14,11,FALSE) -> 47500 | AD24: =VLOOKUP(AA24,FACTS!$B$2:$N$14,13,FALSE) -> 5000 | AE24: =AD24*Y24 -> 1775 | AF24: =AE24+AB24 -> 44275 | AG24: =AF24*FACTS!$T$2 -> 14610.75 | AH24: =Table1[[#This Row],[UNIT (BUILDING) RATE (SEMI FINISHED)]]+4500 -> 48775 | AI24: =Table1[[#This Row],[UNIT (BUILDING) RATE (SEMI FINISHED)]]+7500 -> 51775 | AJ24: =AF24*L24 -> 4870250 | AK24: =Table1[[#This Row],[UNIT (BUILDING) RATE (BASIC FINISH)]]*Table1[[#This Row],[Unit Selling Area]] -> 5365250 | AL24: =Table1[[#This Row],[UNIT (BUILDING) RATE (FULLY FINISH)]]*Table1[[#This Row],[Unit Selling Area]] -> 5695250 | AM24: =AG24*M24 -> 0 | AN24: =(AM24+AJ24)*FACTS!$S$2 -> 413971.25 | AO24: =VLOOKUP(S24,FACTS!$A$17:$C$23,3,FALSE) -> 1 | AP24: =VLOOKUP(AA24,FACTS!$B$2:$J$14,9,FALSE) -> 200000 | AQ24: =Table1[[#This Row],[PARKING VALUE]]*1 -> 200000 | AR24: =AQ24+AM24+AJ24 -> 5070250 | AS24: =Table1[[#This Row],[TOTAL CARS VALUE]]+Table1[[#This Row],[UNIT (BUILDING) VALUE BASIC FINISHED]]+Table1[[#This Row],[UNIT (GARDEN) VALUE]] -> 5565250 | AT24: =Table1[[#This Row],[TOTAL CARS VALUE]]+Table1[[#This Row],[UNIT (GARDEN) VALUE]]+Table1[[#This Row],[UNIT (BUILDING) VALUE FULLY FINISHED]] -> 5895250 | AU24: =VLOOKUP(I24,'C PHASES'!$I$108:$J$110,2,FALSE) -> 45839 | AV24: =VLOOKUP(AA24,'C PHASES'!$I$113:$J$125,2,FALSE) -> 45170
A25: A | B25: =LEFT(C25,1) -> A | C25: A2 | D25: RESIDENTIAL | E25: 0 | F25: 1 | G25: =LEFT(C25,2)&E25&F25 -> A201 | H25: 1 BEDROOM (STUDIO) | I25: =VLOOKUP(C25,'PREMIUM TABLES'!$G$107:$H$149,2,FALSE) -> C1 | J25: 60.98 | K25: 66.8441 | L25: 75 | M25: 23.8084 | O25: SE | P25: MIDDLE | Q25: ROAD 18M (BUILDINGS) | R25: =VLOOKUP(E25,'PREMIUM TABLES'!$F$214:$G$219,2,FALSE) -> GROUND | S25: {=IF(AND(L25>0,L25<90),"A",IF(AND(L25>90,L25<123),"B",IF(AND(L25>122,L25<159),"C",IF(AND(L25>159,L25<185),"D",IF(AND(L25>185,L25<230),"E",IF(AND(L25>230,L25<350),"F",NONE))))))} -> A | T25: =VLOOKUP(O25,'PREMIUM TABLES'!$G$165:$H$172,2,FALSE) -> 0.08 | U25: =VLOOKUP(P25,'PREMIUM TABLES'!$G$208:$H$209,2,FALSE) -> 0.025 | V25: =VLOOKUP(Q25,'PREMIUM TABLES'!$G$175:$H$195,2,FALSE) -> 0.15 | W25: =VLOOKUP(R25,'PREMIUM TABLES'!$G$214:$H$219,2,FALSE) -> 0.05 | X25: =VLOOKUP(S25,'PREMIUM TABLES'!$F$199:$H$205,3,FALSE) -> 0.05 | Y25: =SUM(T25:X25) -> 0.355 | Z25: {=IF(AND(Y25>0,Y25<0.5),"C",IF(AND(Y25>=0.5,Y25<0.73),"B",IF(AND(Y25>=0.73,Y25<0.98),"A",NONE)))} -> C | AA25: =VLOOKUP(G25,'ALL (R)'!$N$5:$R$862,5,FALSE) -> R 1 | AB25: =VLOOKUP(AA25,FACTS!$B$2:$L$14,10,FALSE) -> 42500 | AC25: =VLOOKUP(AA25,FACTS!$B$2:$L$14,11,FALSE) -> 47500 | AD25: =VLOOKUP(AA25,FACTS!$B$2:$N$14,13,FALSE) -> 5000 | AE25: =AD25*Y25 -> 1775 | AF25: =AE25+AB25 -> 44275 | AG25: =AF25*FACTS!$T$2 -> 14610.75 | AH25: =Table1[[#This Row],[UNIT (BUILDING) RATE (SEMI FINISHED)]]+4500 -> 48775 | AI25: =Table1[[#This Row],[UNIT (BUILDING) RATE (SEMI FINISHED)]]+7500 -> 51775 | AJ25: =AF25*L25 -> 3320625 | AK25: =Table1[[#This Row],[UNIT (BUILDING) RATE (BASIC FINISH)]]*Table1[[#This Row],[Unit Selling Area]] -> 3658125 | AL25: =Table1[[#This Row],[UNIT (BUILDING) RATE (FULLY FINISH)]]*Table1[[#This Row],[Unit Selling Area]] -> 3883125 | AM25: =AG25*M25 -> 347858.58 | AN25: =(AM25+AJ25)*FACTS!$S$2 -> 311821.1 | AO25: =VLOOKUP(S25,FACTS!$A$17:$C$23,3,FALSE) -> 1 | AP25: =VLOOKUP(AA25,FACTS!$B$2:$J$14,9,FALSE) -> 200000 | AQ25: =Table1[[#This Row],[PARKING VALUE]]*1 -> 200000 | AR25: =AQ25+AM25+AJ25 -> 3868483.6 | AS25: =Table1[[#This Row],[TOTAL CARS VALUE]]+Table1[[#This Row],[UNIT (BUILDING) VALUE BASIC FINISHED]]+Table1[[#This Row],[UNIT (GARDEN) VALUE]] -> 4205983.6 | AT25: =Table1[[#This Row],[TOTAL CARS VALUE]]+Table1[[#This Row],[UNIT (GARDEN) VALUE]]+Table1[[#This Row],[UNIT (BUILDING) VALUE FULLY FINISHED]] -> 4430983.6 | AU25: =VLOOKUP(I25,'C PHASES'!$I$108:$J$110,2,FALSE) -> 45839 | AV25: =VLOOKUP(AA25,'C PHASES'!$I$113:$J$125,2,FALSE) -> 45170
B26: =LEFT(C26,1) -> A | C26: A2 | D26: RESIDENTIAL | E26: 0 | F26: 2 | G26: =LEFT(C26,2)&E26&F26 -> A202 | H26: 2 BEDROOM | I26: =VLOOKUP(C26,'PREMIUM TABLES'!$G$107:$H$149,2,FALSE) -> C1 | J26: 89.96 | K26: 98.610941 | L26: 111 | M26: 50.5039 | O26: NW | P26: MIDDLE | Q26: LAKE A-1 | R26: =VLOOKUP(E26,'PREMIUM TABLES'!$F$214:$G$219,2,FALSE) -> GROUND | S26: {=IF(AND(L26>0,L26<90),"A",IF(AND(L26>90,L26<123),"B",IF(AND(L26>122,L26<159),"C",IF(AND(L26>159,L26<185),"D",IF(AND(L26>185,L26<230),"E",IF(AND(L26>230,L26<350),"F",NONE))))))} -> B | T26: =VLOOKUP(O26,'PREMIUM TABLES'!$G$165:$H$172,2,FALSE) -> 0.13 | U26: =VLOOKUP(P26,'PREMIUM TABLES'!$G$208:$H$209,2,FALSE) -> 0.025 | V26: =VLOOKUP(Q26,'PREMIUM TABLES'!$G$175:$H$195,2,FALSE) -> 0.4 | W26: =VLOOKUP(R26,'PREMIUM TABLES'!$G$214:$H$219,2,FALSE) -> 0.05 | X26: =VLOOKUP(S26,'PREMIUM TABLES'!$F$199:$H$205,3,FALSE) -> 0.04 | Y26: =SUM(T26:X26) -> 0.645 | Z26: {=IF(AND(Y26>0,Y26<0.5),"C",IF(AND(Y26>=0.5,Y26<0.73),"B",IF(AND(Y26>=0.73,Y26<0.98),"A",NONE)))} -> B | AA26: =VLOOKUP(G26,'ALL (R)'!$N$5:$R$862,5,FALSE) -> R 4 | AB26: =VLOOKUP(AA26,FACTS!$B$2:$L$14,10,FALSE) -> 45687.5 | AC26: =VLOOKUP(AA26,FACTS!$B$2:$L$14,11,FALSE) -> 51062.5 | AD26: =VLOOKUP(AA26,FACTS!$B$2:$N$14,13,FALSE) -> 5375 | AE26: =AD26*Y26 -> 3466.875 | AF26: =AE26+AB26 -> 49154.375 | AG26: =AF26*FACTS!$T$2 -> 16220.944 | AH26: =Table1[[#This Row],[UNIT (BUILDING) RATE (SEMI FINISHED)]]+4500 -> 53654.375 | AI26: =Table1[[#This Row],[UNIT (BUILDING) RATE (SEMI FINISHED)]]+7500 -> 56654.375 | AJ26: =AF26*L26 -> 5456135.6 | AK26: =Table1[[#This Row],[UNIT (BUILDING) RATE (BASIC FINISH)]]*Table1[[#This Row],[Unit Selling Area]] -> 5955635.6 | AL26: =Table1[[#This Row],[UNIT (BUILDING) RATE (FULLY FINISH)]]*Table1[[#This Row],[Unit Selling Area]] -> 6288635.6 | AM26: =AG26*M26 -> 819220.92 | AN26: =(AM26+AJ26)*FACTS!$S$2 -> 533405.31 | AO26: =VLOOKUP(S26,FACTS!$A$17:$C$23,3,FALSE) -> 1 | AP26: =VLOOKUP(AA26,FACTS!$B$2:$J$14,9,FALSE) -> 215000 | AQ26: =Table1[[#This Row],[PARKING VALUE]]*1 -> 215000 | AR26: =AQ26+AM26+AJ26 -> 6490356.5 | AS26: =Table1[[#This Row],[TOTAL CARS VALUE]]+Table1[[#This Row],[UNIT (BUILDING) VALUE BASIC FINISHED]]+Table1[[#This Row],[UNIT (GARDEN) VALUE]] -> 6989856.5 | AT26: =Table1[[#This Row],[TOTAL CARS VALUE]]+Table1[[#This Row],[UNIT (GARDEN) VALUE]]+Table1[[#This Row],[UNIT (BUILDING) VALUE FULLY FINISHED]] -> 7322856.5 | AU26: =VLOOKUP(I26,'C PHASES'!$I$108:$J$110,2,FALSE) -> 45839 | AV26: =VLOOKUP(AA26,'C PHASES'!$I$113:$J$125,2,FALSE) -> 45474
B27: =LEFT(C27,1) -> A | C27: A2 | D27: RESIDENTIAL | E27: 0 | F27: 3 | G27: =LEFT(C27,2)&E27&F27 -> A203 | H27: 2 BEDROOM | I27: =VLOOKUP(C27,'PREMIUM TABLES'!$G$107:$H$149,2,FALSE) -> C1 | J27: 97.98 | K27: 107.40218 | L27: 121 | M27: 50.7053 | O27: NW | P27: MIDDLE | Q27: LAKE A-1 | R27: =VLOOKUP(E27,'PREMIUM TABLES'!$F$214:$G$219,2,FALSE) -> GROUND | S27: {=IF(AND(L27>0,L27<90),"A",IF(AND(L27>90,L27<123),"B",IF(AND(L27>122,L27<159),"C",IF(AND(L27>159,L27<185),"D",IF(AND(L27>185,L27<230),"E",IF(AND(L27>230,L27<350),"F",NONE))))))} -> B | T27: =VLOOKUP(O27,'PREMIUM TABLES'!$G$165:$H$172,2,FALSE) -> 0.13 | U27: =VLOOKUP(P27,'PREMIUM TABLES'!$G$208:$H$209,2,FALSE) -> 0.025 | V27: =VLOOKUP(Q27,'PREMIUM TABLES'!$G$175:$H$195,2,FALSE) -> 0.4 | W27: =VLOOKUP(R27,'PREMIUM TABLES'!$G$214:$H$219,2,FALSE) -> 0.05 | X27: =VLOOKUP(S27,'PREMIUM TABLES'!$F$199:$H$205,3,FALSE) -> 0.04 | Y27: =SUM(T27:X27) -> 0.645 | Z27: {=IF(AND(Y27>0,Y27<0.5),"C",IF(AND(Y27>=0.5,Y27<0.73),"B",IF(AND(Y27>=0.73,Y27<0.98),"A",NONE)))} -> B | AA27: =VLOOKUP(G27,'ALL (R)'!$N$5:$R$862,5,FALSE) -> R 4 | AB27: =VLOOKUP(AA27,FACTS!$B$2:$L$14,10,FALSE) -> 45687.5 | AC27: =VLOOKUP(AA27,FACTS!$B$2:$L$14,11,FALSE) -> 51062.5 | AD27: =VLOOKUP(AA27,FACTS!$B$2:$N$14,13,FALSE) -> 5375 | AE27: =AD27*Y27 -> 3466.875 | AF27: =AE27+AB27 -> 49154.375 | AG27: =AF27*FACTS!$T$2 -> 16220.944 | AH27: =Table1[[#This Row],[UNIT (BUILDING) RATE (SEMI FINISHED)]]+4500 -> 53654.375 | AI27: =Table1[[#This Row],[UNIT (BUILDING) RATE (SEMI FINISHED)]]+7500 -> 56654.375 | AJ27: =AF27*L27 -> 5947679.4 | AK27: =Table1[[#This Row],[UNIT (BUILDING) RATE (BASIC FINISH)]]*Table1[[#This Row],[Unit Selling Area]] -> 6492179.4 | AL27: =Table1[[#This Row],[UNIT (BUILDING) RATE (FULLY FINISH)]]*Table1[[#This Row],[Unit Selling Area]] -> 6855179.4 | AM27: =AG27*M27 -> 822487.82 | AN27: =(AM27+AJ27)*FACTS!$S$2 -> 575464.21 | AO27: =VLOOKUP(S27,FACTS!$A$17:$C$23,3,FALSE) -> 1 | AP27: =VLOOKUP(AA27,FACTS!$B$2:$J$14,9,FALSE) -> 215000 | AQ27: =Table1[[#This Row],[PARKING VALUE]]*1 -> 215000 | AR27: =AQ27+AM27+AJ27 -> 6985167.2 | AS27: =Table1[[#This Row],[TOTAL CARS VALUE]]+Table1[[#This Row],[UNIT (BUILDING) VALUE BASIC FINISHED]]+Table1[[#This Row],[UNIT (GARDEN) VALUE]] -> 7529667.2 | AT27: =Table1[[#This Row],[TOTAL CARS VALUE]]+Table1[[#This Row],[UNIT (GARDEN) VALUE]]+Table1[[#This Row],[UNIT (BUILDING) VALUE FULLY FINISHED]] -> 7892667.2 | AU27: =VLOOKUP(I27,'C PHASES'!$I$108:$J$110,2,FALSE) -> 45839 | AV27: =VLOOKUP(AA27,'C PHASES'!$I$113:$J$125,2,FALSE) -> 45474
B28: =LEFT(C28,1) -> A | C28: A2 | D28: RESIDENTIAL | E28: 0 | F28: 4 | G28: =LEFT(C28,2)&E28&F28 -> A204 | H28: 2 BEDROOM | I28: =VLOOKUP(C28,'PREMIUM TABLES'!$G$107:$H$149,2,FALSE) -> C1 | J28: 98.17 | K28: 107.61045 | L28: 121 | M28: 31.6139 | O28: SE | P28: MIDDLE | Q28: ROAD 18M (BUILDINGS) | R28: =VLOOKUP(E28,'PREMIUM TABLES'!$F$214:$G$219,2,FALSE) -> GROUND | S28: {=IF(AND(L28>0,L28<90),"A",IF(AND(L28>90,L28<123),"B",IF(AND(L28>122,L28<159),"C",IF(AND(L28>159,L28<185),"D",IF(AND(L28>185,L28<230),"E",IF(AND(L28>230,L28<350),"F",NONE))))))} -> B | T28: =VLOOKUP(O28,'PREMIUM TABLES'!$G$165:$H$172,2,FALSE) -> 0.08 | U28: =VLOOKUP(P28,'PREMIUM TABLES'!$G$208:$H$209,2,FALSE) -> 0.025 | V28: =VLOOKUP(Q28,'PREMIUM TABLES'!$G$175:$H$195,2,FALSE) -> 0.15 | W28: =VLOOKUP(R28,'PREMIUM TABLES'!$G$214:$H$219,2,FALSE) -> 0.05 | X28: =VLOOKUP(S28,'PREMIUM TABLES'!$F$199:$H$205,3,FALSE) -> 0.04 | Y28: =SUM(T28:X28) -> 0.345 | Z28: {=IF(AND(Y28>0,Y28<0.5),"C",IF(AND(Y28>=0.5,Y28<0.73),"B",IF(AND(Y28>=0.73,Y28<0.98),"A",NONE)))} -> C | AA28: =VLOOKUP(G28,'ALL (R)'!$N$5:$R$862,5,FALSE) -> R 1 | AB28: =VLOOKUP(AA28,FACTS!$B$2:$L$14,10,FALSE) -> 42500 | AC28: =VLOOKUP(AA28,FACTS!$B$2:$L$14,11,FALSE) -> 47500 | AD28: =VLOOKUP(AA28,FACTS!$B$2:$N$14,13,FALSE) -> 5000 | AE28: =AD28*Y28 -> 1725 | AF28: =AE28+AB28 -> 44225 | AG28: =AF28*FACTS!$T$2 -> 14594.25 | AH28: =Table1[[#This Row],[UNIT (BUILDING) RATE (SEMI FINISHED)]]+4500 -> 48725 | AI28: =Table1[[#This Row],[UNIT (BUILDING) RATE (SEMI FINISHED)]]+7500 -> 51725 | AJ28: =AF28*L28 -> 5351225 | AK28: =Table1[[#This Row],[UNIT (BUILDING) RATE (BASIC FINISH)]]*Table1[[#This Row],[Unit Selling Area]] -> 5895725 | AL28: =Table1[[#This Row],[UNIT (BUILDING) RATE (FULLY FINISH)]]*Table1[[#This Row],[Unit Selling Area]] -> 6258725 | AM28: =AG28*M28 -> 461381.16 | AN28: =(AM28+AJ28)*FACTS!$S$2 -> 494071.52 | AO28: =VLOOKUP(S28,FACTS!$A$17:$C$23,3,FALSE) -> 1 | AP28: =VLOOKUP(AA28,FACTS!$B$2:$J$14,9,FALSE) -> 200000 | AQ28: =Table1[[#This Row],[PARKING VALUE]]*1 -> 200000 | AR28: =AQ28+AM28+AJ28 -> 6012606.2 | AS28: =Table1[[#This Row],[TOTAL CARS VALUE]]+Table1[[#This Row],[UNIT (BUILDING) VALUE BASIC FINISHED]]+Table1[[#This Row],[UNIT (GARDEN) VALUE]] -> 6557106.2 | AT28: =Table1[[#This Row],[TOTAL CARS VALUE]]+Table1[[#This Row],[UNIT (GARDEN) VALUE]]+Table1[[#This Row],[UNIT (BUILDING) VALUE FULLY FINISHED]] -> 6920106.2 | AU28: =VLOOKUP(I28,'C PHASES'!$I$108:$J$110,2,FALSE) -> 45839 | AV28: =VLOOKUP(AA28,'C PHASES'!$I$113:$J$125,2,FALSE) -> 45170
B29: =LEFT(C29,1) -> A | C29: A2 | D29: RESIDENTIAL | E29: 1 | F29: 1 | G29: =LEFT(C29,2)&E29&F29 -> A211 | H29: 1 BEDROOM (STUDIO) | I29: =VLOOKUP(C29,'PREMIUM TABLES'!$G$107:$H$149,2,FALSE) -> C1 | J29: 61.82 | K29: 67.764878 | L29: 76 | O29: SE | P29: MIDDLE | Q29: ROAD 18M (BUILDINGS) | R29: =VLOOKUP(E29,'PREMIUM TABLES'!$F$214:$G$219,2,FALSE) -> FIRST | S29: {=IF(AND(L29>0,L29<90),"A",IF(AND(L29>90,L29<123),"B",IF(AND(L29>122,L29<159),"C",IF(AND(L29>159,L29<185),"D",IF(AND(L29>185,L29<230),"E",IF(AND(L29>230,L29<350),"F",NONE))))))} -> A | T29: =VLOOKUP(O29,'PREMIUM TABLES'!$G$165:$H$172,2,FALSE) -> 0.08 | U29: =VLOOKUP(P29,'PREMIUM TABLES'!$G$208:$H$209,2,FALSE) -> 0.025 | V29: =VLOOKUP(Q29,'PREMIUM TABLES'!$G$175:$H$195,2,FALSE) -> 0.15 | W29: =VLOOKUP(R29,'PREMIUM TABLES'!$G$214:$H$219,2,FALSE) -> 0.07 | X29: =VLOOKUP(S29,'PREMIUM TABLES'!$F$199:$H$205,3,FALSE) -> 0.05 | Y29: =SUM(T29:X29) -> 0.375 | Z29: {=IF(AND(Y29>0,Y29<0.5),"C",IF(AND(Y29>=0.5,Y29<0.73),"B",IF(AND(Y29>=0.73,Y29<0.98),"A",NONE)))} -> C | AA29: =VLOOKUP(G29,'ALL (R)'!$N$5:$R$862,5,FALSE) -> R 3 | AB29: =VLOOKUP(AA29,FACTS!$B$2:$L$14,10,FALSE) -> 44625 | AC29: =VLOOKUP(AA29,FACTS!$B$2:$L$14,11,FALSE) -> 49875 | AD29: =VLOOKUP(AA29,FACTS!$B$2:$N$14,13,FALSE) -> 5250 | AE29: =AD29*Y29 -> 1968.75 | AF29: =AE29+AB29 -> 46593.75 | AG29: =AF29*FACTS!$T$2 -> 15375.938 | AH29: =Table1[[#This Row],[UNIT (BUILDING) RATE (SEMI FINISHED)]]+4500 -> 51093.75 | AI29: =Table1[[#This Row],[UNIT (BUILDING) RATE (SEMI FINISHED)]]+7500 -> 54093.75 | AJ29: =AF29*L29 -> 3541125 | AK29: =Table1[[#This Row],[UNIT (BUILDING) RATE (BASIC FINISH)]]*Table1[[#This Row],[Unit Selling Area]] -> 3883125 | AL29: =Table1[[#This Row],[UNIT (BUILDING) RATE (FULLY FINISH)]]*Table1[[#This Row],[Unit Selling Area]] -> 4111125 | AM29: =AG29*M29 -> 0 | AN29: =(AM29+AJ29)*FACTS!$S$2 -> 300995.62 | AO29: =VLOOKUP(S29,FACTS!$A$17:$C$23,3,FALSE) -> 1 | AP29: =VLOOKUP(AA29,FACTS!$B$2:$J$14,9,FALSE) -> 210000 | AQ29: =Table1[[#This Row],[PARKING VALUE]]*1 -> 210000 | AR29: =AQ29+AM29+AJ29 -> 3751125 | AS29: =Table1[[#This Row],[TOTAL CARS VALUE]]+Table1[[#This Row],[UNIT (BUILDING) VALUE BASIC FINISHED]]+Table1[[#This Row],[UNIT (GARDEN) VALUE]] -> 4093125 | AT29: =Table1[[#This Row],[TOTAL CARS VALUE]]+Table1[[#This Row],[UNIT (GARDEN) VALUE]]+Table1[[#This Row],[UNIT (BUILDING) VALUE FULLY FINISHED]] -> 4321125 | AU29: =VLOOKUP(I29,'C PHASES'!$I$108:$J$110,2,FALSE) -> 45839 | AV29: =VLOOKUP(AA29,'C PHASES'!$I$113:$J$125,2,FALSE) -> 45383
B30: =LEFT(C30,1) -> A | C30: A2 | D30: RESIDENTIAL | E30: 1 | F30: 2 | G30: =LEFT(C30,2)&E30&F30 -> A212 | H30: 2 BEDROOM | I30: =VLOOKUP(C30,'PREMIUM TABLES'!$G$107:$H$149,2,FALSE) -> C1 | J30: 89.05 | K30: 97.613432 | L30: 110 | O30: NW | P30: MIDDLE | Q30: LAKE A-1 | R30: =VLOOKUP(E30,'PREMIUM TABLES'!$F$214:$G$219,2,FALSE) -> FIRST | S30: {=IF(AND(L30>0,L30<90),"A",IF(AND(L30>90,L30<123),"B",IF(AND(L30>122,L30<159),"C",IF(AND(L30>159,L30<185),"D",IF(AND(L30>185,L30<230),"E",IF(AND(L30>230,L30<350),"F",NONE))))))} -> B | T30: =VLOOKUP(O30,'PREMIUM TABLES'!$G$165:$H$172,2,FALSE) -> 0.13 | U30: =VLOOKUP(P30,'PREMIUM TABLES'!$G$208:$H$209,2,FALSE) -> 0.025 | V30: =VLOOKUP(Q30,'PREMIUM TABLES'!$G$175:$H$195,2,FALSE) -> 0.4 | W30: =VLOOKUP(R30,'PREMIUM TABLES'!$G$214:$H$219,2,FALSE) -> 0.07 | X30: =VLOOKUP(S30,'PREMIUM TABLES'!$F$199:$H$205,3,FALSE) -> 0.04 | Y30: =SUM(T30:X30) -> 0.665 | Z30: {=IF(AND(Y30>0,Y30<0.5),"C",IF(AND(Y30>=0.5,Y30<0.73),"B",IF(AND(Y30>=0.73,Y30<0.98),"A",NONE)))} -> B | AA30: =VLOOKUP(G30,'ALL (R)'!$N$5:$R$862,5,FALSE) -> R 5 | AB30: =VLOOKUP(AA30,FACTS!$B$2:$L$14,10,FALSE) -> 46750 | AC30: =VLOOKUP(AA30,FACTS!$B$2:$L$14,11,FALSE) -> 52250 | AD30: =VLOOKUP(AA30,FACTS!$B$2:$N$14,13,FALSE) -> 5500 | AE30: =AD30*Y30 -> 3657.5 | AF30: =AE30+AB30 -> 50407.5 | AG30: =AF30*FACTS!$T$2 -> 16634.475 | AH30: =Table1[[#This Row],[UNIT (BUILDING) RATE (SEMI FINISHED)]]+4500 -> 54907.5 | AI30: =Table1[[#This Row],[UNIT (BUILDING) RATE (SEMI FINISHED)]]+7500 -> 57907.5 | AJ30: =AF30*L30 -> 5544825 | AK30: =Table1[[#This Row],[UNIT (BUILDING) RATE (BASIC FINISH)]]*Table1[[#This Row],[Unit Selling Area]] -> 6039825 | AL30: =Table1[[#This Row],[UNIT (BUILDING) RATE (FULLY FINISH)]]*Table1[[#This Row],[Unit Selling Area]] -> 6369825 | AM30: =AG30*M30 -> 0 | AN30: =(AM30+AJ30)*FACTS!$S$2 -> 471310.13 | AO30: =VLOOKUP(S30,FACTS!$A$17:$C$23,3,FALSE) -> 1 | AP30: =VLOOKUP(AA30,FACTS!$B$2:$J$14,9,FALSE) -> 220000 | AQ30: =Table1[[#This Row],[PARKING VALUE]]*1 -> 220000 | AR30: =AQ30+AM30+AJ30 -> 5764825 | AS30: =Table1[[#This Row],[TOTAL CARS VALUE]]+Table1[[#This Row],[UNIT (BUILDING) VALUE BASIC FINISHED]]+Table1[[#This Row],[UNIT (GARDEN) VALUE]] -> 6259825 | AT30: =Table1[[#This Row],[TOTAL CARS VALUE]]+Table1[[#This Row],[UNIT (GARDEN) VALUE]]+Table1[[#This Row],[UNIT (BUILDING) VALUE FULLY FINISHED]] -> 6589825 | AU30: =VLOOKUP(I30,'C PHASES'!$I$108:$J$110,2,FALSE) -> 45839 | AV30: =VLOOKUP(AA30,'C PHASES'!$I$113:$J$125,2,FALSE) -> 45566
B31: =LEFT(C31,1) -> A | C31: A2 | D31: RESIDENTIAL | E31: 1 | F31: 3 | G31: =LEFT(C31,2)&E31&F31 -> A213 | H31: 2 BEDROOM | I31: =VLOOKUP(C31,'PREMIUM TABLES'!$G$107:$H$149,2,FALSE) -> C1 | J31: 97.06 | K31: 106.39371 | L31: 120 | O31: NW | P31: MIDDLE | Q31: LAKE A-1 | R31: =VLOOKUP(E31,'PREMIUM TABLES'!$F$214:$G$219,2,FALSE) -> FIRST | S31: {=IF(AND(L31>0,L31<90),"A",IF(AND(L31>90,L31<123),"B",IF(AND(L31>122,L31<159),"C",IF(AND(L31>159,L31<185),"D",IF(AND(L31>185,L31<230),"E",IF(AND(L31>230,L31<350),"F",NONE))))))} -> B | T31: =VLOOKUP(O31,'PREMIUM TABLES'!$G$165:$H$172,2,FALSE) -> 0.13 | U31: =VLOOKUP(P31,'PREMIUM TABLES'!$G$208:$H$209,2,FALSE) -> 0.025 | V31: =VLOOKUP(Q31,'PREMIUM TABLES'!$G$175:$H$195,2,FALSE) -> 0.4 | W31: =VLOOKUP(R31,'PREMIUM TABLES'!$G$214:$H$219,2,FALSE) -> 0.07 | X31: =VLOOKUP(S31,'PREMIUM TABLES'!$F$199:$H$205,3,FALSE) -> 0.04 | Y31: =SUM(T31:X31) -> 0.665 | Z31: {=IF(AND(Y31>0,Y31<0.5),"C",IF(AND(Y31>=0.5,Y31<0.73),"B",IF(AND(Y31>=0.73,Y31<0.98),"A",NONE)))} -> B | AA31: =VLOOKUP(G31,'ALL (R)'!$N$5:$R$862,5,FALSE) -> R 5 | AB31: =VLOOKUP(AA31,FACTS!$B$2:$L$14,10,FALSE) -> 46750 | AC31: =VLOOKUP(AA31,FACTS!$B$2:$L$14,11,FALSE) -> 52250 | AD31: =VLOOKUP(AA31,FACTS!$B$2:$N$14,13,FALSE) -> 5500 | AE31: =AD31*Y31 -> 3657.5 | AF31: =AE31+AB31 -> 50407.5 | AG31: =AF31*FACTS!$T$2 -> 16634.475 | AH31: =Table1[[#This Row],[UNIT (BUILDING) RATE (SEMI FINISHED)]]+4500 -> 54907.5 | AI31: =Table1[[#This Row],[UNIT (BUILDING) RATE (SEMI FINISHED)]]+7500 -> 57907.5 | AJ31: =AF31*L31 -> 6048900 | AK31: =Table1[[#This Row],[UNIT (BUILDING) RATE (BASIC FINISH)]]*Table1[[#This Row],[Unit Selling Area]] -> 6588900 | AL31: =Table1[[#This Row],[UNIT (BUILDING) RATE (FULLY FINISH)]]*Table1[[#This Row],[Unit Selling Area]] -> 6948900 | AM31: =AG31*M31 -> 0 | AN31: =(AM31+AJ31)*FACTS!$S$2 -> 514156.5 | AO31: =VLOOKUP(S31,FACTS!$A$17:$C$23,3,FALSE) -> 1 | AP31: =VLOOKUP(AA31,FACTS!$B$2:$J$14,9,FALSE) -> 220000 | AQ31: =Table1[[#This Row],[PARKING VALUE]]*1 -> 220000 | AR31: =AQ31+AM31+AJ31 -> 6268900 | AS31: =Table1[[#This Row],[TOTAL CARS VALUE]]+Table1[[#This Row],[UNIT (BUILDING) VALUE BASIC FINISHED]]+Table1[[#This Row],[UNIT (GARDEN) VALUE]] -> 6808900 | AT31: =Table1[[#This Row],[TOTAL CARS VALUE]]+Table1[[#This Row],[UNIT (GARDEN) VALUE]]+Table1[[#This Row],[UNIT (BUILDING) VALUE FULLY FINISHED]] -> 7168900 | AU31: =VLOOKUP(I31,'C PHASES'!$I$108:$J$110,2,FALSE) -> 45839 | AV31: =VLOOKUP(AA31,'C PHASES'!$I$113:$J$125,2,FALSE) -> 45566
B32: =LEFT(C32,1) -> A | C32: A2 | D32: RESIDENTIAL | E32: 1 | F32: 4 | G32: =LEFT(C32,2)&E32&F32 -> A214 | H32: 2 BEDROOM | I32: =VLOOKUP(C32,'PREMIUM TABLES'!$G$107:$H$149,2,FALSE) -> C1 | J32: 97.09 | K32: 106.42659 | L32: 119 | O32: SE | P32: MIDDLE | Q32: ROAD 18M (BUILDINGS) | R32: =VLOOKUP(E32,'PREMIUM TABLES'!$F$214:$G$219,2,FALSE) -> FIRST | S32: {=IF(AND(L32>0,L32<90),"A",IF(AND(L32>90,L32<123),"B",IF(AND(L32>122,L32<159),"C",IF(AND(L32>159,L32<185),"D",IF(AND(L32>185,L32<230),"E",IF(AND(L32>230,L32<350),"F",NONE))))))} -> B | T32: =VLOOKUP(O32,'PREMIUM TABLES'!$G$165:$H$172,2,FALSE) -> 0.08 | U32: =VLOOKUP(P32,'PREMIUM TABLES'!$G$208:$H$209,2,FALSE) -> 0.025 | V32: =VLOOKUP(Q32,'PREMIUM TABLES'!$G$175:$H$195,2,FALSE) -> 0.15 | W32: =VLOOKUP(R32,'PREMIUM TABLES'!$G$214:$H$219,2,FALSE) -> 0.07 | X32: =VLOOKUP(S32,'PREMIUM TABLES'!$F$199:$H$205,3,FALSE) -> 0.04 | Y32: =SUM(T32:X32) -> 0.365 | Z32: {=IF(AND(Y32>0,Y32<0.5),"C",IF(AND(Y32>=0.5,Y32<0.73),"B",IF(AND(Y32>=0.73,Y32<0.98),"A",NONE)))} -> C | AA32: =VLOOKUP(G32,'ALL (R)'!$N$5:$R$862,5,FALSE) -> R 2 | AB32: =VLOOKUP(AA32,FACTS!$B$2:$L$14,10,FALSE) -> 43562.5 | AC32: =VLOOKUP(AA32,FACTS!$B$2:$L$14,11,FALSE) -> 48687.5 | AD32: =VLOOKUP(AA32,FACTS!$B$2:$N$14,13,FALSE) -> 5125 | AE32: =AD32*Y32 -> 1870.625 | AF32: =AE32+AB32 -> 45433.125 | AG32: =AF32*FACTS!$T$2 -> 14992.931 | AH32: =Table1[[#This Row],[UNIT (BUILDING) RATE (SEMI FINISHED)]]+4500 -> 49933.125 | AI32: =Table1[[#This Row],[UNIT (BUILDING) RATE (SEMI FINISHED)]]+7500 -> 52933.125 | AJ32: =AF32*L32 -> 5406541.9 | AK32: =Table1[[#This Row],[UNIT (BUILDING) RATE (BASIC FINISH)]]*Table1[[#This Row],[Unit Selling Area]] -> 5942041.9 | AL32: =Table1[[#This Row],[UNIT (BUILDING) RATE (FULLY FINISH)]]*Table1[[#This Row],[Unit Selling Area]] -> 6299041.9 | AM32: =AG32*M32 -> 0 | AN32: =(AM32+AJ32)*FACTS!$S$2 -> 459556.06 | AO32: =VLOOKUP(S32,FACTS!$A$17:$C$23,3,FALSE) -> 1 | AP32: =VLOOKUP(AA32,FACTS!$B$2:$J$14,9,FALSE) -> 205000 | AQ32: =Table1[[#This Row],[PARKING VALUE]]*1 -> 205000 | AR32: =AQ32+AM32+AJ32 -> 5611541.9 | AS32: =Table1[[#This Row],[TOTAL CARS VALUE]]+Table1[[#This Row],[UNIT (BUILDING) VALUE BASIC FINISHED]]+Table1[[#This Row],[UNIT (GARDEN) VALUE]] -> 6147041.9 | AT32: =Table1[[#This Row],[TOTAL CARS VALUE]]+Table1[[#This Row],[UNIT (GARDEN) VALUE]]+Table1[[#This Row],[UNIT (BUILDING) VALUE FULLY FINISHED]] -> 6504041.9 | AU32: =VLOOKUP(I32,'C PHASES'!$I$108:$J$110,2,FALSE) -> 45839 | AV32: =VLOOKUP(AA32,'C PHASES'!$I$113:$J$125,2,FALSE) -> 45292
B33: =LEFT(C33,1) -> A | C33: A2 | D33: RESIDENTIAL | E33: 2 | F33: 1 | G33: =LEFT(C33,2)&E33&F33 -> A221 | H33: 2 BEDROOM | I33: =VLOOKUP(C33,'PREMIUM TABLES'!$G$107:$H$149,2,FALSE) -> C1 | J33: 90.91 | K33: 99.652297 | L33: 112 | O33: SE | P33: MIDDLE | Q33: ROAD 18M (BUILDINGS) | R33: =VLOOKUP(E33,'PREMIUM TABLES'!$F$214:$G$219,2,FALSE) -> SECOND | S33: {=IF(AND(L33>0,L33<90),"A",IF(AND(L33>90,L33<123),"B",IF(AND(L33>122,L33<159),"C",IF(AND(L33>159,L33<185),"D",IF(AND(L33>185,L33<230),"E",IF(AND(L33>230,L33<350),"F",NONE))))))} -> B | T33: =VLOOKUP(O33,'PREMIUM TABLES'!$G$165:$H$172,2,FALSE) -> 0.08 | U33: =VLOOKUP(P33,'PREMIUM TABLES'!$G$208:$H$209,2,FALSE) -> 0.025 | V33: =VLOOKUP(Q33,'PREMIUM TABLES'!$G$175:$H$195,2,FALSE) -> 0.15 | W33: =VLOOKUP(R33,'PREMIUM TABLES'!$G$214:$H$219,2,FALSE) -> 0.11 | X33: =VLOOKUP(S33,'PREMIUM TABLES'!$F$199:$H$205,3,FALSE) -> 0.04 | Y33: =SUM(T33:X33) -> 0.405 | Z33: {=IF(AND(Y33>0,Y33<0.5),"C",IF(AND(Y33>=0.5,Y33<0.73),"B",IF(AND(Y33>=0.73,Y33<0.98),"A",NONE)))} -> C | AA33: =VLOOKUP(G33,'ALL (R)'!$N$5:$R$862,5,FALSE) -> R 6 | AB33: =VLOOKUP(AA33,FACTS!$B$2:$L$14,10,FALSE) -> 48450 | AC33: =VLOOKUP(AA33,FACTS!$B$2:$L$14,11,FALSE) -> 54150 | AD33: =VLOOKUP(AA33,FACTS!$B$2:$N$14,13,FALSE) -> 5700 | AE33: =AD33*Y33 -> 2308.5 | AF33: =AE33+AB33 -> 50758.5 | AG33: =AF33*FACTS!$T$2 -> 16750.305 | AH33: =Table1[[#This Row],[UNIT (BUILDING) RATE (SEMI FINISHED)]]+4500 -> 55258.5 | AI33: =Table1[[#This Row],[UNIT (BUILDING) RATE (SEMI FINISHED)]]+7500 -> 58258.5 | AJ33: =AF33*L33 -> 5684952 | AK33: =Table1[[#This Row],[UNIT (BUILDING) RATE (BASIC FINISH)]]*Table1[[#This Row],[Unit Selling Area]] -> 6188952 | AL33: =Table1[[#This Row],[UNIT (BUILDING) RATE (FULLY FINISH)]]*Table1[[#This Row],[Unit Selling Area]] -> 6524952 | AM33: =AG33*M33 -> 0 | AN33: =(AM33+AJ33)*FACTS!$S$2 -> 483220.92 | AO33: =VLOOKUP(S33,FACTS!$A$17:$C$23,3,FALSE) -> 1 | AP33: =VLOOKUP(AA33,FACTS!$B$2:$J$14,9,FALSE) -> 228000 | AQ33: =Table1[[#This Row],[PARKING VALUE]]*1 -> 228000 | AR33: =AQ33+AM33+AJ33 -> 5912952 | AS33: =Table1[[#This Row],[TOTAL CARS VALUE]]+Table1[[#This Row],[UNIT (BUILDING) VALUE BASIC FINISHED]]+Table1[[#This Row],[UNIT (GARDEN) VALUE]] -> 6416952 | AT33: =Table1[[#This Row],[TOTAL CARS VALUE]]+Table1[[#This Row],[UNIT (GARDEN) VALUE]]+Table1[[#This Row],[UNIT (BUILDING) VALUE FULLY FINISHED]] -> 6752952 | AU33: =VLOOKUP(I33,'C PHASES'!$I$108:$J$110,2,FALSE) -> 45839 | AV33: =VLOOKUP(AA33,'C PHASES'!$I$113:$J$125,2,FALSE) -> 45658
B34: =LEFT(C34,1) -> A | C34: A2 | D34: RESIDENTIAL | E34: 2 | F34: 2 | G34: =LEFT(C34,2)&E34&F34 -> A222 | H34: 2 BEDROOM | I34: =VLOOKUP(C34,'PREMIUM TABLES'!$G$107:$H$149,2,FALSE) -> C1 | J34: 90.91 | K34: 99.652297 | L34: 112 | O34: NW | P34: MIDDLE | Q34: LAKE A-1 | R34: =VLOOKUP(E34,'PREMIUM TABLES'!$F$214:$G$219,2,FALSE) -> SECOND | S34: {=IF(AND(L34>0,L34<90),"A",IF(AND(L34>90,L34<123),"B",IF(AND(L34>122,L34<159),"C",IF(AND(L34>159,L34<185),"D",IF(AND(L34>185,L34<230),"E",IF(AND(L34>230,L34<350),"F",NONE))))))} -> B | T34: =VLOOKUP(O34,'PREMIUM TABLES'!$G$165:$H$172,2,FALSE) -> 0.13 | U34: =VLOOKUP(P34,'PREMIUM TABLES'!$G$208:$H$209,2,FALSE) -> 0.025 | V34: =VLOOKUP(Q34,'PREMIUM TABLES'!$G$175:$H$195,2,FALSE) -> 0.4 | W34: =VLOOKUP(R34,'PREMIUM TABLES'!$G$214:$H$219,2,FALSE) -> 0.11 | X34: =VLOOKUP(S34,'PREMIUM TABLES'!$F$199:$H$205,3,FALSE) -> 0.04 | Y34: =SUM(T34:X34) -> 0.705 | Z34: {=IF(AND(Y34>0,Y34<0.5),"C",IF(AND(Y34>=0.5,Y34<0.73),"B",IF(AND(Y34>=0.73,Y34<0.98),"A",NONE)))} -> B | AA34: =VLOOKUP(G34,'ALL (R)'!$N$5:$R$862,5,FALSE) -> R 10 | AB34: =VLOOKUP(AA34,FACTS!$B$2:$L$14,10,FALSE) -> 56100 | AC34: =VLOOKUP(AA34,FACTS!$B$2:$L$14,11,FALSE) -> 62700 | AD34: =VLOOKUP(AA34,FACTS!$B$2:$N$14,13,FALSE) -> 6600 | AE34: =AD34*Y34 -> 4653 | AF34: =AE34+AB34 -> 60753 | AG34: =AF34*FACTS!$T$2 -> 20048.49 | AH34: =Table1[[#This Row],[UNIT (BUILDING) RATE (SEMI FINISHED)]]+4500 -> 65253 | AI34: =Table1[[#This Row],[UNIT (BUILDING) RATE (SEMI FINISHED)]]+7500 -> 68253 | AJ34: =AF34*L34 -> 6804336 | AK34: =Table1[[#This Row],[UNIT (BUILDING) RATE (BASIC FINISH)]]*Table1[[#This Row],[Unit Selling Area]] -> 7308336 | AL34: =Table1[[#This Row],[UNIT (BUILDING) RATE (FULLY FINISH)]]*Table1[[#This Row],[Unit Selling Area]] -> 7644336 | AM34: =AG34*M34 -> 0 | AN34: =(AM34+AJ34)*FACTS!$S$2 -> 578368.56 | AO34: =VLOOKUP(S34,FACTS!$A$17:$C$23,3,FALSE) -> 1 | AP34: =VLOOKUP(AA34,FACTS!$B$2:$J$14,9,FALSE) -> 264000 | AQ34: =Table1[[#This Row],[PARKING VALUE]]*1 -> 264000 | AR34: =AQ34+AM34+AJ34 -> 7068336 | AS34: =Table1[[#This Row],[TOTAL CARS VALUE]]+Table1[[#This Row],[UNIT (BUILDING) VALUE BASIC FINISHED]]+Table1[[#This Row],[UNIT (GARDEN) VALUE]] -> 7572336 | AT34: =Table1[[#This Row],[TOTAL CARS VALUE]]+Table1[[#This Row],[UNIT (GARDEN) VALUE]]+Table1[[#This Row],[UNIT (BUILDING) VALUE FULLY FINISHED]] -> 7908336 | AU34: =VLOOKUP(I34,'C PHASES'!$I$108:$J$110,2,FALSE) -> 45839 | AV34: =VLOOKUP(AA34,'C PHASES'!$I$113:$J$125,2,FALSE) -> 46023
B35: =LEFT(C35,1) -> A | C35: A2 | D35: RESIDENTIAL | E35: 2 | F35: 3 | G35: =LEFT(C35,2)&E35&F35 -> A223 | H35: 2 BEDROOM | I35: =VLOOKUP(C35,'PREMIUM TABLES'!$G$107:$H$149,2,FALSE) -> C1 | J35: 98.95 | K35: 108.46546 | L35: 122 | O35: NW | P35: MIDDLE | Q35: LAKE A-1 | R35: =VLOOKUP(E35,'PREMIUM TABLES'!$F$214:$G$219,2,FALSE) -> SECOND | S35: {=IF(AND(L35>0,L35<90),"A",IF(AND(L35>90,L35<123),"B",IF(AND(L35>122,L35<159),"C",IF(AND(L35>159,L35<185),"D",IF(AND(L35>185,L35<230),"E",IF(AND(L35>230,L35<350),"F",NONE))))))} -> B | T35: =VLOOKUP(O35,'PREMIUM TABLES'!$G$165:$H$172,2,FALSE) -> 0.13 | U35: =VLOOKUP(P35,'PREMIUM TABLES'!$G$208:$H$209,2,FALSE) -> 0.025 | V35: =VLOOKUP(Q35,'PREMIUM TABLES'!$G$175:$H$195,2,FALSE) -> 0.4 | W35: =VLOOKUP(R35,'PREMIUM TABLES'!$G$214:$H$219,2,FALSE) -> 0.11 | X35: =VLOOKUP(S35,'PREMIUM TABLES'!$F$199:$H$205,3,FALSE) -> 0.04 | Y35: =SUM(T35:X35) -> 0.705 | Z35: {=IF(AND(Y35>0,Y35<0.5),"C",IF(AND(Y35>=0.5,Y35<0.73),"B",IF(AND(Y35>=0.73,Y35<0.98),"A",NONE)))} -> B | AA35: =VLOOKUP(G35,'ALL (R)'!$N$5:$R$862,5,FALSE) -> R 10 | AB35: =VLOOKUP(AA35,FACTS!$B$2:$L$14,10,FALSE) -> 56100 | AC35: =VLOOKUP(AA35,FACTS!$B$2:$L$14,11,FALSE) -> 62700 | AD35: =VLOOKUP(AA35,FACTS!$B$2:$N$14,13,FALSE) -> 6600 | AE35: =AD35*Y35 -> 4653 | AF35: =AE35+AB35 -> 60753 | AG35: =AF35*FACTS!$T$2 -> 20048.49 | AH35: =Table1[[#This Row],[UNIT (BUILDING) RATE (SEMI FINISHED)]]+4500 -> 65253 | AI35: =Table1[[#This Row],[UNIT (BUILDING) RATE (SEMI FINISHED)]]+7500 -> 68253 | AJ35: =AF35*L35 -> 7411866 | AK35: =Table1[[#This Row],[UNIT (BUILDING) RATE (BASIC FINISH)]]*Table1[[#This Row],[Unit Selling Area]] -> 7960866 | AL35: =Table1[[#This Row],[UNIT (BUILDING) RATE (FULLY FINISH)]]*Table1[[#This Row],[Unit Selling Area]] -> 8326866 | AM35: =AG35*M35 -> 0 | AN35: =(AM35+AJ35)*FACTS!$S$2 -> 630008.61 | AO35: =VLOOKUP(S35,FACTS!$A$17:$C$23,3,FALSE) -> 1 | AP35: =VLOOKUP(AA35,FACTS!$B$2:$J$14,9,FALSE) -> 264000 | AQ35: =Table1[[#This Row],[PARKING VALUE]]*1 -> 264000 | AR35: =AQ35+AM35+AJ35 -> 7675866 | AS35: =Table1[[#This Row],[TOTAL CARS VALUE]]+Table1[[#This Row],[UNIT (BUILDING) VALUE BASIC FINISHED]]+Table1[[#This Row],[UNIT (GARDEN) VALUE]] -> 8224866 | AT35: =Table1[[#This Row],[TOTAL CARS VALUE]]+Table1[[#This Row],[UNIT (GARDEN) VALUE]]+Table1[[#This Row],[UNIT (BUILDING) VALUE FULLY FINISHED]] -> 8590866 | AU35: =VLOOKUP(I35,'C PHASES'!$I$108:$J$110,2,FALSE) -> 45839 | AV35: =VLOOKUP(AA35,'C PHASES'!$I$113:$J$125,2,FALSE) -> 46023
B36: =LEFT(C36,1) -> A | C36: A2 | D36: RESIDENTIAL | E36: 2 | F36: 4 | G36: =LEFT(C36,2)&E36&F36 -> A224 | H36: 2 BEDROOM | I36: =VLOOKUP(C36,'PREMIUM TABLES'!$G$107:$H$149,2,FALSE) -> C1 | J36: 98.95 | K36: 108.46546 | L36: 122 | O36: SE | P36: MIDDLE | Q36: ROAD 18M (BUILDINGS) | R36: =VLOOKUP(E36,'PREMIUM TABLES'!$F$214:$G$219,2,FALSE) -> SECOND | S36: {=IF(AND(L36>0,L36<90),"A",IF(AND(L36>90,L36<123),"B",IF(AND(L36>122,L36<159),"C",IF(AND(L36>159,L36<185),"D",IF(AND(L36>185,L36<230),"E",IF(AND(L36>230,L36<350),"F",NONE))))))} -> B | T36: =VLOOKUP(O36,'PREMIUM TABLES'!$G$165:$H$172,2,FALSE) -> 0.08 | U36: =VLOOKUP(P36,'PREMIUM TABLES'!$G$208:$H$209,2,FALSE) -> 0.025 | V36: =VLOOKUP(Q36,'PREMIUM TABLES'!$G$175:$H$195,2,FALSE) -> 0.15 | W36: =VLOOKUP(R36,'PREMIUM TABLES'!$G$214:$H$219,2,FALSE) -> 0.11 | X36: =VLOOKUP(S36,'PREMIUM TABLES'!$F$199:$H$205,3,FALSE) -> 0.04 | Y36: =SUM(T36:X36) -> 0.405 | Z36: {=IF(AND(Y36>0,Y36<0.5),"C",IF(AND(Y36>=0.5,Y36<0.73),"B",IF(AND(Y36>=0.73,Y36<0.98),"A",NONE)))} -> C | AA36: =VLOOKUP(G36,'ALL (R)'!$N$5:$R$862,5,FALSE) -> R 6 | AB36: =VLOOKUP(AA36,FACTS!$B$2:$L$14,10,FALSE) -> 48450 | AC36: =VLOOKUP(AA36,FACTS!$B$2:$L$14,11,FALSE) -> 54150 | AD36: =VLOOKUP(AA36,FACTS!$B$2:$N$14,13,FALSE) -> 5700 | AE36: =AD36*Y36 -> 2308.5 | AF36: =AE36+AB36 -> 50758.5 | AG36: =AF36*FACTS!$T$2 -> 16750.305 | AH36: =Table1[[#This Row],[UNIT (BUILDING) RATE (SEMI FINISHED)]]+4500 -> 55258.5 | AI36: =Table1[[#This Row],[UNIT (BUILDING) RATE (SEMI FINISHED)]]+7500 -> 58258.5 | AJ36: =AF36*L36 -> 6192537 | AK36: =Table1[[#This Row],[UNIT (BUILDING) RATE (BASIC FINISH)]]*Table1[[#This Row],[Unit Selling Area]] -> 6741537 | AL36: =Table1[[#This Row],[UNIT (BUILDING) RATE (FULLY FINISH)]]*Table1[[#This Row],[Unit Selling Area]] -> 7107537 | AM36: =AG36*M36 -> 0 | AN36: =(AM36+AJ36)*FACTS!$S$2 -> 526365.65 | AO36: =VLOOKUP(S36,FACTS!$A$17:$C$23,3,FALSE) -> 1 | AP36: =VLOOKUP(AA36,FACTS!$B$2:$J$14,9,FALSE) -> 228000 | AQ36: =Table1[[#This Row],[PARKING VALUE]]*1 -> 228000 | AR36: =AQ36+AM36+AJ36 -> 6420537 | AS36: =Table1[[#This Row],[TOTAL CARS VALUE]]+Table1[[#This Row],[UNIT (BUILDING) VALUE BASIC FINISHED]]+Table1[[#This Row],[UNIT (GARDEN) VALUE]] -> 6969537 | AT36: =Table1[[#This Row],[TOTAL CARS VALUE]]+Table1[[#This Row],[UNIT (GARDEN) VALUE]]+Table1[[#This Row],[UNIT (BUILDING) VALUE FULLY FINISHED]] -> 7335537 | AU36: =VLOOKUP(I36,'C PHASES'!$I$108:$J$110,2,FALSE) -> 45839 | AV36: =VLOOKUP(AA36,'C PHASES'!$I$113:$J$125,2,FALSE) -> 45658
B37: =LEFT(C37,1) -> A | C37: A2 | D37: RESIDENTIAL | E37: 3 | F37: 1 | G37: =LEFT(C37,2)&E37&F37 -> A231 | H37: 2 BEDROOM | I37: =VLOOKUP(C37,'PREMIUM TABLES'!$G$107:$H$149,2,FALSE) -> C1 | J37: 89.05 | K37: 97.613432 | L37: 110 | O37: SE | P37: MIDDLE | Q37: ROAD 18M (BUILDINGS) | R37: =VLOOKUP(E37,'PREMIUM TABLES'!$F$214:$G$219,2,FALSE) -> THIRD | S37: {=IF(AND(L37>0,L37<90),"A",IF(AND(L37>90,L37<123),"B",IF(AND(L37>122,L37<159),"C",IF(AND(L37>159,L37<185),"D",IF(AND(L37>185,L37<230),"E",IF(AND(L37>230,L37<350),"F",NONE))))))} -> B | T37: =VLOOKUP(O37,'PREMIUM TABLES'!$G$165:$H$172,2,FALSE) -> 0.08 | U37: =VLOOKUP(P37,'PREMIUM TABLES'!$G$208:$H$209,2,FALSE) -> 0.025 | V37: =VLOOKUP(Q37,'PREMIUM TABLES'!$G$175:$H$195,2,FALSE) -> 0.15 | W37: =VLOOKUP(R37,'PREMIUM TABLES'!$G$214:$H$219,2,FALSE) -> 0.15 | X37: =VLOOKUP(S37,'PREMIUM TABLES'!$F$199:$H$205,3,FALSE) -> 0.04 | Y37: =SUM(T37:X37) -> 0.445 | Z37: {=IF(AND(Y37>0,Y37<0.5),"C",IF(AND(Y37>=0.5,Y37<0.73),"B",IF(AND(Y37>=0.73,Y37<0.98),"A",NONE)))} -> C | AA37: =VLOOKUP(G37,'ALL (R)'!$N$5:$R$862,5,FALSE) -> R 9 | AB37: =VLOOKUP(AA37,FACTS!$B$2:$L$14,10,FALSE) -> 53550 | AC37: =VLOOKUP(AA37,FACTS!$B$2:$L$14,11,FALSE) -> 59850 | AD37: =VLOOKUP(AA37,FACTS!$B$2:$N$14,13,FALSE) -> 6300 | AE37: =AD37*Y37 -> 2803.5 | AF37: =AE37+AB37 -> 56353.5 | AG37: =AF37*FACTS!$T$2 -> 18596.655 | AH37: =Table1[[#This Row],[UNIT (BUILDING) RATE (SEMI FINISHED)]]+4500 -> 60853.5 | AI37: =Table1[[#This Row],[UNIT (BUILDING) RATE (SEMI FINISHED)]]+7500 -> 63853.5 | AJ37: =AF37*L37 -> 6198885 | AK37: =Table1[[#This Row],[UNIT (BUILDING) RATE (BASIC FINISH)]]*Table1[[#This Row],[Unit Selling Area]] -> 6693885 | AL37: =Table1[[#This Row],[UNIT (BUILDING) RATE (FULLY FINISH)]]*Table1[[#This Row],[Unit Selling Area]] -> 7023885 | AM37: =AG37*M37 -> 0 | AN37: =(AM37+AJ37)*FACTS!$S$2 -> 526905.23 | AO37: =VLOOKUP(S37,FACTS!$A$17:$C$23,3,FALSE) -> 1 | AP37: =VLOOKUP(AA37,FACTS!$B$2:$J$14,9,FALSE) -> 252000 | AQ37: =Table1[[#This Row],[PARKING VALUE]]*1 -> 252000 | AR37: =AQ37+AM37+AJ37 -> 6450885 | AS37: =Table1[[#This Row],[TOTAL CARS VALUE]]+Table1[[#This Row],[UNIT (BUILDING) VALUE BASIC FINISHED]]+Table1[[#This Row],[UNIT (GARDEN) VALUE]] -> 6945885 | AT37: =Table1[[#This Row],[TOTAL CARS VALUE]]+Table1[[#This Row],[UNIT (GARDEN) VALUE]]+Table1[[#This Row],[UNIT (BUILDING) VALUE FULLY FINISHED]] -> 7275885 | AU37: =VLOOKUP(I37,'C PHASES'!$I$108:$J$110,2,FALSE) -> 45839 | AV37: =VLOOKUP(AA37,'C PHASES'!$I$113:$J$125,2,FALSE) -> 45931
B38: =LEFT(C38,1) -> A | C38: A2 | D38: RESIDENTIAL | E38: 3 | F38: 2 | G38: =LEFT(C38,2)&E38&F38 -> A232 | H38: 2 BEDROOM | I38: =VLOOKUP(C38,'PREMIUM TABLES'!$G$107:$H$149,2,FALSE) -> C1 | J38: 89.05 | K38: 97.613432 | L38: 110 | O38: NW | P38: MIDDLE | Q38: LAKE A-1 | R38: =VLOOKUP(E38,'PREMIUM TABLES'!$F$214:$G$219,2,FALSE) -> THIRD | S38: {=IF(AND(L38>0,L38<90),"A",IF(AND(L38>90,L38<123),"B",IF(AND(L38>122,L38<159),"C",IF(AND(L38>159,L38<185),"D",IF(AND(L38>185,L38<230),"E",IF(AND(L38>230,L38<350),"F",NONE))))))} -> B | T38: =VLOOKUP(O38,'PREMIUM TABLES'!$G$165:$H$172,2,FALSE) -> 0.13 | U38: =VLOOKUP(P38,'PREMIUM TABLES'!$G$208:$H$209,2,FALSE) -> 0.025 | V38: =VLOOKUP(Q38,'PREMIUM TABLES'!$G$175:$H$195,2,FALSE) -> 0.4 | W38: =VLOOKUP(R38,'PREMIUM TABLES'!$G$214:$H$219,2,FALSE) -> 0.15 | X38: =VLOOKUP(S38,'PREMIUM TABLES'!$F$199:$H$205,3,FALSE) -> 0.04 | Y38: =SUM(T38:X38) -> 0.745 | Z38: {=IF(AND(Y38>0,Y38<0.5),"C",IF(AND(Y38>=0.5,Y38<0.73),"B",IF(AND(Y38>=0.73,Y38<0.98),"A",NONE)))} -> A | AA38: =VLOOKUP(G38,'ALL (R)'!$N$5:$R$862,5,FALSE) -> R 1 | AB38: =VLOOKUP(AA38,FACTS!$B$2:$L$14,10,FALSE) -> 42500 | AC38: =VLOOKUP(AA38,FACTS!$B$2:$L$14,11,FALSE) -> 47500 | AD38: =VLOOKUP(AA38,FACTS!$B$2:$N$14,13,FALSE) -> 5000 | AE38: =AD38*Y38 -> 3725 | AF38: =AE38+AB38 -> 46225 | AG38: =AF38*FACTS!$T$2 -> 15254.25 | AH38: =Table1[[#This Row],[UNIT (BUILDING) RATE (SEMI FINISHED)]]+4500 -> 50725 | AI38: =Table1[[#This Row],[UNIT (BUILDING) RATE (SEMI FINISHED)]]+7500 -> 53725 | AJ38: =AF38*L38 -> 5084750 | AK38: =Table1[[#This Row],[UNIT (BUILDING) RATE (BASIC FINISH)]]*Table1[[#This Row],[Unit Selling Area]] -> 5579750 | AL38: =Table1[[#This Row],[UNIT (BUILDING) RATE (FULLY FINISH)]]*Table1[[#This Row],[Unit Selling Area]] -> 5909750 | AM38: =AG38*M38 -> 0 | AN38: =(AM38+AJ38)*FACTS!$S$2 -> 432203.75 | AO38: =VLOOKUP(S38,FACTS!$A$17:$C$23,3,FALSE) -> 1 | AP38: =VLOOKUP(AA38,FACTS!$B$2:$J$14,9,FALSE) -> 200000 | AQ38: =Table1[[#This Row],[PARKING VALUE]]*1 -> 200000 | AR38: =AQ38+AM38+AJ38 -> 5284750 | AS38: =Table1[[#This Row],[TOTAL CARS VALUE]]+Table1[[#This Row],[UNIT (BUILDING) VALUE BASIC FINISHED]]+Table1[[#This Row],[UNIT (GARDEN) VALUE]] -> 5779750 | AT38: =Table1[[#This Row],[TOTAL CARS VALUE]]+Table1[[#This Row],[UNIT (GARDEN) VALUE]]+Table1[[#This Row],[UNIT (BUILDING) VALUE FULLY FINISHED]] -> 6109750 | AU38: =VLOOKUP(I38,'C PHASES'!$I$108:$J$110,2,FALSE) -> 45839 | AV38: =VLOOKUP(AA38,'C PHASES'!$I$113:$J$125,2,FALSE) -> 45170
B39: =LEFT(C39,1) -> A | C39: A2 | D39: RESIDENTIAL | E39: 3 | F39: 3 | G39: =LEFT(C39,2)&E39&F39 -> A233 | H39: 2 BEDROOM | I39: =VLOOKUP(C39,'PREMIUM TABLES'!$G$107:$H$149,2,FALSE) -> C1 | J39: 97.09 | K39: 106.42659 | L39: 119 | O39: NW | P39: MIDDLE | Q39: LAKE A-1 | R39: =VLOOKUP(E39,'PREMIUM TABLES'!$F$214:$G$219,2,FALSE) -> THIRD | S39: {=IF(AND(L39>0,L39<90),"A",IF(AND(L39>90,L39<123),"B",IF(AND(L39>122,L39<159),"C",IF(AND(L39>159,L39<185),"D",IF(AND(L39>185,L39<230),"E",IF(AND(L39>230,L39<350),"F",NONE))))))} -> B | T39: =VLOOKUP(O39,'PREMIUM TABLES'!$G$165:$H$172,2,FALSE) -> 0.13 | U39: =VLOOKUP(P39,'PREMIUM TABLES'!$G$208:$H$209,2,FALSE) -> 0.025 | V39: =VLOOKUP(Q39,'PREMIUM TABLES'!$G$175:$H$195,2,FALSE) -> 0.4 | W39: =VLOOKUP(R39,'PREMIUM TABLES'!$G$214:$H$219,2,FALSE) -> 0.15 | X39: =VLOOKUP(S39,'PREMIUM TABLES'!$F$199:$H$205,3,FALSE) -> 0.04 | Y39: =SUM(T39:X39) -> 0.745 | Z39: {=IF(AND(Y39>0,Y39<0.5),"C",IF(AND(Y39>=0.5,Y39<0.73),"B",IF(AND(Y39>=0.73,Y39<0.98),"A",NONE)))} -> A | AA39: =VLOOKUP(G39,'ALL (R)'!$N$5:$R$862,5,FALSE) -> R 1 | AB39: =VLOOKUP(AA39,FACTS!$B$2:$L$14,10,FALSE) -> 42500 | AC39: =VLOOKUP(AA39,FACTS!$B$2:$L$14,11,FALSE) -> 47500 | AD39: =VLOOKUP(AA39,FACTS!$B$2:$N$14,13,FALSE) -> 5000 | AE39: =AD39*Y39 -> 3725 | AF39: =AE39+AB39 -> 46225 | AG39: =AF39*FACTS!$T$2 -> 15254.25 | AH39: =Table1[[#This Row],[UNIT (BUILDING) RATE (SEMI FINISHED)]]+4500 -> 50725 | AI39: =Table1[[#This Row],[UNIT (BUILDING) RATE (SEMI FINISHED)]]+7500 -> 53725 | AJ39: =AF39*L39 -> 5500775 | AK39: =Table1[[#This Row],[UNIT (BUILDING) RATE (BASIC FINISH)]]*Table1[[#This Row],[Unit Selling Area]] -> 6036275 | AL39: =Table1[[#This Row],[UNIT (BUILDING) RATE (FULLY FINISH)]]*Table1[[#This Row],[Unit Selling Area]] -> 6393275 | AM39: =AG39*M39 -> 0 | AN39: =(AM39+AJ39)*FACTS!$S$2 -> 467565.88 | AO39: =VLOOKUP(S39,FACTS!$A$17:$C$23,3,FALSE) -> 1 | AP39: =VLOOKUP(AA39,FACTS!$B$2:$J$14,9,FALSE) -> 200000 | AQ39: =Table1[[#This Row],[PARKING VALUE]]*1 -> 200000 | AR39: =AQ39+AM39+AJ39 -> 5700775 | AS39: =Table1[[#This Row],[TOTAL CARS VALUE]]+Table1[[#This Row],[UNIT (BUILDING) VALUE BASIC FINISHED]]+Table1[[#This Row],[UNIT (GARDEN) VALUE]] -> 6236275 | AT39: =Table1[[#This Row],[TOTAL CARS VALUE]]+Table1[[#This Row],[UNIT (GARDEN) VALUE]]+Table1[[#This Row],[UNIT (BUILDING) VALUE FULLY FINISHED]] -> 6593275 | AU39: =VLOOKUP(I39,'C PHASES'!$I$108:$J$110,2,FALSE) -> 45839 | AV39: =VLOOKUP(AA39,'C PHASES'!$I$113:$J$125,2,FALSE) -> 45170
B40: =LEFT(C40,1) -> A | C40: A2 | D40: RESIDENTIAL | E40: 3 | F40: 4 | G40: =LEFT(C40,2)&E40&F40 -> A234 | H40: 2 BEDROOM | I40: =VLOOKUP(C40,'PREMIUM TABLES'!$G$107:$H$149,2,FALSE) -> C1 | J40: 97.09 | K40: 106.42659 | L40: 119 | O40: SE | P40: MIDDLE | Q40: ROAD 18M (BUILDINGS) | R40: =VLOOKUP(E40,'PREMIUM TABLES'!$F$214:$G$219,2,FALSE) -> THIRD | S40: {=IF(AND(L40>0,L40<90),"A",IF(AND(L40>90,L40<123),"B",IF(AND(L40>122,L40<159),"C",IF(AND(L40>159,L40<185),"D",IF(AND(L40>185,L40<230),"E",IF(AND(L40>230,L40<350),"F",NONE))))))} -> B | T40: =VLOOKUP(O40,'PREMIUM TABLES'!$G$165:$H$172,2,FALSE) -> 0.08 | U40: =VLOOKUP(P40,'PREMIUM TABLES'!$G$208:$H$209,2,FALSE) -> 0.025 | V40: =VLOOKUP(Q40,'PREMIUM TABLES'!$G$175:$H$195,2,FALSE) -> 0.15 | W40: =VLOOKUP(R40,'PREMIUM TABLES'!$G$214:$H$219,2,FALSE) -> 0.15 | X40: =VLOOKUP(S40,'PREMIUM TABLES'!$F$199:$H$205,3,FALSE) -> 0.04 | Y40: =SUM(T40:X40) -> 0.445 | Z40: {=IF(AND(Y40>0,Y40<0.5),"C",IF(AND(Y40>=0.5,Y40<0.73),"B",IF(AND(Y40>=0.73,Y40<0.98),"A",NONE)))} -> C | AA40: =VLOOKUP(G40,'ALL (R)'!$N$5:$R$862,5,FALSE) -> R 9 | AB40: =VLOOKUP(AA40,FACTS!$B$2:$L$14,10,FALSE) -> 53550 | AC40: =VLOOKUP(AA40,FACTS!$B$2:$L$14,11,FALSE) -> 59850 | AD40: =VLOOKUP(AA40,FACTS!$B$2:$N$14,13,FALSE) -> 6300 | AE40: =AD40*Y40 -> 2803.5 | AF40: =AE40+AB40 -> 56353.5 | AG40: =AF40*FACTS!$T$2 -> 18596.655 | AH40: =Table1[[#This Row],[UNIT (BUILDING) RATE (SEMI FINISHED)]]+4500 -> 60853.5 | AI40: =Table1[[#This Row],[UNIT (BUILDING) RATE (SEMI FINISHED)]]+7500 -> 63853.5 | AJ40: =AF40*L40 -> 6706066.5 | AK40: =Table1[[#This Row],[UNIT (BUILDING) RATE (BASIC FINISH)]]*Table1[[#This Row],[Unit Selling Area]] -> 7241566.5 | AL40: =Table1[[#This Row],[UNIT (BUILDING) RATE (FULLY FINISH)]]*Table1[[#This Row],[Unit Selling Area]] -> 7598566.5 | AM40: =AG40*M40 -> 0 | AN40: =(AM40+AJ40)*FACTS!$S$2 -> 570015.65 | AO40: =VLOOKUP(S40,FACTS!$A$17:$C$23,3,FALSE) -> 1 | AP40: =VLOOKUP(AA40,FACTS!$B$2:$J$14,9,FALSE) -> 252000 | AQ40: =Table1[[#This Row],[PARKING VALUE]]*1 -> 252000 | AR40: =AQ40+AM40+AJ40 -> 6958066.5 | AS40: =Table1[[#This Row],[TOTAL CARS VALUE]]+Table1[[#This Row],[UNIT (BUILDING) VALUE BASIC FINISHED]]+Table1[[#This Row],[UNIT (GARDEN) VALUE]] -> 7493566.5 | AT40: =Table1[[#This Row],[TOTAL CARS VALUE]]+Table1[[#This Row],[UNIT (GARDEN) VALUE]]+Table1[[#This Row],[UNIT (BUILDING) VALUE FULLY FINISHED]] -> 7850566.5 | AU40: =VLOOKUP(I40,'C PHASES'!$I$108:$J$110,2,FALSE) -> 45839 | AV40: =VLOOKUP(AA40,'C PHASES'!$I$113:$J$125,2,FALSE) -> 45931
... B44: =LEFT(C44,1) -> A | C44: A2 | D44: RESIDENTIAL | E44: 4 | F44: 4 | G44: =LEFT(C44,2)&E44&F44 -> A244 | H44: 2 BEDROOM | I44: =VLOOKUP(C44,'PREMIUM TABLES'!$G$107:$H$149,2,FALSE) -> C1 | J44: 97.17 | K44: 106.51429 | L44: 120 | O44: SE | P44: MIDDLE | Q44: ROAD 18M (BUILDINGS) | R44: =VLOOKUP(E44,'PREMIUM TABLES'!$F$214:$G$219,2,FALSE) -> FORTH | S44: {=IF(AND(L44>0,L44<90),"A",IF(AND(L44>90,L44<123),"B",IF(AND(L44>122,L44<159),"C",IF(AND(L44>159,L44<185),"D",IF(AND(L44>185,L44<230),"E",IF(AND(L44>230,L44<350),"F",NONE))))))} -> B | T44: =VLOOKUP(O44,'PREMIUM TABLES'!$G$165:$H$172,2,FALSE) -> 0.08 | U44: =VLOOKUP(P44,'PREMIUM TABLES'!$G$208:$H$209,2,FALSE) -> 0.025 | V44: =VLOOKUP(Q44,'PREMIUM TABLES'!$G$175:$H$195,2,FALSE) -> 0.15 | W44: =VLOOKUP(R44,'PREMIUM TABLES'!$G$214:$H$219,2,FALSE) -> 0.06 | X44: =VLOOKUP(S44,'PREMIUM TABLES'!$F$199:$H$205,3,FALSE) -> 0.04 | Y44: =SUM(T44:X44) -> 0.355 | Z44: {=IF(AND(Y44>0,Y44<0.5),"C",IF(AND(Y44>=0.5,Y44<0.73),"B",IF(AND(Y44>=0.73,Y44<0.98),"A",NONE)))} -> C | AA44: =VLOOKUP(G44,'ALL (R)'!$N$5:$R$862,5,FALSE) -> R 1 | AB44: =VLOOKUP(AA44,FACTS!$B$2:$L$14,10,FALSE) -> 42500 | AC44: =VLOOKUP(AA44,FACTS!$B$2:$L$14,11,FALSE) -> 47500 | AD44: =VLOOKUP(AA44,FACTS!$B$2:$N$14,13,FALSE) -> 5000 | AE44: =AD44*Y44 -> 1775 | AF44: =AE44+AB44 -> 44275 | AG44: =AF44*FACTS!$T$2 -> 14610.75 | AH44: =Table1[[#This Row],[UNIT (BUILDING) RATE (SEMI FINISHED)]]+4500 -> 48775 | AI44: =Table1[[#This Row],[UNIT (BUILDING) RATE (SEMI FINISHED)]]+7500 -> 51775 | AJ44: =AF44*L44 -> 5313000 | AK44: =Table1[[#This Row],[UNIT (BUILDING) RATE (BASIC FINISH)]]*Table1[[#This Row],[Unit Selling Area]] -> 5853000 | AL44: =Table1[[#This Row],[UNIT (BUILDING) RATE (FULLY FINISH)]]*Table1[[#This Row],[Unit Selling Area]] -> 6213000 | AM44: =AG44*M44 -> 0 | AN44: =(AM44+AJ44)*FACTS!$S$2 -> 451605 | AO44: =VLOOKUP(S44,FACTS!$A$17:$C$23,3,FALSE) -> 1 | AP44: =VLOOKUP(AA44,FACTS!$B$2:$J$14,9,FALSE) -> 200000 | AQ44: =Table1[[#This Row],[PARKING VALUE]]*1 -> 200000 | AR44: =AQ44+AM44+AJ44 -> 5513000 | AS44: =Table1[[#This Row],[TOTAL CARS VALUE]]+Table1[[#This Row],[UNIT (BUILDING) VALUE BASIC FINISHED]]+Table1[[#This Row],[UNIT (GARDEN) VALUE]] -> 6053000 | AT44: =Table1[[#This Row],[TOTAL CARS VALUE]]+Table1[[#This Row],[UNIT (GARDEN) VALUE]]+Table1[[#This Row],[UNIT (BUILDING) VALUE FULLY FINISHED]] -> 6413000 | AU44: =VLOOKUP(I44,'C PHASES'!$I$108:$J$110,2,FALSE) -> 45839 | AV44: =VLOOKUP(AA44,'C PHASES'!$I$113:$J$125,2,FALSE) -> 45170
A45: A | B45: =LEFT(C45,1) -> A | C45: A3 | D45: RESIDENTIAL | E45: 0 | F45: 1 | G45: =LEFT(C45,2)&E45&F45 -> A301 | H45: 2 BEDROOM | I45: =VLOOKUP(C45,'PREMIUM TABLES'!$G$107:$H$149,2,FALSE) -> C1 | J45: 98.17 | K45: 107.61222 | L45: 121 | M45: 31.6147 | O45: SE | P45: MIDDLE | Q45: ROAD 18M (BUILDINGS) | R45: =VLOOKUP(E45,'PREMIUM TABLES'!$F$214:$G$219,2,FALSE) -> GROUND | S45: {=IF(AND(L45>0,L45<90),"A",IF(AND(L45>90,L45<123),"B",IF(AND(L45>122,L45<159),"C",IF(AND(L45>159,L45<185),"D",IF(AND(L45>185,L45<230),"E",IF(AND(L45>230,L45<350),"F",NONE))))))} -> B | T45: =VLOOKUP(O45,'PREMIUM TABLES'!$G$165:$H$172,2,FALSE) -> 0.08 | U45: =VLOOKUP(P45,'PREMIUM TABLES'!$G$208:$H$209,2,FALSE) -> 0.025 | V45: =VLOOKUP(Q45,'PREMIUM TABLES'!$G$175:$H$195,2,FALSE) -> 0.15 | W45: =VLOOKUP(R45,'PREMIUM TABLES'!$G$214:$H$219,2,FALSE) -> 0.05 | X45: =VLOOKUP(S45,'PREMIUM TABLES'!$F$199:$H$205,3,FALSE) -> 0.04 | Y45: =SUM(T45:X45) -> 0.345 | Z45: {=IF(AND(Y45>0,Y45<0.5),"C",IF(AND(Y45>=0.5,Y45<0.73),"B",IF(AND(Y45>=0.73,Y45<0.98),"A",NONE)))} -> C | AA45: =VLOOKUP(G45,'ALL (R)'!$N$5:$R$862,5,FALSE) -> R 1 | AB45: =VLOOKUP(AA45,FACTS!$B$2:$L$14,10,FALSE) -> 42500 | AC45: =VLOOKUP(AA45,FACTS!$B$2:$L$14,11,FALSE) -> 47500 | AD45: =VLOOKUP(AA45,FACTS!$B$2:$N$14,13,FALSE) -> 5000 | AE45: =AD45*Y45 -> 1725 | AF45: =AE45+AB45 -> 44225 | AG45: =AF45*FACTS!$T$2 -> 14594.25 | AH45: =Table1[[#This Row],[UNIT (BUILDING) RATE (SEMI FINISHED)]]+4500 -> 48725 | AI45: =Table1[[#This Row],[UNIT (BUILDING) RATE (SEMI FINISHED)]]+7500 -> 51725 | AJ45: =AF45*L45 -> 5351225 | AK45: =Table1[[#This Row],[UNIT (BUILDING) RATE (BASIC FINISH)]]*Table1[[#This Row],[Unit Selling Area]] -> 5895725 | AL45: =Table1[[#This Row],[UNIT (BUILDING) RATE (FULLY FINISH)]]*Table1[[#This Row],[Unit Selling Area]] -> 6258725 | AM45: =AG45*M45 -> 461392.84 | AN45: =(AM45+AJ45)*FACTS!$S$2 -> 494072.52 | AO45: =VLOOKUP(S45,FACTS!$A$17:$C$23,3,FALSE) -> 1 | AP45: =VLOOKUP(AA45,FACTS!$B$2:$J$14,9,FALSE) -> 200000 | AQ45: =Table1[[#This Row],[PARKING VALUE]]*1 -> 200000 | AR45: =AQ45+AM45+AJ45 -> 6012617.8 | AS45: =Table1[[#This Row],[TOTAL CARS VALUE]]+Table1[[#This Row],[UNIT (BUILDING) VALUE BASIC FINISHED]]+Table1[[#This Row],[UNIT (GARDEN) VALUE]] -> 6557117.8 | AT45: =Table1[[#This Row],[TOTAL CARS VALUE]]+Table1[[#This Row],[UNIT (GARDEN) VALUE]]+Table1[[#This Row],[UNIT (BUILDING) VALUE FULLY FINISHED]] -> 6920117.8 | AU45: =VLOOKUP(I45,'C PHASES'!$I$108:$J$110,2,FALSE) -> 45839 | AV45: =VLOOKUP(AA45,'C PHASES'!$I$113:$J$125,2,FALSE) -> 45170
B46: =LEFT(C46,1) -> A | C46: A3 | D46: RESIDENTIAL | E46: 0 | F46: 2 | G46: =LEFT(C46,2)&E46&F46 -> A302 | H46: 2 BEDROOM | I46: =VLOOKUP(C46,'PREMIUM TABLES'!$G$107:$H$149,2,FALSE) -> C1 | J46: 97.98 | K46: 107.40395 | L46: 121 | M46: 50.7053 | O46: NW | P46: MIDDLE | Q46: SEMI LAKE AND FENCE | R46: =VLOOKUP(E46,'PREMIUM TABLES'!$F$214:$G$219,2,FALSE) -> GROUND | S46: {=IF(AND(L46>0,L46<90),"A",IF(AND(L46>90,L46<123),"B",IF(AND(L46>122,L46<159),"C",IF(AND(L46>159,L46<185),"D",IF(AND(L46>185,L46<230),"E",IF(AND(L46>230,L46<350),"F",NONE))))))} -> B | T46: =VLOOKUP(O46,'PREMIUM TABLES'!$G$165:$H$172,2,FALSE) -> 0.13 | U46: =VLOOKUP(P46,'PREMIUM TABLES'!$G$208:$H$209,2,FALSE) -> 0.025 | V46: =VLOOKUP(Q46,'PREMIUM TABLES'!$G$175:$H$195,2,FALSE) -> 0.25 | W46: =VLOOKUP(R46,'PREMIUM TABLES'!$G$214:$H$219,2,FALSE) -> 0.05 | X46: =VLOOKUP(S46,'PREMIUM TABLES'!$F$199:$H$205,3,FALSE) -> 0.04 | Y46: =SUM(T46:X46) -> 0.495 | Z46: {=IF(AND(Y46>0,Y46<0.5),"C",IF(AND(Y46>=0.5,Y46<0.73),"B",IF(AND(Y46>=0.73,Y46<0.98),"A",NONE)))} -> C | AA46: =VLOOKUP(G46,'ALL (R)'!$N$5:$R$862,5,FALSE) -> R 12 | AB46: =VLOOKUP(AA46,FACTS!$B$2:$L$14,10,FALSE) -> 61625 | AC46: =VLOOKUP(AA46,FACTS!$B$2:$L$14,11,FALSE) -> 68875 | AD46: =VLOOKUP(AA46,FACTS!$B$2:$N$14,13,FALSE) -> 7250 | AE46: =AD46*Y46 -> 3588.75 | AF46: =AE46+AB46 -> 65213.75 | AG46: =AF46*FACTS!$T$2 -> 21520.538 | AH46: =Table1[[#This Row],[UNIT (BUILDING) RATE (SEMI FINISHED)]]+4500 -> 69713.75 | AI46: =Table1[[#This Row],[UNIT (BUILDING) RATE (SEMI FINISHED)]]+7500 -> 72713.75 | AJ46: =AF46*L46 -> 7890863.8 | AK46: =Table1[[#This Row],[UNIT (BUILDING) RATE (BASIC FINISH)]]*Table1[[#This Row],[Unit Selling Area]] -> 8435363.8 | AL46: =Table1[[#This Row],[UNIT (BUILDING) RATE (FULLY FINISH)]]*Table1[[#This Row],[Unit Selling Area]] -> 8798363.8 | AM46: =AG46*M46 -> 1091205.3 | AN46: =(AM46+AJ46)*FACTS!$S$2 -> 763475.87 | AO46: =VLOOKUP(S46,FACTS!$A$17:$C$23,3,FALSE) -> 1 | AP46: =VLOOKUP(AA46,FACTS!$B$2:$J$14,9,FALSE) -> 290000 | AQ46: =Table1[[#This Row],[PARKING VALUE]]*1 -> 290000 | AR46: =AQ46+AM46+AJ46 -> 9272069.1 | AS46: =Table1[[#This Row],[TOTAL CARS VALUE]]+Table1[[#This Row],[UNIT (BUILDING) VALUE BASIC FINISHED]]+Table1[[#This Row],[UNIT (GARDEN) VALUE]] -> 9816569.1 | AT46: =Table1[[#This Row],[TOTAL CARS VALUE]]+Table1[[#This Row],[UNIT (GARDEN) VALUE]]+Table1[[#This Row],[UNIT (BUILDING) VALUE FULLY FINISHED]] -> 10179569 | AU46: =VLOOKUP(I46,'C PHASES'!$I$108:$J$110,2,FALSE) -> 45839 | AV46: =VLOOKUP(AA46,'C PHASES'!$I$113:$J$125,2,FALSE) -> 46204
B47: =LEFT(C47,1) -> A | C47: A3 | D47: RESIDENTIAL | E47: 0 | F47: 3 | G47: =LEFT(C47,2)&E47&F47 -> A303 | H47: 2 BEDROOM | I47: =VLOOKUP(C47,'PREMIUM TABLES'!$G$107:$H$149,2,FALSE) -> C1 | J47: 89.96 | K47: 98.612567 | L47: 111 | M47: 50.5401 | O47: NW | P47: MIDDLE | Q47: FENCE | R47: =VLOOKUP(E47,'PREMIUM TABLES'!$F$214:$G$219,2,FALSE) -> GROUND | S47: {=IF(AND(L47>0,L47<90),"A",IF(AND(L47>90,L47<123),"B",IF(AND(L47>122,L47<159),"C",IF(AND(L47>159,L47<185),"D",IF(AND(L47>185,L47<230),"E",IF(AND(L47>230,L47<350),"F",NONE))))))} -> B | T47: =VLOOKUP(O47,'PREMIUM TABLES'!$G$165:$H$172,2,FALSE) -> 0.13 | U47: =VLOOKUP(P47,'PREMIUM TABLES'!$G$208:$H$209,2,FALSE) -> 0.025 | V47: =VLOOKUP(Q47,'PREMIUM TABLES'!$G$175:$H$195,2,FALSE) -> 0.1 | W47: =VLOOKUP(R47,'PREMIUM TABLES'!$G$214:$H$219,2,FALSE) -> 0.05 | X47: =VLOOKUP(S47,'PREMIUM TABLES'!$F$199:$H$205,3,FALSE) -> 0.04 | Y47: =SUM(T47:X47) -> 0.345 | Z47: {=IF(AND(Y47>0,Y47<0.5),"C",IF(AND(Y47>=0.5,Y47<0.73),"B",IF(AND(Y47>=0.73,Y47<0.98),"A",NONE)))} -> C | AA47: =VLOOKUP(G47,'ALL (R)'!$N$5:$R$862,5,FALSE) -> R 1 | AB47: =VLOOKUP(AA47,FACTS!$B$2:$L$14,10,FALSE) -> 42500 | AC47: =VLOOKUP(AA47,FACTS!$B$2:$L$14,11,FALSE) -> 47500 | AD47: =VLOOKUP(AA47,FACTS!$B$2:$N$14,13,FALSE) -> 5000 | AE47: =AD47*Y47 -> 1725 | AF47: =AE47+AB47 -> 44225 | AG47: =AF47*FACTS!$T$2 -> 14594.25 | AH47: =Table1[[#This Row],[UNIT (BUILDING) RATE (SEMI FINISHED)]]+4500 -> 48725 | AI47: =Table1[[#This Row],[UNIT (BUILDING) RATE (SEMI FINISHED)]]+7500 -> 51725 | AJ47: =AF47*L47 -> 4908975 | AK47: =Table1[[#This Row],[UNIT (BUILDING) RATE (BASIC FINISH)]]*Table1[[#This Row],[Unit Selling Area]] -> 5408475 | AL47: =Table1[[#This Row],[UNIT (BUILDING) RATE (FULLY FINISH)]]*Table1[[#This Row],[Unit Selling Area]] -> 5741475 | AM47: =AG47*M47 -> 737594.85 | AN47: =(AM47+AJ47)*FACTS!$S$2 -> 479958.44 | AO47: =VLOOKUP(S47,FACTS!$A$17:$C$23,3,FALSE) -> 1 | AP47: =VLOOKUP(AA47,FACTS!$B$2:$J$14,9,FALSE) -> 200000 | AQ47: =Table1[[#This Row],[PARKING VALUE]]*1 -> 200000 | AR47: =AQ47+AM47+AJ47 -> 5846569.9 | AS47: =Table1[[#This Row],[TOTAL CARS VALUE]]+Table1[[#This Row],[UNIT (BUILDING) VALUE BASIC FINISHED]]+Table1[[#This Row],[UNIT (GARDEN) VALUE]] -> 6346069.9 | AT47: =Table1[[#This Row],[TOTAL CARS VALUE]]+Table1[[#This Row],[UNIT (GARDEN) VALUE]]+Table1[[#This Row],[UNIT (BUILDING) VALUE FULLY FINISHED]] -> 6679069.9 | AU47: =VLOOKUP(I47,'C PHASES'!$I$108:$J$110,2,FALSE) -> 45839 | AV47: =VLOOKUP(AA47,'C PHASES'!$I$113:$J$125,2,FALSE) -> 45170
B48: =LEFT(C48,1) -> A | C48: A3 | D48: RESIDENTIAL | E48: 0 | F48: 4 | G48: =LEFT(C48,2)&E48&F48 -> A304 | H48: 1 BEDROOM (STUDIO) | I48: =VLOOKUP(C48,'PREMIUM TABLES'!$G$107:$H$149,2,FALSE) -> C1 | J48: 60.98 | K48: 66.845202 | L48: 75 | M48: 23.8301 | O48: SE | P48: MIDDLE | Q48: ROAD 18M (BUILDINGS) | R48: =VLOOKUP(E48,'PREMIUM TABLES'!$F$214:$G$219,2,FALSE) -> GROUND | S48: {=IF(AND(L48>0,L48<90),"A",IF(AND(L48>90,L48<123),"B",IF(AND(L48>122,L48<159),"C",IF(AND(L48>159,L48<185),"D",IF(AND(L48>185,L48<230),"E",IF(AND(L48>230,L48<350),"F",NONE))))))} -> A | T48: =VLOOKUP(O48,'PREMIUM TABLES'!$G$165:$H$172,2,FALSE) -> 0.08 | U48: =VLOOKUP(P48,'PREMIUM TABLES'!$G$208:$H$209,2,FALSE) -> 0.025 | V48: =VLOOKUP(Q48,'PREMIUM TABLES'!$G$175:$H$195,2,FALSE) -> 0.15 | W48: =VLOOKUP(R48,'PREMIUM TABLES'!$G$214:$H$219,2,FALSE) -> 0.05 | X48: =VLOOKUP(S48,'PREMIUM TABLES'!$F$199:$H$205,3,FALSE) -> 0.05 | Y48: =SUM(T48:X48) -> 0.355 | Z48: {=IF(AND(Y48>0,Y48<0.5),"C",IF(AND(Y48>=0.5,Y48<0.73),"B",IF(AND(Y48>=0.73,Y48<0.98),"A",NONE)))} -> C | AA48: =VLOOKUP(G48,'ALL (R)'!$N$5:$R$862,5,FALSE) -> R 1 | AB48: =VLOOKUP(AA48,FACTS!$B$2:$L$14,10,FALSE) -> 42500 | AC48: =VLOOKUP(AA48,FACTS!$B$2:$L$14,11,FALSE) -> 47500 | AD48: =VLOOKUP(AA48,FACTS!$B$2:$N$14,13,FALSE) -> 5000 | AE48: =AD48*Y48 -> 1775 | AF48: =AE48+AB48 -> 44275 | AG48: =AF48*FACTS!$T$2 -> 14610.75 | AH48: =Table1[[#This Row],[UNIT (BUILDING) RATE (SEMI FINISHED)]]+4500 -> 48775 | AI48: =Table1[[#This Row],[UNIT (BUILDING) RATE (SEMI FINISHED)]]+7500 -> 51775 | AJ48: =AF48*L48 -> 3320625 | AK48: =Table1[[#This Row],[UNIT (BUILDING) RATE (BASIC FINISH)]]*Table1[[#This Row],[Unit Selling Area]] -> 3658125 | AL48: =Table1[[#This Row],[UNIT (BUILDING) RATE (FULLY FINISH)]]*Table1[[#This Row],[Unit Selling Area]] -> 3883125 | AM48: =AG48*M48 -> 348175.63 | AN48: =(AM48+AJ48)*FACTS!$S$2 -> 311848.05 | AO48: =VLOOKUP(S48,FACTS!$A$17:$C$23,3,FALSE) -> 1 | AP48: =VLOOKUP(AA48,FACTS!$B$2:$J$14,9,FALSE) -> 200000 | AQ48: =Table1[[#This Row],[PARKING VALUE]]*1 -> 200000 | AR48: =AQ48+AM48+AJ48 -> 3868800.6 | AS48: =Table1[[#This Row],[TOTAL CARS VALUE]]+Table1[[#This Row],[UNIT (BUILDING) VALUE BASIC FINISHED]]+Table1[[#This Row],[UNIT (GARDEN) VALUE]] -> 4206300.6 | AT48: =Table1[[#This Row],[TOTAL CARS VALUE]]+Table1[[#This Row],[UNIT (GARDEN) VALUE]]+Table1[[#This Row],[UNIT (BUILDING) VALUE FULLY FINISHED]] -> 4431300.6 | AU48: =VLOOKUP(I48,'C PHASES'!$I$108:$J$110,2,FALSE) -> 45839 | AV48: =VLOOKUP(AA48,'C PHASES'!$I$113:$J$125,2,FALSE) -> 45170
B49: =LEFT(C49,1) -> A | C49: A3 | D49: RESIDENTIAL | E49: 1 | F49: 1 | G49: =LEFT(C49,2)&E49&F49 -> A311 | H49: 2 BEDROOM | I49: =VLOOKUP(C49,'PREMIUM TABLES'!$G$107:$H$149,2,FALSE) -> C1 | J49: 97.09 | K49: 106.42835 | L49: 119 | O49: SE | P49: MIDDLE | Q49: ROAD 18M (BUILDINGS) | R49: =VLOOKUP(E49,'PREMIUM TABLES'!$F$214:$G$219,2,FALSE) -> FIRST | S49: {=IF(AND(L49>0,L49<90),"A",IF(AND(L49>90,L49<123),"B",IF(AND(L49>122,L49<159),"C",IF(AND(L49>159,L49<185),"D",IF(AND(L49>185,L49<230),"E",IF(AND(L49>230,L49<350),"F",NONE))))))} -> B | T49: =VLOOKUP(O49,'PREMIUM TABLES'!$G$165:$H$172,2,FALSE) -> 0.08 | U49: =VLOOKUP(P49,'PREMIUM TABLES'!$G$208:$H$209,2,FALSE) -> 0.025 | V49: =VLOOKUP(Q49,'PREMIUM TABLES'!$G$175:$H$195,2,FALSE) -> 0.15 | W49: =VLOOKUP(R49,'PREMIUM TABLES'!$G$214:$H$219,2,FALSE) -> 0.07 | X49: =VLOOKUP(S49,'PREMIUM TABLES'!$F$199:$H$205,3,FALSE) -> 0.04 | Y49: =SUM(T49:X49) -> 0.365 | Z49: {=IF(AND(Y49>0,Y49<0.5),"C",IF(AND(Y49>=0.5,Y49<0.73),"B",IF(AND(Y49>=0.73,Y49<0.98),"A",NONE)))} -> C | AA49: =VLOOKUP(G49,'ALL (R)'!$N$5:$R$862,5,FALSE) -> R 2 | AB49: =VLOOKUP(AA49,FACTS!$B$2:$L$14,10,FALSE) -> 43562.5 | AC49: =VLOOKUP(AA49,FACTS!$B$2:$L$14,11,FALSE) -> 48687.5 | AD49: =VLOOKUP(AA49,FACTS!$B$2:$N$14,13,FALSE) -> 5125 | AE49: =AD49*Y49 -> 1870.625 | AF49: =AE49+AB49 -> 45433.125 | AG49: =AF49*FACTS!$T$2 -> 14992.931 | AH49: =Table1[[#This Row],[UNIT (BUILDING) RATE (SEMI FINISHED)]]+4500 -> 49933.125 | AI49: =Table1[[#This Row],[UNIT (BUILDING) RATE (SEMI FINISHED)]]+7500 -> 52933.125 | AJ49: =AF49*L49 -> 5406541.9 | AK49: =Table1[[#This Row],[UNIT (BUILDING) RATE (BASIC FINISH)]]*Table1[[#This Row],[Unit Selling Area]] -> 5942041.9 | AL49: =Table1[[#This Row],[UNIT (BUILDING) RATE (FULLY FINISH)]]*Table1[[#This Row],[Unit Selling Area]] -> 6299041.9 | AM49: =AG49*M49 -> 0 | AN49: =(AM49+AJ49)*FACTS!$S$2 -> 459556.06 | AO49: =VLOOKUP(S49,FACTS!$A$17:$C$23,3,FALSE) -> 1 | AP49: =VLOOKUP(AA49,FACTS!$B$2:$J$14,9,FALSE) -> 205000 | AQ49: =Table1[[#This Row],[PARKING VALUE]]*1 -> 205000 | AR49: =AQ49+AM49+AJ49 -> 5611541.9 | AS49: =Table1[[#This Row],[TOTAL CARS VALUE]]+Table1[[#This Row],[UNIT (BUILDING) VALUE BASIC FINISHED]]+Table1[[#This Row],[UNIT (GARDEN) VALUE]] -> 6147041.9 | AT49: =Table1[[#This Row],[TOTAL CARS VALUE]]+Table1[[#This Row],[UNIT (GARDEN) VALUE]]+Table1[[#This Row],[UNIT (BUILDING) VALUE FULLY FINISHED]] -> 6504041.9 | AU49: =VLOOKUP(I49,'C PHASES'!$I$108:$J$110,2,FALSE) -> 45839 | AV49: =VLOOKUP(AA49,'C PHASES'!$I$113:$J$125,2,FALSE) -> 45292
B50: =LEFT(C50,1) -> A | C50: A3 | D50: RESIDENTIAL | E50: 1 | F50: 2 | G50: =LEFT(C50,2)&E50&F50 -> A312 | H50: 2 BEDROOM | I50: =VLOOKUP(C50,'PREMIUM TABLES'!$G$107:$H$149,2,FALSE) -> C1 | J50: 97.06 | K50: 106.39546 | L50: 119 | O50: NW | P50: MIDDLE | Q50: SEMI LAKE AND FENCE | R50: =VLOOKUP(E50,'PREMIUM TABLES'!$F$214:$G$219,2,FALSE) -> FIRST | S50: {=IF(AND(L50>0,L50<90),"A",IF(AND(L50>90,L50<123),"B",IF(AND(L50>122,L50<159),"C",IF(AND(L50>159,L50<185),"D",IF(AND(L50>185,L50<230),"E",IF(AND(L50>230,L50<350),"F",NONE))))))} -> B | T50: =VLOOKUP(O50,'PREMIUM TABLES'!$G$165:$H$172,2,FALSE) -> 0.13 | U50: =VLOOKUP(P50,'PREMIUM TABLES'!$G$208:$H$209,2,FALSE) -> 0.025 | V50: =VLOOKUP(Q50,'PREMIUM TABLES'!$G$175:$H$195,2,FALSE) -> 0.25 | W50: =VLOOKUP(R50,'PREMIUM TABLES'!$G$214:$H$219,2,FALSE) -> 0.07 | X50: =VLOOKUP(S50,'PREMIUM TABLES'!$F$199:$H$205,3,FALSE) -> 0.04 | Y50: =SUM(T50:X50) -> 0.515 | Z50: {=IF(AND(Y50>0,Y50<0.5),"C",IF(AND(Y50>=0.5,Y50<0.73),"B",IF(AND(Y50>=0.73,Y50<0.98),"A",NONE)))} -> B | AA50: =VLOOKUP(G50,'ALL (R)'!$N$5:$R$862,5,FALSE) -> R 1 | AB50: =VLOOKUP(AA50,FACTS!$B$2:$L$14,10,FALSE) -> 42500 | AC50: =VLOOKUP(AA50,FACTS!$B$2:$L$14,11,FALSE) -> 47500 | AD50: =VLOOKUP(AA50,FACTS!$B$2:$N$14,13,FALSE) -> 5000 | AE50: =AD50*Y50 -> 2575 | AF50: =AE50+AB50 -> 45075 | AG50: =AF50*FACTS!$T$2 -> 14874.75 | AH50: =Table1[[#This Row],[UNIT (BUILDING) RATE (SEMI FINISHED)]]+4500 -> 49575 | AI50: =Table1[[#This Row],[UNIT (BUILDING) RATE (SEMI FINISHED)]]+7500 -> 52575 | AJ50: =AF50*L50 -> 5363925 | AK50: =Table1[[#This Row],[UNIT (BUILDING) RATE (BASIC FINISH)]]*Table1[[#This Row],[Unit Selling Area]] -> 5899425 | AL50: =Table1[[#This Row],[UNIT (BUILDING) RATE (FULLY FINISH)]]*Table1[[#This Row],[Unit Selling Area]] -> 6256425 | AM50: =AG50*M50 -> 0 | AN50: =(AM50+AJ50)*FACTS!$S$2 -> 455933.63 | AO50: =VLOOKUP(S50,FACTS!$A$17:$C$23,3,FALSE) -> 1 | AP50: =VLOOKUP(AA50,FACTS!$B$2:$J$14,9,FALSE) -> 200000 | AQ50: =Table1[[#This Row],[PARKING VALUE]]*1 -> 200000 | AR50: =AQ50+AM50+AJ50 -> 5563925 | AS50: =Table1[[#This Row],[TOTAL CARS VALUE]]+Table1[[#This Row],[UNIT (BUILDING) VALUE BASIC FINISHED]]+Table1[[#This Row],[UNIT (GARDEN) VALUE]] -> 6099425 | AT50: =Table1[[#This Row],[TOTAL CARS VALUE]]+Table1[[#This Row],[UNIT (GARDEN) VALUE]]+Table1[[#This Row],[UNIT (BUILDING) VALUE FULLY FINISHED]] -> 6456425 | AU50: =VLOOKUP(I50,'C PHASES'!$I$108:$J$110,2,FALSE) -> 45839 | AV50: =VLOOKUP(AA50,'C PHASES'!$I$113:$J$125,2,FALSE) -> 45170
B51: =LEFT(C51,1) -> A | C51: A3 | D51: RESIDENTIAL | E51: 1 | F51: 3 | G51: =LEFT(C51,2)&E51&F51 -> A313 | H51: 2 BEDROOM | I51: =VLOOKUP(C51,'PREMIUM TABLES'!$G$107:$H$149,2,FALSE) -> C1 | J51: 89.05 | K51: 97.615041 | L51: 110 | O51: NW | P51: MIDDLE | Q51: LAYAN VILLAS | R51: =VLOOKUP(E51,'PREMIUM TABLES'!$F$214:$G$219,2,FALSE) -> FIRST | S51: {=IF(AND(L51>0,L51<90),"A",IF(AND(L51>90,L51<123),"B",IF(AND(L51>122,L51<159),"C",IF(AND(L51>159,L51<185),"D",IF(AND(L51>185,L51<230),"E",IF(AND(L51>230,L51<350),"F",NONE))))))} -> B | T51: =VLOOKUP(O51,'PREMIUM TABLES'!$G$165:$H$172,2,FALSE) -> 0.13 | U51: =VLOOKUP(P51,'PREMIUM TABLES'!$G$208:$H$209,2,FALSE) -> 0.025 | V51: =VLOOKUP(Q51,'PREMIUM TABLES'!$G$175:$H$195,2,FALSE) -> 0.2 | W51: =VLOOKUP(R51,'PREMIUM TABLES'!$G$214:$H$219,2,FALSE) -> 0.07 | X51: =VLOOKUP(S51,'PREMIUM TABLES'!$F$199:$H$205,3,FALSE) -> 0.04 | Y51: =SUM(T51:X51) -> 0.465 | Z51: {=IF(AND(Y51>0,Y51<0.5),"C",IF(AND(Y51>=0.5,Y51<0.73),"B",IF(AND(Y51>=0.73,Y51<0.98),"A",NONE)))} -> C | AA51: =VLOOKUP(G51,'ALL (R)'!$N$5:$R$862,5,FALSE) -> R 10 | AB51: =VLOOKUP(AA51,FACTS!$B$2:$L$14,10,FALSE) -> 56100 | AC51: =VLOOKUP(AA51,FACTS!$B$2:$L$14,11,FALSE) -> 62700 | AD51: =VLOOKUP(AA51,FACTS!$B$2:$N$14,13,FALSE) -> 6600 | AE51: =AD51*Y51 -> 3069 | AF51: =AE51+AB51 -> 59169 | AG51: =AF51*FACTS!$T$2 -> 19525.77 | AH51: =Table1[[#This Row],[UNIT (BUILDING) RATE (SEMI FINISHED)]]+4500 -> 63669 | AI51: =Table1[[#This Row],[UNIT (BUILDING) RATE (SEMI FINISHED)]]+7500 -> 66669 | AJ51: =AF51*L51 -> 6508590 | AK51: =Table1[[#This Row],[UNIT (BUILDING) RATE (BASIC FINISH)]]*Table1[[#This Row],[Unit Selling Area]] -> 7003590 | AL51: =Table1[[#This Row],[UNIT (BUILDING) RATE (FULLY FINISH)]]*Table1[[#This Row],[Unit Selling Area]] -> 7333590 | AM51: =AG51*M51 -> 0 | AN51: =(AM51+AJ51)*FACTS!$S$2 -> 553230.15 | AO51: =VLOOKUP(S51,FACTS!$A$17:$C$23,3,FALSE) -> 1 | AP51: =VLOOKUP(AA51,FACTS!$B$2:$J$14,9,FALSE) -> 264000 | AQ51: =Table1[[#This Row],[PARKING VALUE]]*1 -> 264000 | AR51: =AQ51+AM51+AJ51 -> 6772590 | AS51: =Table1[[#This Row],[TOTAL CARS VALUE]]+Table1[[#This Row],[UNIT (BUILDING) VALUE BASIC FINISHED]]+Table1[[#This Row],[UNIT (GARDEN) VALUE]] -> 7267590 | AT51: =Table1[[#This Row],[TOTAL CARS VALUE]]+Table1[[#This Row],[UNIT (GARDEN) VALUE]]+Table1[[#This Row],[UNIT (BUILDING) VALUE FULLY FINISHED]] -> 7597590 | AU51: =VLOOKUP(I51,'C PHASES'!$I$108:$J$110,2,FALSE) -> 45839 | AV51: =VLOOKUP(AA51,'C PHASES'!$I$113:$J$125,2,FALSE) -> 46023
B52: =LEFT(C52,1) -> A | C52: A3 | D52: RESIDENTIAL | E52: 1 | F52: 4 | G52: =LEFT(C52,2)&E52&F52 -> A314 | H52: 1 BEDROOM (STUDIO) | I52: =VLOOKUP(C52,'PREMIUM TABLES'!$G$107:$H$149,2,FALSE) -> C1 | J52: 61.82 | K52: 67.765995 | L52: 76 | O52: SE | P52: MIDDLE | Q52: ROAD 18M (BUILDINGS) | R52: =VLOOKUP(E52,'PREMIUM TABLES'!$F$214:$G$219,2,FALSE) -> FIRST | S52: {=IF(AND(L52>0,L52<90),"A",IF(AND(L52>90,L52<123),"B",IF(AND(L52>122,L52<159),"C",IF(AND(L52>159,L52<185),"D",IF(AND(L52>185,L52<230),"E",IF(AND(L52>230,L52<350),"F",NONE))))))} -> A | T52: =VLOOKUP(O52,'PREMIUM TABLES'!$G$165:$H$172,2,FALSE) -> 0.08 | U52: =VLOOKUP(P52,'PREMIUM TABLES'!$G$208:$H$209,2,FALSE) -> 0.025 | V52: =VLOOKUP(Q52,'PREMIUM TABLES'!$G$175:$H$195,2,FALSE) -> 0.15 | W52: =VLOOKUP(R52,'PREMIUM TABLES'!$G$214:$H$219,2,FALSE) -> 0.07 | X52: =VLOOKUP(S52,'PREMIUM TABLES'!$F$199:$H$205,3,FALSE) -> 0.05 | Y52: =SUM(T52:X52) -> 0.375 | Z52: {=IF(AND(Y52>0,Y52<0.5),"C",IF(AND(Y52>=0.5,Y52<0.73),"B",IF(AND(Y52>=0.73,Y52<0.98),"A",NONE)))} -> C | AA52: =VLOOKUP(G52,'ALL (R)'!$N$5:$R$862,5,FALSE) -> R 3 | AB52: =VLOOKUP(AA52,FACTS!$B$2:$L$14,10,FALSE) -> 44625 | AC52: =VLOOKUP(AA52,FACTS!$B$2:$L$14,11,FALSE) -> 49875 | AD52: =VLOOKUP(AA52,FACTS!$B$2:$N$14,13,FALSE) -> 5250 | AE52: =AD52*Y52 -> 1968.75 | AF52: =AE52+AB52 -> 46593.75 | AG52: =AF52*FACTS!$T$2 -> 15375.938 | AH52: =Table1[[#This Row],[UNIT (BUILDING) RATE (SEMI FINISHED)]]+4500 -> 51093.75 | AI52: =Table1[[#This Row],[UNIT (BUILDING) RATE (SEMI FINISHED)]]+7500 -> 54093.75 | AJ52: =AF52*L52 -> 3541125 | AK52: =Table1[[#This Row],[UNIT (BUILDING) RATE (BASIC FINISH)]]*Table1[[#This Row],[Unit Selling Area]] -> 3883125 | AL52: =Table1[[#This Row],[UNIT (BUILDING) RATE (FULLY FINISH)]]*Table1[[#This Row],[Unit Selling Area]] -> 4111125 | AM52: =AG52*M52 -> 0 | AN52: =(AM52+AJ52)*FACTS!$S$2 -> 300995.62 | AO52: =VLOOKUP(S52,FACTS!$A$17:$C$23,3,FALSE) -> 1 | AP52: =VLOOKUP(AA52,FACTS!$B$2:$J$14,9,FALSE) -> 210000 | AQ52: =Table1[[#This Row],[PARKING VALUE]]*1 -> 210000 | AR52: =AQ52+AM52+AJ52 -> 3751125 | AS52: =Table1[[#This Row],[TOTAL CARS VALUE]]+Table1[[#This Row],[UNIT (BUILDING) VALUE BASIC FINISHED]]+Table1[[#This Row],[UNIT (GARDEN) VALUE]] -> 4093125 | AT52: =Table1[[#This Row],[TOTAL CARS VALUE]]+Table1[[#This Row],[UNIT (GARDEN) VALUE]]+Table1[[#This Row],[UNIT (BUILDING) VALUE FULLY FINISHED]] -> 4321125 | AU52: =VLOOKUP(I52,'C PHASES'!$I$108:$J$110,2,FALSE) -> 45839 | AV52: =VLOOKUP(AA52,'C PHASES'!$I$113:$J$125,2,FALSE) -> 45383
B53: =LEFT(C53,1) -> A | C53: A3 | D53: RESIDENTIAL | E53: 2 | F53: 1 | G53: =LEFT(C53,2)&E53&F53 -> A321 | H53: 2 BEDROOM | I53: =VLOOKUP(C53,'PREMIUM TABLES'!$G$107:$H$149,2,FALSE) -> C1 | J53: 98.95 | K53: 108.46725 | L53: 122 | O53: SE | P53: MIDDLE | Q53: ROAD 18M (BUILDINGS) | R53: =VLOOKUP(E53,'PREMIUM TABLES'!$F$214:$G$219,2,FALSE) -> SECOND | S53: {=IF(AND(L53>0,L53<90),"A",IF(AND(L53>90,L53<123),"B",IF(AND(L53>122,L53<159),"C",IF(AND(L53>159,L53<185),"D",IF(AND(L53>185,L53<230),"E",IF(AND(L53>230,L53<350),"F",NONE))))))} -> B | T53: =VLOOKUP(O53,'PREMIUM TABLES'!$G$165:$H$172,2,FALSE) -> 0.08 | U53: =VLOOKUP(P53,'PREMIUM TABLES'!$G$208:$H$209,2,FALSE) -> 0.025 | V53: =VLOOKUP(Q53,'PREMIUM TABLES'!$G$175:$H$195,2,FALSE) -> 0.15 | W53: =VLOOKUP(R53,'PREMIUM TABLES'!$G$214:$H$219,2,FALSE) -> 0.11 | X53: =VLOOKUP(S53,'PREMIUM TABLES'!$F$199:$H$205,3,FALSE) -> 0.04 | Y53: =SUM(T53:X53) -> 0.405 | Z53: {=IF(AND(Y53>0,Y53<0.5),"C",IF(AND(Y53>=0.5,Y53<0.73),"B",IF(AND(Y53>=0.73,Y53<0.98),"A",NONE)))} -> C | AA53: =VLOOKUP(G53,'ALL (R)'!$N$5:$R$862,5,FALSE) -> R 6 | AB53: =VLOOKUP(AA53,FACTS!$B$2:$L$14,10,FALSE) -> 48450 | AC53: =VLOOKUP(AA53,FACTS!$B$2:$L$14,11,FALSE) -> 54150 | AD53: =VLOOKUP(AA53,FACTS!$B$2:$N$14,13,FALSE) -> 5700 | AE53: =AD53*Y53 -> 2308.5 | AF53: =AE53+AB53 -> 50758.5 | AG53: =AF53*FACTS!$T$2 -> 16750.305 | AH53: =Table1[[#This Row],[UNIT (BUILDING) RATE (SEMI FINISHED)]]+4500 -> 55258.5 | AI53: =Table1[[#This Row],[UNIT (BUILDING) RATE (SEMI FINISHED)]]+7500 -> 58258.5 | AJ53: =AF53*L53 -> 6192537 | AK53: =Table1[[#This Row],[UNIT (BUILDING) RATE (BASIC FINISH)]]*Table1[[#This Row],[Unit Selling Area]] -> 6741537 | AL53: =Table1[[#This Row],[UNIT (BUILDING) RATE (FULLY FINISH)]]*Table1[[#This Row],[Unit Selling Area]] -> 7107537 | AM53: =AG53*M53 -> 0 | AN53: =(AM53+AJ53)*FACTS!$S$2 -> 526365.65 | AO53: =VLOOKUP(S53,FACTS!$A$17:$C$23,3,FALSE) -> 1 | AP53: =VLOOKUP(AA53,FACTS!$B$2:$J$14,9,FALSE) -> 228000 | AQ53: =Table1[[#This Row],[PARKING VALUE]]*1 -> 228000 | AR53: =AQ53+AM53+AJ53 -> 6420537 | AS53: =Table1[[#This Row],[TOTAL CARS VALUE]]+Table1[[#This Row],[UNIT (BUILDING) VALUE BASIC FINISHED]]+Table1[[#This Row],[UNIT (GARDEN) VALUE]] -> 6969537 | AT53: =Table1[[#This Row],[TOTAL CARS VALUE]]+Table1[[#This Row],[UNIT (GARDEN) VALUE]]+Table1[[#This Row],[UNIT (BUILDING) VALUE FULLY FINISHED]] -> 7335537 | AU53: =VLOOKUP(I53,'C PHASES'!$I$108:$J$110,2,FALSE) -> 45839 | AV53: =VLOOKUP(AA53,'C PHASES'!$I$113:$J$125,2,FALSE) -> 45658
B54: =LEFT(C54,1) -> A | C54: A3 | D54: RESIDENTIAL | E54: 2 | F54: 2 | G54: =LEFT(C54,2)&E54&F54 -> A322 | H54: 2 BEDROOM | I54: =VLOOKUP(C54,'PREMIUM TABLES'!$G$107:$H$149,2,FALSE) -> C1 | J54: 98.93 | K54: 108.44532 | L54: 122 | O54: NW | P54: MIDDLE | Q54: SEMI LAKE AND FENCE | R54: =VLOOKUP(E54,'PREMIUM TABLES'!$F$214:$G$219,2,FALSE) -> SECOND | S54: {=IF(AND(L54>0,L54<90),"A",IF(AND(L54>90,L54<123),"B",IF(AND(L54>122,L54<159),"C",IF(AND(L54>159,L54<185),"D",IF(AND(L54>185,L54<230),"E",IF(AND(L54>230,L54<350),"F",NONE))))))} -> B | T54: =VLOOKUP(O54,'PREMIUM TABLES'!$G$165:$H$172,2,FALSE) -> 0.13 | U54: =VLOOKUP(P54,'PREMIUM TABLES'!$G$208:$H$209,2,FALSE) -> 0.025 | V54: =VLOOKUP(Q54,'PREMIUM TABLES'!$G$175:$H$195,2,FALSE) -> 0.25 | W54: =VLOOKUP(R54,'PREMIUM TABLES'!$G$214:$H$219,2,FALSE) -> 0.11 | X54: =VLOOKUP(S54,'PREMIUM TABLES'!$F$199:$H$205,3,FALSE) -> 0.04 | Y54: =SUM(T54:X54) -> 0.555 | Z54: {=IF(AND(Y54>0,Y54<0.5),"C",IF(AND(Y54>=0.5,Y54<0.73),"B",IF(AND(Y54>=0.73,Y54<0.98),"A",NONE)))} -> B | AA54: =VLOOKUP(G54,'ALL (R)'!$N$5:$R$862,5,FALSE) -> R 1 | AB54: =VLOOKUP(AA54,FACTS!$B$2:$L$14,10,FALSE) -> 42500 | AC54: =VLOOKUP(AA54,FACTS!$B$2:$L$14,11,FALSE) -> 47500 | AD54: =VLOOKUP(AA54,FACTS!$B$2:$N$14,13,FALSE) -> 5000 | AE54: =AD54*Y54 -> 2775 | AF54: =AE54+AB54 -> 45275 | AG54: =AF54*FACTS!$T$2 -> 14940.75 | AH54: =Table1[[#This Row],[UNIT (BUILDING) RATE (SEMI FINISHED)]]+4500 -> 49775 | AI54: =Table1[[#This Row],[UNIT (BUILDING) RATE (SEMI FINISHED)]]+7500 -> 52775 | AJ54: =AF54*L54 -> 5523550 | AK54: =Table1[[#This Row],[UNIT (BUILDING) RATE (BASIC FINISH)]]*Table1[[#This Row],[Unit Selling Area]] -> 6072550 | AL54: =Table1[[#This Row],[UNIT (BUILDING) RATE (FULLY FINISH)]]*Table1[[#This Row],[Unit Selling Area]] -> 6438550 | AM54: =AG54*M54 -> 0 | AN54: =(AM54+AJ54)*FACTS!$S$2 -> 469501.75 | AO54: =VLOOKUP(S54,FACTS!$A$17:$C$23,3,FALSE) -> 1 | AP54: =VLOOKUP(AA54,FACTS!$B$2:$J$14,9,FALSE) -> 200000 | AQ54: =Table1[[#This Row],[PARKING VALUE]]*1 -> 200000 | AR54: =AQ54+AM54+AJ54 -> 5723550 | AS54: =Table1[[#This Row],[TOTAL CARS VALUE]]+Table1[[#This Row],[UNIT (BUILDING) VALUE BASIC FINISHED]]+Table1[[#This Row],[UNIT (GARDEN) VALUE]] -> 6272550 | AT54: =Table1[[#This Row],[TOTAL CARS VALUE]]+Table1[[#This Row],[UNIT (GARDEN) VALUE]]+Table1[[#This Row],[UNIT (BUILDING) VALUE FULLY FINISHED]] -> 6638550 | AU54: =VLOOKUP(I54,'C PHASES'!$I$108:$J$110,2,FALSE) -> 45839 | AV54: =VLOOKUP(AA54,'C PHASES'!$I$113:$J$125,2,FALSE) -> 45170
B55: =LEFT(C55,1) -> A | C55: A3 | D55: RESIDENTIAL | E55: 2 | F55: 3 | G55: =LEFT(C55,2)&E55&F55 -> A323 | H55: 2 BEDROOM | I55: =VLOOKUP(C55,'PREMIUM TABLES'!$G$107:$H$149,2,FALSE) -> C1 | J55: 90.91 | K55: 99.653941 | L55: 112 | O55: NW | P55: MIDDLE | Q55: LAYAN VILLAS | R55: =VLOOKUP(E55,'PREMIUM TABLES'!$F$214:$G$219,2,FALSE) -> SECOND | S55: {=IF(AND(L55>0,L55<90),"A",IF(AND(L55>90,L55<123),"B",IF(AND(L55>122,L55<159),"C",IF(AND(L55>159,L55<185),"D",IF(AND(L55>185,L55<230),"E",IF(AND(L55>230,L55<350),"F",NONE))))))} -> B | T55: =VLOOKUP(O55,'PREMIUM TABLES'!$G$165:$H$172,2,FALSE) -> 0.13 | U55: =VLOOKUP(P55,'PREMIUM TABLES'!$G$208:$H$209,2,FALSE) -> 0.025 | V55: =VLOOKUP(Q55,'PREMIUM TABLES'!$G$175:$H$195,2,FALSE) -> 0.2 | W55: =VLOOKUP(R55,'PREMIUM TABLES'!$G$214:$H$219,2,FALSE) -> 0.11 | X55: =VLOOKUP(S55,'PREMIUM TABLES'!$F$199:$H$205,3,FALSE) -> 0.04 | Y55: =SUM(T55:X55) -> 0.505 | Z55: {=IF(AND(Y55>0,Y55<0.5),"C",IF(AND(Y55>=0.5,Y55<0.73),"B",IF(AND(Y55>=0.73,Y55<0.98),"A",NONE)))} -> B | AA55: =VLOOKUP(G55,'ALL (R)'!$N$5:$R$862,5,FALSE) -> R 1 | AB55: =VLOOKUP(AA55,FACTS!$B$2:$L$14,10,FALSE) -> 42500 | AC55: =VLOOKUP(AA55,FACTS!$B$2:$L$14,11,FALSE) -> 47500 | AD55: =VLOOKUP(AA55,FACTS!$B$2:$N$14,13,FALSE) -> 5000 | AE55: =AD55*Y55 -> 2525 | AF55: =AE55+AB55 -> 45025 | AG55: =AF55*FACTS!$T$2 -> 14858.25 | AH55: =Table1[[#This Row],[UNIT (BUILDING) RATE (SEMI FINISHED)]]+4500 -> 49525 | AI55: =Table1[[#This Row],[UNIT (BUILDING) RATE (SEMI FINISHED)]]+7500 -> 52525 | AJ55: =AF55*L55 -> 5042800 | AK55: =Table1[[#This Row],[UNIT (BUILDING) RATE (BASIC FINISH)]]*Table1[[#This Row],[Unit Selling Area]] -> 5546800 | AL55: =Table1[[#This Row],[UNIT (BUILDING) RATE (FULLY FINISH)]]*Table1[[#This Row],[Unit Selling Area]] -> 5882800 | AM55: =AG55*M55 -> 0 | AN55: =(AM55+AJ55)*FACTS!$S$2 -> 428638 | AO55: =VLOOKUP(S55,FACTS!$A$17:$C$23,3,FALSE) -> 1 | AP55: =VLOOKUP(AA55,FACTS!$B$2:$J$14,9,FALSE) -> 200000 | AQ55: =Table1[[#This Row],[PARKING VALUE]]*1 -> 200000 | AR55: =AQ55+AM55+AJ55 -> 5242800 | AS55: =Table1[[#This Row],[TOTAL CARS VALUE]]+Table1[[#This Row],[UNIT (BUILDING) VALUE BASIC FINISHED]]+Table1[[#This Row],[UNIT (GARDEN) VALUE]] -> 5746800 | AT55: =Table1[[#This Row],[TOTAL CARS VALUE]]+Table1[[#This Row],[UNIT (GARDEN) VALUE]]+Table1[[#This Row],[UNIT (BUILDING) VALUE FULLY FINISHED]] -> 6082800 | AU55: =VLOOKUP(I55,'C PHASES'!$I$108:$J$110,2,FALSE) -> 45839 | AV55: =VLOOKUP(AA55,'C PHASES'!$I$113:$J$125,2,FALSE) -> 45170
B56: =LEFT(C56,1) -> A | C56: A3 | D56: RESIDENTIAL | E56: 2 | F56: 4 | G56: =LEFT(C56,2)&E56&F56 -> A324 | H56: 2 BEDROOM | I56: =VLOOKUP(C56,'PREMIUM TABLES'!$G$107:$H$149,2,FALSE) -> C1 | J56: 90.9 | K56: 99.642979 | L56: 112 | O56: SE | P56: MIDDLE | Q56: ROAD 18M (BUILDINGS) | R56: =VLOOKUP(E56,'PREMIUM TABLES'!$F$214:$G$219,2,FALSE) -> SECOND | S56: {=IF(AND(L56>0,L56<90),"A",IF(AND(L56>90,L56<123),"B",IF(AND(L56>122,L56<159),"C",IF(AND(L56>159,L56<185),"D",IF(AND(L56>185,L56<230),"E",IF(AND(L56>230,L56<350),"F",NONE))))))} -> B | T56: =VLOOKUP(O56,'PREMIUM TABLES'!$G$165:$H$172,2,FALSE) -> 0.08 | U56: =VLOOKUP(P56,'PREMIUM TABLES'!$G$208:$H$209,2,FALSE) -> 0.025 | V56: =VLOOKUP(Q56,'PREMIUM TABLES'!$G$175:$H$195,2,FALSE) -> 0.15 | W56: =VLOOKUP(R56,'PREMIUM TABLES'!$G$214:$H$219,2,FALSE) -> 0.11 | X56: =VLOOKUP(S56,'PREMIUM TABLES'!$F$199:$H$205,3,FALSE) -> 0.04 | Y56: =SUM(T56:X56) -> 0.405 | Z56: {=IF(AND(Y56>0,Y56<0.5),"C",IF(AND(Y56>=0.5,Y56<0.73),"B",IF(AND(Y56>=0.73,Y56<0.98),"A",NONE)))} -> C | AA56: =VLOOKUP(G56,'ALL (R)'!$N$5:$R$862,5,FALSE) -> R 5 | AB56: =VLOOKUP(AA56,FACTS!$B$2:$L$14,10,FALSE) -> 46750 | AC56: =VLOOKUP(AA56,FACTS!$B$2:$L$14,11,FALSE) -> 52250 | AD56: =VLOOKUP(AA56,FACTS!$B$2:$N$14,13,FALSE) -> 5500 | AE56: =AD56*Y56 -> 2227.5 | AF56: =AE56+AB56 -> 48977.5 | AG56: =AF56*FACTS!$T$2 -> 16162.575 | AH56: =Table1[[#This Row],[UNIT (BUILDING) RATE (SEMI FINISHED)]]+4500 -> 53477.5 | AI56: =Table1[[#This Row],[UNIT (BUILDING) RATE (SEMI FINISHED)]]+7500 -> 56477.5 | AJ56: =AF56*L56 -> 5485480 | AK56: =Table1[[#This Row],[UNIT (BUILDING) RATE (BASIC FINISH)]]*Table1[[#This Row],[Unit Selling Area]] -> 5989480 | AL56: =Table1[[#This Row],[UNIT (BUILDING) RATE (FULLY FINISH)]]*Table1[[#This Row],[Unit Selling Area]] -> 6325480 | AM56: =AG56*M56 -> 0 | AN56: =(AM56+AJ56)*FACTS!$S$2 -> 466265.8 | AO56: =VLOOKUP(S56,FACTS!$A$17:$C$23,3,FALSE) -> 1 | AP56: =VLOOKUP(AA56,FACTS!$B$2:$J$14,9,FALSE) -> 220000 | AQ56: =Table1[[#This Row],[PARKING VALUE]]*1 -> 220000 | AR56: =AQ56+AM56+AJ56 -> 5705480 | AS56: =Table1[[#This Row],[TOTAL CARS VALUE]]+Table1[[#This Row],[UNIT (BUILDING) VALUE BASIC FINISHED]]+Table1[[#This Row],[UNIT (GARDEN) VALUE]] -> 6209480 | AT56: =Table1[[#This Row],[TOTAL CARS VALUE]]+Table1[[#This Row],[UNIT (GARDEN) VALUE]]+Table1[[#This Row],[UNIT (BUILDING) VALUE FULLY FINISHED]] -> 6545480 | AU56: =VLOOKUP(I56,'C PHASES'!$I$108:$J$110,2,FALSE) -> 45839 | AV56: =VLOOKUP(AA56,'C PHASES'!$I$113:$J$125,2,FALSE) -> 45566
B57: =LEFT(C57,1) -> A | C57: A3 | D57: RESIDENTIAL | E57: 3 | F57: 1 | G57: =LEFT(C57,2)&E57&F57 -> A331 | H57: 2 BEDROOM | I57: =VLOOKUP(C57,'PREMIUM TABLES'!$G$107:$H$149,2,FALSE) -> C1 | J57: 97.09 | K57: 106.42835 | L57: 119 | O57: SE | P57: MIDDLE | Q57: ROAD 18M (BUILDINGS) | R57: =VLOOKUP(E57,'PREMIUM TABLES'!$F$214:$G$219,2,FALSE) -> THIRD | S57: {=IF(AND(L57>0,L57<90),"A",IF(AND(L57>90,L57<123),"B",IF(AND(L57>122,L57<159),"C",IF(AND(L57>159,L57<185),"D",IF(AND(L57>185,L57<230),"E",IF(AND(L57>230,L57<350),"F",NONE))))))} -> B | T57: =VLOOKUP(O57,'PREMIUM TABLES'!$G$165:$H$172,2,FALSE) -> 0.08 | U57: =VLOOKUP(P57,'PREMIUM TABLES'!$G$208:$H$209,2,FALSE) -> 0.025 | V57: =VLOOKUP(Q57,'PREMIUM TABLES'!$G$175:$H$195,2,FALSE) -> 0.15 | W57: =VLOOKUP(R57,'PREMIUM TABLES'!$G$214:$H$219,2,FALSE) -> 0.15 | X57: =VLOOKUP(S57,'PREMIUM TABLES'!$F$199:$H$205,3,FALSE) -> 0.04 | Y57: =SUM(T57:X57) -> 0.445 | Z57: {=IF(AND(Y57>0,Y57<0.5),"C",IF(AND(Y57>=0.5,Y57<0.73),"B",IF(AND(Y57>=0.73,Y57<0.98),"A",NONE)))} -> C | AA57: =VLOOKUP(G57,'ALL (R)'!$N$5:$R$862,5,FALSE) -> R 9 | AB57: =VLOOKUP(AA57,FACTS!$B$2:$L$14,10,FALSE) -> 53550 | AC57: =VLOOKUP(AA57,FACTS!$B$2:$L$14,11,FALSE) -> 59850 | AD57: =VLOOKUP(AA57,FACTS!$B$2:$N$14,13,FALSE) -> 6300 | AE57: =AD57*Y57 -> 2803.5 | AF57: =AE57+AB57 -> 56353.5 | AG57: =AF57*FACTS!$T$2 -> 18596.655 | AH57: =Table1[[#This Row],[UNIT (BUILDING) RATE (SEMI FINISHED)]]+4500 -> 60853.5 | AI57: =Table1[[#This Row],[UNIT (BUILDING) RATE (SEMI FINISHED)]]+7500 -> 63853.5 | AJ57: =AF57*L57 -> 6706066.5 | AK57: =Table1[[#This Row],[UNIT (BUILDING) RATE (BASIC FINISH)]]*Table1[[#This Row],[Unit Selling Area]] -> 7241566.5 | AL57: =Table1[[#This Row],[UNIT (BUILDING) RATE (FULLY FINISH)]]*Table1[[#This Row],[Unit Selling Area]] -> 7598566.5 | AM57: =AG57*M57 -> 0 | AN57: =(AM57+AJ57)*FACTS!$S$2 -> 570015.65 | AO57: =VLOOKUP(S57,FACTS!$A$17:$C$23,3,FALSE) -> 1 | AP57: =VLOOKUP(AA57,FACTS!$B$2:$J$14,9,FALSE) -> 252000 | AQ57: =Table1[[#This Row],[PARKING VALUE]]*1 -> 252000 | AR57: =AQ57+AM57+AJ57 -> 6958066.5 | AS57: =Table1[[#This Row],[TOTAL CARS VALUE]]+Table1[[#This Row],[UNIT (BUILDING) VALUE BASIC FINISHED]]+Table1[[#This Row],[UNIT (GARDEN) VALUE]] -> 7493566.5 | AT57: =Table1[[#This Row],[TOTAL CARS VALUE]]+Table1[[#This Row],[UNIT (GARDEN) VALUE]]+Table1[[#This Row],[UNIT (BUILDING) VALUE FULLY FINISHED]] -> 7850566.5 | AU57: =VLOOKUP(I57,'C PHASES'!$I$108:$J$110,2,FALSE) -> 45839 | AV57: =VLOOKUP(AA57,'C PHASES'!$I$113:$J$125,2,FALSE) -> 45931
B58: =LEFT(C58,1) -> A | C58: A3 | D58: RESIDENTIAL | E58: 3 | F58: 2 | G58: =LEFT(C58,2)&E58&F58 -> A332 | H58: 2 BEDROOM | I58: =VLOOKUP(C58,'PREMIUM TABLES'!$G$107:$H$149,2,FALSE) -> C1 | J58: 97.09 | K58: 106.42835 | L58: 119 | O58: NW | P58: MIDDLE | Q58: SEMI LAKE AND FENCE | R58: =VLOOKUP(E58,'PREMIUM TABLES'!$F$214:$G$219,2,FALSE) -> THIRD | S58: {=IF(AND(L58>0,L58<90),"A",IF(AND(L58>90,L58<123),"B",IF(AND(L58>122,L58<159),"C",IF(AND(L58>159,L58<185),"D",IF(AND(L58>185,L58<230),"E",IF(AND(L58>230,L58<350),"F",NONE))))))} -> B | T58: =VLOOKUP(O58,'PREMIUM TABLES'!$G$165:$H$172,2,FALSE) -> 0.13 | U58: =VLOOKUP(P58,'PREMIUM TABLES'!$G$208:$H$209,2,FALSE) -> 0.025 | V58: =VLOOKUP(Q58,'PREMIUM TABLES'!$G$175:$H$195,2,FALSE) -> 0.25 | W58: =VLOOKUP(R58,'PREMIUM TABLES'!$G$214:$H$219,2,FALSE) -> 0.15 | X58: =VLOOKUP(S58,'PREMIUM TABLES'!$F$199:$H$205,3,FALSE) -> 0.04 | Y58: =SUM(T58:X58) -> 0.595 | Z58: {=IF(AND(Y58>0,Y58<0.5),"C",IF(AND(Y58>=0.5,Y58<0.73),"B",IF(AND(Y58>=0.73,Y58<0.98),"A",NONE)))} -> B | AA58: =VLOOKUP(G58,'ALL (R)'!$N$5:$R$862,5,FALSE) -> R 2 | AB58: =VLOOKUP(AA58,FACTS!$B$2:$L$14,10,FALSE) -> 43562.5 | AC58: =VLOOKUP(AA58,FACTS!$B$2:$L$14,11,FALSE) -> 48687.5 | AD58: =VLOOKUP(AA58,FACTS!$B$2:$N$14,13,FALSE) -> 5125 | AE58: =AD58*Y58 -> 3049.375 | AF58: =AE58+AB58 -> 46611.875 | AG58: =AF58*FACTS!$T$2 -> 15381.919 | AH58: =Table1[[#This Row],[UNIT (BUILDING) RATE (SEMI FINISHED)]]+4500 -> 51111.875 | AI58: =Table1[[#This Row],[UNIT (BUILDING) RATE (SEMI FINISHED)]]+7500 -> 54111.875 | AJ58: =AF58*L58 -> 5546813.1 | AK58: =Table1[[#This Row],[UNIT (BUILDING) RATE (BASIC FINISH)]]*Table1[[#This Row],[Unit Selling Area]] -> 6082313.1 | AL58: =Table1[[#This Row],[UNIT (BUILDING) RATE (FULLY FINISH)]]*Table1[[#This Row],[Unit Selling Area]] -> 6439313.1 | AM58: =AG58*M58 -> 0 | AN58: =(AM58+AJ58)*FACTS!$S$2 -> 471479.12 | AO58: =VLOOKUP(S58,FACTS!$A$17:$C$23,3,FALSE) -> 1 | AP58: =VLOOKUP(AA58,FACTS!$B$2:$J$14,9,FALSE) -> 205000 | AQ58: =Table1[[#This Row],[PARKING VALUE]]*1 -> 205000 | AR58: =AQ58+AM58+AJ58 -> 5751813.1 | AS58: =Table1[[#This Row],[TOTAL CARS VALUE]]+Table1[[#This Row],[UNIT (BUILDING) VALUE BASIC FINISHED]]+Table1[[#This Row],[UNIT (GARDEN) VALUE]] -> 6287313.1 | AT58: =Table1[[#This Row],[TOTAL CARS VALUE]]+Table1[[#This Row],[UNIT (GARDEN) VALUE]]+Table1[[#This Row],[UNIT (BUILDING) VALUE FULLY FINISHED]] -> 6644313.1 | AU58: =VLOOKUP(I58,'C PHASES'!$I$108:$J$110,2,FALSE) -> 45839 | AV58: =VLOOKUP(AA58,'C PHASES'!$I$113:$J$125,2,FALSE) -> 45292
B59: =LEFT(C59,1) -> A | C59: A3 | D59: RESIDENTIAL | E59: 3 | F59: 3 | G59: =LEFT(C59,2)&E59&F59 -> A333 | H59: 2 BEDROOM | I59: =VLOOKUP(C59,'PREMIUM TABLES'!$G$107:$H$149,2,FALSE) -> C1 | J59: 89.05 | K59: 97.615041 | L59: 110 | O59: NW | P59: MIDDLE | Q59: LAYAN VILLAS | R59: =VLOOKUP(E59,'PREMIUM TABLES'!$F$214:$G$219,2,FALSE) -> THIRD | S59: {=IF(AND(L59>0,L59<90),"A",IF(AND(L59>90,L59<123),"B",IF(AND(L59>122,L59<159),"C",IF(AND(L59>159,L59<185),"D",IF(AND(L59>185,L59<230),"E",IF(AND(L59>230,L59<350),"F",NONE))))))} -> B | T59: =VLOOKUP(O59,'PREMIUM TABLES'!$G$165:$H$172,2,FALSE) -> 0.13 | U59: =VLOOKUP(P59,'PREMIUM TABLES'!$G$208:$H$209,2,FALSE) -> 0.025 | V59: =VLOOKUP(Q59,'PREMIUM TABLES'!$G$175:$H$195,2,FALSE) -> 0.2 | W59: =VLOOKUP(R59,'PREMIUM TABLES'!$G$214:$H$219,2,FALSE) -> 0.15 | X59: =VLOOKUP(S59,'PREMIUM TABLES'!$F$199:$H$205,3,FALSE) -> 0.04 | Y59: =SUM(T59:X59) -> 0.545 | Z59: {=IF(AND(Y59>0,Y59<0.5),"C",IF(AND(Y59>=0.5,Y59<0.73),"B",IF(AND(Y59>=0.73,Y59<0.98),"A",NONE)))} -> B | AA59: =VLOOKUP(G59,'ALL (R)'!$N$5:$R$862,5,FALSE) -> R 1 | AB59: =VLOOKUP(AA59,FACTS!$B$2:$L$14,10,FALSE) -> 42500 | AC59: =VLOOKUP(AA59,FACTS!$B$2:$L$14,11,FALSE) -> 47500 | AD59: =VLOOKUP(AA59,FACTS!$B$2:$N$14,13,FALSE) -> 5000 | AE59: =AD59*Y59 -> 2725 | AF59: =AE59+AB59 -> 45225 | AG59: =AF59*FACTS!$T$2 -> 14924.25 | AH59: =Table1[[#This Row],[UNIT (BUILDING) RATE (SEMI FINISHED)]]+4500 -> 49725 | AI59: =Table1[[#This Row],[UNIT (BUILDING) RATE (SEMI FINISHED)]]+7500 -> 52725 | AJ59: =AF59*L59 -> 4974750 | AK59: =Table1[[#This Row],[UNIT (BUILDING) RATE (BASIC FINISH)]]*Table1[[#This Row],[Unit Selling Area]] -> 5469750 | AL59: =Table1[[#This Row],[UNIT (BUILDING) RATE (FULLY FINISH)]]*Table1[[#This Row],[Unit Selling Area]] -> 5799750 | AM59: =AG59*M59 -> 0 | AN59: =(AM59+AJ59)*FACTS!$S$2 -> 422853.75 | AO59: =VLOOKUP(S59,FACTS!$A$17:$C$23,3,FALSE) -> 1 | AP59: =VLOOKUP(AA59,FACTS!$B$2:$J$14,9,FALSE) -> 200000 | AQ59: =Table1[[#This Row],[PARKING VALUE]]*1 -> 200000 | AR59: =AQ59+AM59+AJ59 -> 5174750 | AS59: =Table1[[#This Row],[TOTAL CARS VALUE]]+Table1[[#This Row],[UNIT (BUILDING) VALUE BASIC FINISHED]]+Table1[[#This Row],[UNIT (GARDEN) VALUE]] -> 5669750 | AT59: =Table1[[#This Row],[TOTAL CARS VALUE]]+Table1[[#This Row],[UNIT (GARDEN) VALUE]]+Table1[[#This Row],[UNIT (BUILDING) VALUE FULLY FINISHED]] -> 5999750 | AU59: =VLOOKUP(I59,'C PHASES'!$I$108:$J$110,2,FALSE) -> 45839 | AV59: =VLOOKUP(AA59,'C PHASES'!$I$113:$J$125,2,FALSE) -> 45170
B60: =LEFT(C60,1) -> A | C60: A3 | D60: RESIDENTIAL | E60: 3 | F60: 4 | G60: =LEFT(C60,2)&E60&F60 -> A334 | H60: 2 BEDROOM | I60: =VLOOKUP(C60,'PREMIUM TABLES'!$G$107:$H$149,2,FALSE) -> C1 | J60: 89.05 | K60: 97.615041 | L60: 110 | O60: SE | P60: MIDDLE | Q60: ROAD 18M (BUILDINGS) | R60: =VLOOKUP(E60,'PREMIUM TABLES'!$F$214:$G$219,2,FALSE) -> THIRD | S60: {=IF(AND(L60>0,L60<90),"A",IF(AND(L60>90,L60<123),"B",IF(AND(L60>122,L60<159),"C",IF(AND(L60>159,L60<185),"D",IF(AND(L60>185,L60<230),"E",IF(AND(L60>230,L60<350),"F",NONE))))))} -> B | T60: =VLOOKUP(O60,'PREMIUM TABLES'!$G$165:$H$172,2,FALSE) -> 0.08 | U60: =VLOOKUP(P60,'PREMIUM TABLES'!$G$208:$H$209,2,FALSE) -> 0.025 | V60: =VLOOKUP(Q60,'PREMIUM TABLES'!$G$175:$H$195,2,FALSE) -> 0.15 | W60: =VLOOKUP(R60,'PREMIUM TABLES'!$G$214:$H$219,2,FALSE) -> 0.15 | X60: =VLOOKUP(S60,'PREMIUM TABLES'!$F$199:$H$205,3,FALSE) -> 0.04 | Y60: =SUM(T60:X60) -> 0.445 | Z60: {=IF(AND(Y60>0,Y60<0.5),"C",IF(AND(Y60>=0.5,Y60<0.73),"B",IF(AND(Y60>=0.73,Y60<0.98),"A",NONE)))} -> C | AA60: =VLOOKUP(G60,'ALL (R)'!$N$5:$R$862,5,FALSE) -> R 9 | AB60: =VLOOKUP(AA60,FACTS!$B$2:$L$14,10,FALSE) -> 53550 | AC60: =VLOOKUP(AA60,FACTS!$B$2:$L$14,11,FALSE) -> 59850 | AD60: =VLOOKUP(AA60,FACTS!$B$2:$N$14,13,FALSE) -> 6300 | AE60: =AD60*Y60 -> 2803.5 | AF60: =AE60+AB60 -> 56353.5 | AG60: =AF60*FACTS!$T$2 -> 18596.655 | AH60: =Table1[[#This Row],[UNIT (BUILDING) RATE (SEMI FINISHED)]]+4500 -> 60853.5 | AI60: =Table1[[#This Row],[UNIT (BUILDING) RATE (SEMI FINISHED)]]+7500 -> 63853.5 | AJ60: =AF60*L60 -> 6198885 | AK60: =Table1[[#This Row],[UNIT (BUILDING) RATE (BASIC FINISH)]]*Table1[[#This Row],[Unit Selling Area]] -> 6693885 | AL60: =Table1[[#This Row],[UNIT (BUILDING) RATE (FULLY FINISH)]]*Table1[[#This Row],[Unit Selling Area]] -> 7023885 | AM60: =AG60*M60 -> 0 | AN60: =(AM60+AJ60)*FACTS!$S$2 -> 526905.23 | AO60: =VLOOKUP(S60,FACTS!$A$17:$C$23,3,FALSE) -> 1 | AP60: =VLOOKUP(AA60,FACTS!$B$2:$J$14,9,FALSE) -> 252000 | AQ60: =Table1[[#This Row],[PARKING VALUE]]*1 -> 252000 | AR60: =AQ60+AM60+AJ60 -> 6450885 | AS60: =Table1[[#This Row],[TOTAL CARS VALUE]]+Table1[[#This Row],[UNIT (BUILDING) VALUE BASIC FINISHED]]+Table1[[#This Row],[UNIT (GARDEN) VALUE]] -> 6945885 | AT60: =Table1[[#This Row],[TOTAL CARS VALUE]]+Table1[[#This Row],[UNIT (GARDEN) VALUE]]+Table1[[#This Row],[UNIT (BUILDING) VALUE FULLY FINISHED]] -> 7275885 | AU60: =VLOOKUP(I60,'C PHASES'!$I$108:$J$110,2,FALSE) -> 45839 | AV60: =VLOOKUP(AA60,'C PHASES'!$I$113:$J$125,2,FALSE) -> 45931
... B64: =LEFT(C64,1) -> A | C64: A3 | D64: RESIDENTIAL | E64: 4 | F64: 4 | G64: =LEFT(C64,2)&E64&F64 -> A344 | H64: 2 BEDROOM | I64: =VLOOKUP(C64,'PREMIUM TABLES'!$G$107:$H$149,2,FALSE) -> C1 | J64: 89.12 | K64: 97.691774 | L64: 110 | O64: SE | P64: MIDDLE | Q64: ROAD 18M (BUILDINGS) | R64: =VLOOKUP(E64,'PREMIUM TABLES'!$F$214:$G$219,2,FALSE) -> FORTH | S64: {=IF(AND(L64>0,L64<90),"A",IF(AND(L64>90,L64<123),"B",IF(AND(L64>122,L64<159),"C",IF(AND(L64>159,L64<185),"D",IF(AND(L64>185,L64<230),"E",IF(AND(L64>230,L64<350),"F",NONE))))))} -> B | T64: =VLOOKUP(O64,'PREMIUM TABLES'!$G$165:$H$172,2,FALSE) -> 0.08 | U64: =VLOOKUP(P64,'PREMIUM TABLES'!$G$208:$H$209,2,FALSE) -> 0.025 | V64: =VLOOKUP(Q64,'PREMIUM TABLES'!$G$175:$H$195,2,FALSE) -> 0.15 | W64: =VLOOKUP(R64,'PREMIUM TABLES'!$G$214:$H$219,2,FALSE) -> 0.06 | X64: =VLOOKUP(S64,'PREMIUM TABLES'!$F$199:$H$205,3,FALSE) -> 0.04 | Y64: =SUM(T64:X64) -> 0.355 | Z64: {=IF(AND(Y64>0,Y64<0.5),"C",IF(AND(Y64>=0.5,Y64<0.73),"B",IF(AND(Y64>=0.73,Y64<0.98),"A",NONE)))} -> C | AA64: =VLOOKUP(G64,'ALL (R)'!$N$5:$R$862,5,FALSE) -> R 1 | AB64: =VLOOKUP(AA64,FACTS!$B$2:$L$14,10,FALSE) -> 42500 | AC64: =VLOOKUP(AA64,FACTS!$B$2:$L$14,11,FALSE) -> 47500 | AD64: =VLOOKUP(AA64,FACTS!$B$2:$N$14,13,FALSE) -> 5000 | AE64: =AD64*Y64 -> 1775 | AF64: =AE64+AB64 -> 44275 | AG64: =AF64*FACTS!$T$2 -> 14610.75 | AH64: =Table1[[#This Row],[UNIT (BUILDING) RATE (SEMI FINISHED)]]+4500 -> 48775 | AI64: =Table1[[#This Row],[UNIT (BUILDING) RATE (SEMI FINISHED)]]+7500 -> 51775 | AJ64: =AF64*L64 -> 4870250 | AK64: =Table1[[#This Row],[UNIT (BUILDING) RATE (BASIC FINISH)]]*Table1[[#This Row],[Unit Selling Area]] -> 5365250 | AL64: =Table1[[#This Row],[UNIT (BUILDING) RATE (FULLY FINISH)]]*Table1[[#This Row],[Unit Selling Area]] -> 5695250 | AM64: =AG64*M64 -> 0 | AN64: =(AM64+AJ64)*FACTS!$S$2 -> 413971.25 | AO64: =VLOOKUP(S64,FACTS!$A$17:$C$23,3,FALSE) -> 1 | AP64: =VLOOKUP(AA64,FACTS!$B$2:$J$14,9,FALSE) -> 200000 | AQ64: =Table1[[#This Row],[PARKING VALUE]]*1 -> 200000 | AR64: =AQ64+AM64+AJ64 -> 5070250 | AS64: =Table1[[#This Row],[TOTAL CARS VALUE]]+Table1[[#This Row],[UNIT (BUILDING) VALUE BASIC FINISHED]]+Table1[[#This Row],[UNIT (GARDEN) VALUE]] -> 5565250 | AT64: =Table1[[#This Row],[TOTAL CARS VALUE]]+Table1[[#This Row],[UNIT (GARDEN) VALUE]]+Table1[[#This Row],[UNIT (BUILDING) VALUE FULLY FINISHED]] -> 5895250 | AU64: =VLOOKUP(I64,'C PHASES'!$I$108:$J$110,2,FALSE) -> 45839 | AV64: =VLOOKUP(AA64,'C PHASES'!$I$113:$J$125,2,FALSE) -> 45170
A65: A | B65: =LEFT(C65,1) -> A | C65: A4 | D65: HOTEL APP. | E65: 0 | F65: 1 | G65: =LEFT(C65,2)&E65&F65 -> A401 | H65: 1 BEDROOM (STUDIO) | I65: =VLOOKUP(C65,'PREMIUM TABLES'!$G$107:$H$149,2,FALSE) -> C1 | J65: 63.79 | K65: 81.452738 | L65: 78 | M65: 24.6822 | O65: SE | P65: MIDDLE | Q65: ROAD 18M (BUILDINGS) | R65: =VLOOKUP(E65,'PREMIUM TABLES'!$F$214:$G$219,2,FALSE) -> GROUND | S65: {=IF(AND(L65>0,L65<90),"A",IF(AND(L65>90,L65<123),"B",IF(AND(L65>122,L65<159),"C",IF(AND(L65>159,L65<185),"D",IF(AND(L65>185,L65<230),"E",IF(AND(L65>230,L65<350),"F",NONE))))))} -> A | T65: =VLOOKUP(O65,'PREMIUM TABLES'!$G$165:$H$172,2,FALSE) -> 0.08 | U65: =VLOOKUP(P65,'PREMIUM TABLES'!$G$208:$H$209,2,FALSE) -> 0.025 | V65: =VLOOKUP(Q65,'PREMIUM TABLES'!$G$175:$H$195,2,FALSE) -> 0.15 | W65: =VLOOKUP(R65,'PREMIUM TABLES'!$G$214:$H$219,2,FALSE) -> 0.05 | X65: =VLOOKUP(S65,'PREMIUM TABLES'!$F$199:$H$205,3,FALSE) -> 0.05 | Y65: =SUM(T65:X65) -> 0.355 | Z65: HOTEL | AA65: =VLOOKUP(G65,'ALL (R)'!$N$5:$R$862,5,FALSE) -> RH | AB65: =VLOOKUP(AA65,FACTS!$B$2:$L$14,10,FALSE) -> 76850 | AC65: =VLOOKUP(AA65,FACTS!$B$2:$L$14,11,FALSE) -> 82950 | AD65: =VLOOKUP(AA65,FACTS!$B$2:$N$14,13,FALSE) -> 6100 | AE65: =AD65*Y65 -> 2165.5 | AF65: =AE65+AB65 -> 79015.5 | AG65: =AF65*FACTS!$T$2 -> 26075.115 | AH65: =Table1[[#This Row],[UNIT (BUILDING) RATE (SEMI FINISHED)]]+4500 -> 83515.5 | AI65: =Table1[[#This Row],[UNIT (BUILDING) RATE (SEMI FINISHED)]]+7500 -> 86515.5 | AJ65: =AF65*L65 -> 6163209 | AK65: =Table1[[#This Row],[UNIT (BUILDING) RATE (BASIC FINISH)]]*Table1[[#This Row],[Unit Selling Area]] -> 6514209 | AL65: =Table1[[#This Row],[UNIT (BUILDING) RATE (FULLY FINISH)]]*Table1[[#This Row],[Unit Selling Area]] -> 6748209 | AM65: =AG65*M65 -> 643591.2 | AN65: =(AM65+AJ65)*FACTS!$S$2 -> 578578.02 | AO65: =VLOOKUP(S65,FACTS!$A$17:$C$23,3,FALSE) -> 1 | AP65: =VLOOKUP(AA65,FACTS!$B$2:$J$14,9,FALSE) -> 244000 | AQ65: =Table1[[#This Row],[PARKING VALUE]]*1 -> 244000 | AR65: =AQ65+AM65+AJ65 -> 7050800.2 | AS65: =Table1[[#This Row],[TOTAL CARS VALUE]]+Table1[[#This Row],[UNIT (BUILDING) VALUE BASIC FINISHED]]+Table1[[#This Row],[UNIT (GARDEN) VALUE]] -> 7401800.2 | AT65: =Table1[[#This Row],[TOTAL CARS VALUE]]+Table1[[#This Row],[UNIT (GARDEN) VALUE]]+Table1[[#This Row],[UNIT (BUILDING) VALUE FULLY FINISHED]] -> 7635800.2 | AU65: =VLOOKUP(I65,'C PHASES'!$I$108:$J$110,2,FALSE) -> 45839 | AV65: =VLOOKUP(AA65,'C PHASES'!$I$113:$J$125,2,FALSE) -> 45839
